Workbook

Sheet Dashboard
A1: IDX VALUE SCREENER — DASHBOARD
A2: Every figure below is a live formula against the RAW_* sheets. Rebuild the workbook to refresh the membership of the ranked tables.
A4: DATA & UNIVERSE
A5: Last data refresh (Fetched At) | D5: =RAW_key_statistics!$EF$2
A6: Tickers in universe | D6: =COUNTA(Screener!$A$2:$A$957)
A7: Names at/above MOS Buy threshold | D7: =COUNTIF(Screener!$AC$2:$AC$957,">="&Setup!$B$9)
A8: Names at/above MOS Watch threshold | D8: =COUNTIF(Screener!$AC$2:$AC$957,">="&Setup!$B$10)
A10: VERDICT SPLIT | F10: MARKET CONTEXT (universe medians)
A11: Verdict | B11: Count | C11: % of universe | F11: Measure | G11: Value
A12: BUY | B12: =COUNTIF(Screener!$AI$2:$AI$957,"BUY") | C12: =IFERROR(B12/$D$6,"") | F12: Median PE (TTM) | G12: =IFERROR(MEDIAN(Screener!$G$2:$G$957),"")
A13: DEEP VALUE | B13: =COUNTIF(Screener!$AI$2:$AI$957,"DEEP VALUE") | C13: =IFERROR(B13/$D$6,"") | F13: Median PB | G13: =IFERROR(MEDIAN(Screener!$H$2:$H$957),"")
A14: WATCH | B14: =COUNTIF(Screener!$AI$2:$AI$957,"WATCH") | C14: =IFERROR(B14/$D$6,"") | F14: Median EV/EBIT | G14: =IFERROR(MEDIAN(Screener!$I$2:$I$957),"")
A15: SKIP | B15: =COUNTIF(Screener!$AI$2:$AI$957,"SKIP") | C15: =IFERROR(B15/$D$6,"") | F15: Names with F-Score >= 7 | G15: =COUNTIF(Screener!$Q$2:$Q$957,">=7")
F16: Names with Altman Z < 1.1 | G16: =COUNTIF(Screener!$R$2:$R$957,"<1.1")
F17: Median MOS (blended) | G17: =IFERROR(MEDIAN(Screener!$AC$2:$AC$957),"")
A20: TOP IDEAS — highest Composite Score among BUY / DEEP VALUE
A21: Membership fixed at build time (SORT/FILTER are not portable); all displayed figures are live INDEX/MATCH lookups.
A22: Rank | B22: Ticker | C22: Name | D22: Sector | E22: Business Type | F22: Price | G22: Blended IV | H22: MOS | I22: Composite | J22: Quality | K22: Safety | L22: Value | M22: F-Score | N22: Verdict
A23: 1 | B23: CASS | C23: =IFERROR(IF(ISBLANK(INDEX(Screener!$B$2:$B$957,MATCH($B23,Screener!$A$2:$A$957,0))),"",INDEX(Screener!$B$2:$B$957,MATCH($B23,Screener!$A$2:$A$957,0))),"") | D23: =IFERROR(IF(ISBLANK(INDEX(Screener!$C$2:$C$957,MATCH($B23,Screener!$A$2:$A$957,0))),"",INDEX(Screener!$C$2:$C$957,MATCH($B23,Screener!$A$2:$A$957,0))),"") | E23: =IFERROR(IF(ISBLANK(INDEX(Screener!$D$2:$D$957,MATCH($B23,Screener!$A$2:$A$957,0))),"",INDEX(Screener!$D$2:$D$957,MATCH($B23,Screener!$A$2:$A$957,0))),"") | F23: =IFERROR(IF(ISBLANK(INDEX(Screener!$E$2:$E$957,MATCH($B23,Screener!$A$2:$A$957,0))),"",INDEX(Screener!$E$2:$E$957,MATCH($B23,Screener!$A$2:$A$957,0))),"") | G23: =IFERROR(IF(ISBLANK(INDEX(Screener!$AB$2:$AB$957,MATCH($B23,Screener!$A$2:$A$957,0))),"",INDEX(Screener!$AB$2:$AB$957,MATCH($B23,Screener!$A$2:$A$957,0))),"") | H23: =IFERROR(IF(ISBLANK(INDEX(Screener!$AC$2:$AC$957,MATCH($B23,Screener!$A$2:$A$957,0))),"",INDEX(Screener!$AC$2:$AC$957,MATCH($B23,Screener!$A$2:$A$957,0))),"") | I23: =IFERROR(IF(ISBLANK(INDEX(Screener!$AH$2:$AH$957,MATCH($B23,Screener!$A$2:$A$957,0))),"",INDEX(Screener!$AH$2:$AH$957,MATCH($B23,Screener!$A$2:$A$957,0))),"") | J23: =IFERROR(IF(ISBLANK(INDEX(Screener!$AE$2:$AE$957,MATCH($B23,Screener!$A$2:$A$957,0))),"",INDEX(Screener!$AE$2:$AE$957,MATCH($B23,Screener!$A$2:$A$957,0))),"") | K23: =IFERROR(IF(ISBLANK(INDEX(Screener!$AF$2:$AF$957,MATCH($B23,Screener!$A$2:$A$957,0))),"",INDEX(Screener!$AF$2:$AF$957,MATCH($B23,Screener!$A$2:$A$957,0))),"") | L23: =IFERROR(IF(ISBLANK(INDEX(Screener!$AG$2:$AG$957,MATCH($B23,Screener!$A$2:$A$957,0))),"",INDEX(Screener!$AG$2:$AG$957,MATCH($B23,Screener!$A$2:$A$957,0))),"") | M23: =IFERROR(IF(ISBLANK(INDEX(Screener!$Q$2:$Q$957,MATCH($B23,Screener!$A$2:$A$957,0))),"",INDEX(Screener!$Q$2:$Q$957,MATCH($B23,Screener!$A$2:$A$957,0))),"") | N23: =IFERROR(IF(ISBLANK(INDEX(Screener!$AI$2:$AI$957,MATCH($B23,Screener!$A$2:$A$957,0))),"",INDEX(Screener!$AI$2:$AI$957,MATCH($B23,Screener!$A$2:$A$957,0))),"")
A24: 2 | B24: DMAS | C24: =IFERROR(IF(ISBLANK(INDEX(Screener!$B$2:$B$957,MATCH($B24,Screener!$A$2:$A$957,0))),"",INDEX(Screener!$B$2:$B$957,MATCH($B24,Screener!$A$2:$A$957,0))),"") | D24: =IFERROR(IF(ISBLANK(INDEX(Screener!$C$2:$C$957,MATCH($B24,Screener!$A$2:$A$957,0))),"",INDEX(Screener!$C$2:$C$957,MATCH($B24,Screener!$A$2:$A$957,0))),"") | E24: =IFERROR(IF(ISBLANK(INDEX(Screener!$D$2:$D$957,MATCH($B24,Screener!$A$2:$A$957,0))),"",INDEX(Screener!$D$2:$D$957,MATCH($B24,Screener!$A$2:$A$957,0))),"") | F24: =IFERROR(IF(ISBLANK(INDEX(Screener!$E$2:$E$957,MATCH($B24,Screener!$A$2:$A$957,0))),"",INDEX(Screener!$E$2:$E$957,MATCH($B24,Screener!$A$2:$A$957,0))),"") | G24: =IFERROR(IF(ISBLANK(INDEX(Screener!$AB$2:$AB$957,MATCH($B24,Screener!$A$2:$A$957,0))),"",INDEX(Screener!$AB$2:$AB$957,MATCH($B24,Screener!$A$2:$A$957,0))),"") | H24: =IFERROR(IF(ISBLANK(INDEX(Screener!$AC$2:$AC$957,MATCH($B24,Screener!$A$2:$A$957,0))),"",INDEX(Screener!$AC$2:$AC$957,MATCH($B24,Screener!$A$2:$A$957,0))),"") | I24: =IFERROR(IF(ISBLANK(INDEX(Screener!$AH$2:$AH$957,MATCH($B24,Screener!$A$2:$A$957,0))),"",INDEX(Screener!$AH$2:$AH$957,MATCH($B24,Screener!$A$2:$A$957,0))),"") | J24: =IFERROR(IF(ISBLANK(INDEX(Screener!$AE$2:$AE$957,MATCH($B24,Screener!$A$2:$A$957,0))),"",INDEX(Screener!$AE$2:$AE$957,MATCH($B24,Screener!$A$2:$A$957,0))),"") | K24: =IFERROR(IF(ISBLANK(INDEX(Screener!$AF$2:$AF$957,MATCH($B24,Screener!$A$2:$A$957,0))),"",INDEX(Screener!$AF$2:$AF$957,MATCH($B24,Screener!$A$2:$A$957,0))),"") | L24: =IFERROR(IF(ISBLANK(INDEX(Screener!$AG$2:$AG$957,MATCH($B24,Screener!$A$2:$A$957,0))),"",INDEX(Screener!$AG$2:$AG$957,MATCH($B24,Screener!$A$2:$A$957,0))),"") | M24: =IFERROR(IF(ISBLANK(INDEX(Screener!$Q$2:$Q$957,MATCH($B24,Screener!$A$2:$A$957,0))),"",INDEX(Screener!$Q$2:$Q$957,MATCH($B24,Screener!$A$2:$A$957,0))),"") | N24: =IFERROR(IF(ISBLANK(INDEX(Screener!$AI$2:$AI$957,MATCH($B24,Screener!$A$2:$A$957,0))),"",INDEX(Screener!$AI$2:$AI$957,MATCH($B24,Screener!$A$2:$A$957,0))),"")
A25: 3 | B25: MAPI | C25: =IFERROR(IF(ISBLANK(INDEX(Screener!$B$2:$B$957,MATCH($B25,Screener!$A$2:$A$957,0))),"",INDEX(Screener!$B$2:$B$957,MATCH($B25,Screener!$A$2:$A$957,0))),"") | D25: =IFERROR(IF(ISBLANK(INDEX(Screener!$C$2:$C$957,MATCH($B25,Screener!$A$2:$A$957,0))),"",INDEX(Screener!$C$2:$C$957,MATCH($B25,Screener!$A$2:$A$957,0))),"") | E25: =IFERROR(IF(ISBLANK(INDEX(Screener!$D$2:$D$957,MATCH($B25,Screener!$A$2:$A$957,0))),"",INDEX(Screener!$D$2:$D$957,MATCH($B25,Screener!$A$2:$A$957,0))),"") | F25: =IFERROR(IF(ISBLANK(INDEX(Screener!$E$2:$E$957,MATCH($B25,Screener!$A$2:$A$957,0))),"",INDEX(Screener!$E$2:$E$957,MATCH($B25,Screener!$A$2:$A$957,0))),"") | G25: =IFERROR(IF(ISBLANK(INDEX(Screener!$AB$2:$AB$957,MATCH($B25,Screener!$A$2:$A$957,0))),"",INDEX(Screener!$AB$2:$AB$957,MATCH($B25,Screener!$A$2:$A$957,0))),"") | H25: =IFERROR(IF(ISBLANK(INDEX(Screener!$AC$2:$AC$957,MATCH($B25,Screener!$A$2:$A$957,0))),"",INDEX(Screener!$AC$2:$AC$957,MATCH($B25,Screener!$A$2:$A$957,0))),"") | I25: =IFERROR(IF(ISBLANK(INDEX(Screener!$AH$2:$AH$957,MATCH($B25,Screener!$A$2:$A$957,0))),"",INDEX(Screener!$AH$2:$AH$957,MATCH($B25,Screener!$A$2:$A$957,0))),"") | J25: =IFERROR(IF(ISBLANK(INDEX(Screener!$AE$2:$AE$957,MATCH($B25,Screener!$A$2:$A$957,0))),"",INDEX(Screener!$AE$2:$AE$957,MATCH($B25,Screener!$A$2:$A$957,0))),"") | K25: =IFERROR(IF(ISBLANK(INDEX(Screener!$AF$2:$AF$957,MATCH($B25,Screener!$A$2:$A$957,0))),"",INDEX(Screener!$AF$2:$AF$957,MATCH($B25,Screener!$A$2:$A$957,0))),"") | L25: =IFERROR(IF(ISBLANK(INDEX(Screener!$AG$2:$AG$957,MATCH($B25,Screener!$A$2:$A$957,0))),"",INDEX(Screener!$AG$2:$AG$957,MATCH($B25,Screener!$A$2:$A$957,0))),"") | M25: =IFERROR(IF(ISBLANK(INDEX(Screener!$Q$2:$Q$957,MATCH($B25,Screener!$A$2:$A$957,0))),"",INDEX(Screener!$Q$2:$Q$957,MATCH($B25,Screener!$A$2:$A$957,0))),"") | N25: =IFERROR(IF(ISBLANK(INDEX(Screener!$AI$2:$AI$957,MATCH($B25,Screener!$A$2:$A$957,0))),"",INDEX(Screener!$AI$2:$AI$957,MATCH($B25,Screener!$A$2:$A$957,0))),"")
A26: 4 | B26: LSIP | C26: =IFERROR(IF(ISBLANK(INDEX(Screener!$B$2:$B$957,MATCH($B26,Screener!$A$2:$A$957,0))),"",INDEX(Screener!$B$2:$B$957,MATCH($B26,Screener!$A$2:$A$957,0))),"") | D26: =IFERROR(IF(ISBLANK(INDEX(Screener!$C$2:$C$957,MATCH($B26,Screener!$A$2:$A$957,0))),"",INDEX(Screener!$C$2:$C$957,MATCH($B26,Screener!$A$2:$A$957,0))),"") | E26: =IFERROR(IF(ISBLANK(INDEX(Screener!$D$2:$D$957,MATCH($B26,Screener!$A$2:$A$957,0))),"",INDEX(Screener!$D$2:$D$957,MATCH($B26,Screener!$A$2:$A$957,0))),"") | F26: =IFERROR(IF(ISBLANK(INDEX(Screener!$E$2:$E$957,MATCH($B26,Screener!$A$2:$A$957,0))),"",INDEX(Screener!$E$2:$E$957,MATCH($B26,Screener!$A$2:$A$957,0))),"") | G26: =IFERROR(IF(ISBLANK(INDEX(Screener!$AB$2:$AB$957,MATCH($B26,Screener!$A$2:$A$957,0))),"",INDEX(Screener!$AB$2:$AB$957,MATCH($B26,Screener!$A$2:$A$957,0))),"") | H26: =IFERROR(IF(ISBLANK(INDEX(Screener!$AC$2:$AC$957,MATCH($B26,Screener!$A$2:$A$957,0))),"",INDEX(Screener!$AC$2:$AC$957,MATCH($B26,Screener!$A$2:$A$957,0))),"") | I26: =IFERROR(IF(ISBLANK(INDEX(Screener!$AH$2:$AH$957,MATCH($B26,Screener!$A$2:$A$957,0))),"",INDEX(Screener!$AH$2:$AH$957,MATCH($B26,Screener!$A$2:$A$957,0))),"") | J26: =IFERROR(IF(ISBLANK(INDEX(Screener!$AE$2:$AE$957,MATCH($B26,Screener!$A$2:$A$957,0))),"",INDEX(Screener!$AE$2:$AE$957,MATCH($B26,Screener!$A$2:$A$957,0))),"") | K26: =IFERROR(IF(ISBLANK(INDEX(Screener!$AF$2:$AF$957,MATCH($B26,Screener!$A$2:$A$957,0))),"",INDEX(Screener!$AF$2:$AF$957,MATCH($B26,Screener!$A$2:$A$957,0))),"") | L26: =IFERROR(IF(ISBLANK(INDEX(Screener!$AG$2:$AG$957,MATCH($B26,Screener!$A$2:$A$957,0))),"",INDEX(Screener!$AG$2:$AG$957,MATCH($B26,Screener!$A$2:$A$957,0))),"") | M26: =IFERROR(IF(ISBLANK(INDEX(Screener!$Q$2:$Q$957,MATCH($B26,Screener!$A$2:$A$957,0))),"",INDEX(Screener!$Q$2:$Q$957,MATCH($B26,Screener!$A$2:$A$957,0))),"") | N26: =IFERROR(IF(ISBLANK(INDEX(Screener!$AI$2:$AI$957,MATCH($B26,Screener!$A$2:$A$957,0))),"",INDEX(Screener!$AI$2:$AI$957,MATCH($B26,Screener!$A$2:$A$957,0))),"")
A27: 5 | B27: CTRA | C27: =IFERROR(IF(ISBLANK(INDEX(Screener!$B$2:$B$957,MATCH($B27,Screener!$A$2:$A$957,0))),"",INDEX(Screener!$B$2:$B$957,MATCH($B27,Screener!$A$2:$A$957,0))),"") | D27: =IFERROR(IF(ISBLANK(INDEX(Screener!$C$2:$C$957,MATCH($B27,Screener!$A$2:$A$957,0))),"",INDEX(Screener!$C$2:$C$957,MATCH($B27,Screener!$A$2:$A$957,0))),"") | E27: =IFERROR(IF(ISBLANK(INDEX(Screener!$D$2:$D$957,MATCH($B27,Screener!$A$2:$A$957,0))),"",INDEX(Screener!$D$2:$D$957,MATCH($B27,Screener!$A$2:$A$957,0))),"") | F27: =IFERROR(IF(ISBLANK(INDEX(Screener!$E$2:$E$957,MATCH($B27,Screener!$A$2:$A$957,0))),"",INDEX(Screener!$E$2:$E$957,MATCH($B27,Screener!$A$2:$A$957,0))),"") | G27: =IFERROR(IF(ISBLANK(INDEX(Screener!$AB$2:$AB$957,MATCH($B27,Screener!$A$2:$A$957,0))),"",INDEX(Screener!$AB$2:$AB$957,MATCH($B27,Screener!$A$2:$A$957,0))),"") | H27: =IFERROR(IF(ISBLANK(INDEX(Screener!$AC$2:$AC$957,MATCH($B27,Screener!$A$2:$A$957,0))),"",INDEX(Screener!$AC$2:$AC$957,MATCH($B27,Screener!$A$2:$A$957,0))),"") | I27: =IFERROR(IF(ISBLANK(INDEX(Screener!$AH$2:$AH$957,MATCH($B27,Screener!$A$2:$A$957,0))),"",INDEX(Screener!$AH$2:$AH$957,MATCH($B27,Screener!$A$2:$A$957,0))),"") | J27: =IFERROR(IF(ISBLANK(INDEX(Screener!$AE$2:$AE$957,MATCH($B27,Screener!$A$2:$A$957,0))),"",INDEX(Screener!$AE$2:$AE$957,MATCH($B27,Screener!$A$2:$A$957,0))),"") | K27: =IFERROR(IF(ISBLANK(INDEX(Screener!$AF$2:$AF$957,MATCH($B27,Screener!$A$2:$A$957,0))),"",INDEX(Screener!$AF$2:$AF$957,MATCH($B27,Screener!$A$2:$A$957,0))),"") | L27: =IFERROR(IF(ISBLANK(INDEX(Screener!$AG$2:$AG$957,MATCH($B27,Screener!$A$2:$A$957,0))),"",INDEX(Screener!$AG$2:$AG$957,MATCH($B27,Screener!$A$2:$A$957,0))),"") | M27: =IFERROR(IF(ISBLANK(INDEX(Screener!$Q$2:$Q$957,MATCH($B27,Screener!$A$2:$A$957,0))),"",INDEX(Screener!$Q$2:$Q$957,MATCH($B27,Screener!$A$2:$A$957,0))),"") | N27: =IFERROR(IF(ISBLANK(INDEX(Screener!$AI$2:$AI$957,MATCH($B27,Screener!$A$2:$A$957,0))),"",INDEX(Screener!$AI$2:$AI$957,MATCH($B27,Screener!$A$2:$A$957,0))),"")
A28: 6 | B28: PWON | C28: =IFERROR(IF(ISBLANK(INDEX(Screener!$B$2:$B$957,MATCH($B28,Screener!$A$2:$A$957,0))),"",INDEX(Screener!$B$2:$B$957,MATCH($B28,Screener!$A$2:$A$957,0))),"") | D28: =IFERROR(IF(ISBLANK(INDEX(Screener!$C$2:$C$957,MATCH($B28,Screener!$A$2:$A$957,0))),"",INDEX(Screener!$C$2:$C$957,MATCH($B28,Screener!$A$2:$A$957,0))),"") | E28: =IFERROR(IF(ISBLANK(INDEX(Screener!$D$2:$D$957,MATCH($B28,Screener!$A$2:$A$957,0))),"",INDEX(Screener!$D$2:$D$957,MATCH($B28,Screener!$A$2:$A$957,0))),"") | F28: =IFERROR(IF(ISBLANK(INDEX(Screener!$E$2:$E$957,MATCH($B28,Screener!$A$2:$A$957,0))),"",INDEX(Screener!$E$2:$E$957,MATCH($B28,Screener!$A$2:$A$957,0))),"") | G28: =IFERROR(IF(ISBLANK(INDEX(Screener!$AB$2:$AB$957,MATCH($B28,Screener!$A$2:$A$957,0))),"",INDEX(Screener!$AB$2:$AB$957,MATCH($B28,Screener!$A$2:$A$957,0))),"") | H28: =IFERROR(IF(ISBLANK(INDEX(Screener!$AC$2:$AC$957,MATCH($B28,Screener!$A$2:$A$957,0))),"",INDEX(Screener!$AC$2:$AC$957,MATCH($B28,Screener!$A$2:$A$957,0))),"") | I28: =IFERROR(IF(ISBLANK(INDEX(Screener!$AH$2:$AH$957,MATCH($B28,Screener!$A$2:$A$957,0))),"",INDEX(Screener!$AH$2:$AH$957,MATCH($B28,Screener!$A$2:$A$957,0))),"") | J28: =IFERROR(IF(ISBLANK(INDEX(Screener!$AE$2:$AE$957,MATCH($B28,Screener!$A$2:$A$957,0))),"",INDEX(Screener!$AE$2:$AE$957,MATCH($B28,Screener!$A$2:$A$957,0))),"") | K28: =IFERROR(IF(ISBLANK(INDEX(Screener!$AF$2:$AF$957,MATCH($B28,Screener!$A$2:$A$957,0))),"",INDEX(Screener!$AF$2:$AF$957,MATCH($B28,Screener!$A$2:$A$957,0))),"") | L28: =IFERROR(IF(ISBLANK(INDEX(Screener!$AG$2:$AG$957,MATCH($B28,Screener!$A$2:$A$957,0))),"",INDEX(Screener!$AG$2:$AG$957,MATCH($B28,Screener!$A$2:$A$957,0))),"") | M28: =IFERROR(IF(ISBLANK(INDEX(Screener!$Q$2:$Q$957,MATCH($B28,Screener!$A$2:$A$957,0))),"",INDEX(Screener!$Q$2:$Q$957,MATCH($B28,Screener!$A$2:$A$957,0))),"") | N28: =IFERROR(IF(ISBLANK(INDEX(Screener!$AI$2:$AI$957,MATCH($B28,Screener!$A$2:$A$957,0))),"",INDEX(Screener!$AI$2:$AI$957,MATCH($B28,Screener!$A$2:$A$957,0))),"")
A29: 7 | B29: MSTI | C29: =IFERROR(IF(ISBLANK(INDEX(Screener!$B$2:$B$957,MATCH($B29,Screener!$A$2:$A$957,0))),"",INDEX(Screener!$B$2:$B$957,MATCH($B29,Screener!$A$2:$A$957,0))),"") | D29: =IFERROR(IF(ISBLANK(INDEX(Screener!$C$2:$C$957,MATCH($B29,Screener!$A$2:$A$957,0))),"",INDEX(Screener!$C$2:$C$957,MATCH($B29,Screener!$A$2:$A$957,0))),"") | E29: =IFERROR(IF(ISBLANK(INDEX(Screener!$D$2:$D$957,MATCH($B29,Screener!$A$2:$A$957,0))),"",INDEX(Screener!$D$2:$D$957,MATCH($B29,Screener!$A$2:$A$957,0))),"") | F29: =IFERROR(IF(ISBLANK(INDEX(Screener!$E$2:$E$957,MATCH($B29,Screener!$A$2:$A$957,0))),"",INDEX(Screener!$E$2:$E$957,MATCH($B29,Screener!$A$2:$A$957,0))),"") | G29: =IFERROR(IF(ISBLANK(INDEX(Screener!$AB$2:$AB$957,MATCH($B29,Screener!$A$2:$A$957,0))),"",INDEX(Screener!$AB$2:$AB$957,MATCH($B29,Screener!$A$2:$A$957,0))),"") | H29: =IFERROR(IF(ISBLANK(INDEX(Screener!$AC$2:$AC$957,MATCH($B29,Screener!$A$2:$A$957,0))),"",INDEX(Screener!$AC$2:$AC$957,MATCH($B29,Screener!$A$2:$A$957,0))),"") | I29: =IFERROR(IF(ISBLANK(INDEX(Screener!$AH$2:$AH$957,MATCH($B29,Screener!$A$2:$A$957,0))),"",INDEX(Screener!$AH$2:$AH$957,MATCH($B29,Screener!$A$2:$A$957,0))),"") | J29: =IFERROR(IF(ISBLANK(INDEX(Screener!$AE$2:$AE$957,MATCH($B29,Screener!$A$2:$A$957,0))),"",INDEX(Screener!$AE$2:$AE$957,MATCH($B29,Screener!$A$2:$A$957,0))),"") | K29: =IFERROR(IF(ISBLANK(INDEX(Screener!$AF$2:$AF$957,MATCH($B29,Screener!$A$2:$A$957,0))),"",INDEX(Screener!$AF$2:$AF$957,MATCH($B29,Screener!$A$2:$A$957,0))),"") | L29: =IFERROR(IF(ISBLANK(INDEX(Screener!$AG$2:$AG$957,MATCH($B29,Screener!$A$2:$A$957,0))),"",INDEX(Screener!$AG$2:$AG$957,MATCH($B29,Screener!$A$2:$A$957,0))),"") | M29: =IFERROR(IF(ISBLANK(INDEX(Screener!$Q$2:$Q$957,MATCH($B29,Screener!$A$2:$A$957,0))),"",INDEX(Screener!$Q$2:$Q$957,MATCH($B29,Screener!$A$2:$A$957,0))),"") | N29: =IFERROR(IF(ISBLANK(INDEX(Screener!$AI$2:$AI$957,MATCH($B29,Screener!$A$2:$A$957,0))),"",INDEX(Screener!$AI$2:$AI$957,MATCH($B29,Screener!$A$2:$A$957,0))),"")
A30: 8 | B30: KIJA | C30: =IFERROR(IF(ISBLANK(INDEX(Screener!$B$2:$B$957,MATCH($B30,Screener!$A$2:$A$957,0))),"",INDEX(Screener!$B$2:$B$957,MATCH($B30,Screener!$A$2:$A$957,0))),"") | D30: =IFERROR(IF(ISBLANK(INDEX(Screener!$C$2:$C$957,MATCH($B30,Screener!$A$2:$A$957,0))),"",INDEX(Screener!$C$2:$C$957,MATCH($B30,Screener!$A$2:$A$957,0))),"") | E30: =IFERROR(IF(ISBLANK(INDEX(Screener!$D$2:$D$957,MATCH($B30,Screener!$A$2:$A$957,0))),"",INDEX(Screener!$D$2:$D$957,MATCH($B30,Screener!$A$2:$A$957,0))),"") | F30: =IFERROR(IF(ISBLANK(INDEX(Screener!$E$2:$E$957,MATCH($B30,Screener!$A$2:$A$957,0))),"",INDEX(Screener!$E$2:$E$957,MATCH($B30,Screener!$A$2:$A$957,0))),"") | G30: =IFERROR(IF(ISBLANK(INDEX(Screener!$AB$2:$AB$957,MATCH($B30,Screener!$A$2:$A$957,0))),"",INDEX(Screener!$AB$2:$AB$957,MATCH($B30,Screener!$A$2:$A$957,0))),"") | H30: =IFERROR(IF(ISBLANK(INDEX(Screener!$AC$2:$AC$957,MATCH($B30,Screener!$A$2:$A$957,0))),"",INDEX(Screener!$AC$2:$AC$957,MATCH($B30,Screener!$A$2:$A$957,0))),"") | I30: =IFERROR(IF(ISBLANK(INDEX(Screener!$AH$2:$AH$957,MATCH($B30,Screener!$A$2:$A$957,0))),"",INDEX(Screener!$AH$2:$AH$957,MATCH($B30,Screener!$A$2:$A$957,0))),"") | J30: =IFERROR(IF(ISBLANK(INDEX(Screener!$AE$2:$AE$957,MATCH($B30,Screener!$A$2:$A$957,0))),"",INDEX(Screener!$AE$2:$AE$957,MATCH($B30,Screener!$A$2:$A$957,0))),"") | K30: =IFERROR(IF(ISBLANK(INDEX(Screener!$AF$2:$AF$957,MATCH($B30,Screener!$A$2:$A$957,0))),"",INDEX(Screener!$AF$2:$AF$957,MATCH($B30,Screener!$A$2:$A$957,0))),"") | L30: =IFERROR(IF(ISBLANK(INDEX(Screener!$AG$2:$AG$957,MATCH($B30,Screener!$A$2:$A$957,0))),"",INDEX(Screener!$AG$2:$AG$957,MATCH($B30,Screener!$A$2:$A$957,0))),"") | M30: =IFERROR(IF(ISBLANK(INDEX(Screener!$Q$2:$Q$957,MATCH($B30,Screener!$A$2:$A$957,0))),"",INDEX(Screener!$Q$2:$Q$957,MATCH($B30,Screener!$A$2:$A$957,0))),"") | N30: =IFERROR(IF(ISBLANK(INDEX(Screener!$AI$2:$AI$957,MATCH($B30,Screener!$A$2:$A$957,0))),"",INDEX(Screener!$AI$2:$AI$957,MATCH($B30,Screener!$A$2:$A$957,0))),"")
A31: 9 | B31: MINE | C31: =IFERROR(IF(ISBLANK(INDEX(Screener!$B$2:$B$957,MATCH($B31,Screener!$A$2:$A$957,0))),"",INDEX(Screener!$B$2:$B$957,MATCH($B31,Screener!$A$2:$A$957,0))),"") | D31: =IFERROR(IF(ISBLANK(INDEX(Screener!$C$2:$C$957,MATCH($B31,Screener!$A$2:$A$957,0))),"",INDEX(Screener!$C$2:$C$957,MATCH($B31,Screener!$A$2:$A$957,0))),"") | E31: =IFERROR(IF(ISBLANK(INDEX(Screener!$D$2:$D$957,MATCH($B31,Screener!$A$2:$A$957,0))),"",INDEX(Screener!$D$2:$D$957,MATCH($B31,Screener!$A$2:$A$957,0))),"") | F31: =IFERROR(IF(ISBLANK(INDEX(Screener!$E$2:$E$957,MATCH($B31,Screener!$A$2:$A$957,0))),"",INDEX(Screener!$E$2:$E$957,MATCH($B31,Screener!$A$2:$A$957,0))),"") | G31: =IFERROR(IF(ISBLANK(INDEX(Screener!$AB$2:$AB$957,MATCH($B31,Screener!$A$2:$A$957,0))),"",INDEX(Screener!$AB$2:$AB$957,MATCH($B31,Screener!$A$2:$A$957,0))),"") | H31: =IFERROR(IF(ISBLANK(INDEX(Screener!$AC$2:$AC$957,MATCH($B31,Screener!$A$2:$A$957,0))),"",INDEX(Screener!$AC$2:$AC$957,MATCH($B31,Screener!$A$2:$A$957,0))),"") | I31: =IFERROR(IF(ISBLANK(INDEX(Screener!$AH$2:$AH$957,MATCH($B31,Screener!$A$2:$A$957,0))),"",INDEX(Screener!$AH$2:$AH$957,MATCH($B31,Screener!$A$2:$A$957,0))),"") | J31: =IFERROR(IF(ISBLANK(INDEX(Screener!$AE$2:$AE$957,MATCH($B31,Screener!$A$2:$A$957,0))),"",INDEX(Screener!$AE$2:$AE$957,MATCH($B31,Screener!$A$2:$A$957,0))),"") | K31: =IFERROR(IF(ISBLANK(INDEX(Screener!$AF$2:$AF$957,MATCH($B31,Screener!$A$2:$A$957,0))),"",INDEX(Screener!$AF$2:$AF$957,MATCH($B31,Screener!$A$2:$A$957,0))),"") | L31: =IFERROR(IF(ISBLANK(INDEX(Screener!$AG$2:$AG$957,MATCH($B31,Screener!$A$2:$A$957,0))),"",INDEX(Screener!$AG$2:$AG$957,MATCH($B31,Screener!$A$2:$A$957,0))),"") | M31: =IFERROR(IF(ISBLANK(INDEX(Screener!$Q$2:$Q$957,MATCH($B31,Screener!$A$2:$A$957,0))),"",INDEX(Screener!$Q$2:$Q$957,MATCH($B31,Screener!$A$2:$A$957,0))),"") | N31: =IFERROR(IF(ISBLANK(INDEX(Screener!$AI$2:$AI$957,MATCH($B31,Screener!$A$2:$A$957,0))),"",INDEX(Screener!$AI$2:$AI$957,MATCH($B31,Screener!$A$2:$A$957,0))),"")
A32: 10 | B32: PTSP | C32: =IFERROR(IF(ISBLANK(INDEX(Screener!$B$2:$B$957,MATCH($B32,Screener!$A$2:$A$957,0))),"",INDEX(Screener!$B$2:$B$957,MATCH($B32,Screener!$A$2:$A$957,0))),"") | D32: =IFERROR(IF(ISBLANK(INDEX(Screener!$C$2:$C$957,MATCH($B32,Screener!$A$2:$A$957,0))),"",INDEX(Screener!$C$2:$C$957,MATCH($B32,Screener!$A$2:$A$957,0))),"") | E32: =IFERROR(IF(ISBLANK(INDEX(Screener!$D$2:$D$957,MATCH($B32,Screener!$A$2:$A$957,0))),"",INDEX(Screener!$D$2:$D$957,MATCH($B32,Screener!$A$2:$A$957,0))),"") | F32: =IFERROR(IF(ISBLANK(INDEX(Screener!$E$2:$E$957,MATCH($B32,Screener!$A$2:$A$957,0))),"",INDEX(Screener!$E$2:$E$957,MATCH($B32,Screener!$A$2:$A$957,0))),"") | G32: =IFERROR(IF(ISBLANK(INDEX(Screener!$AB$2:$AB$957,MATCH($B32,Screener!$A$2:$A$957,0))),"",INDEX(Screener!$AB$2:$AB$957,MATCH($B32,Screener!$A$2:$A$957,0))),"") | H32: =IFERROR(IF(ISBLANK(INDEX(Screener!$AC$2:$AC$957,MATCH($B32,Screener!$A$2:$A$957,0))),"",INDEX(Screener!$AC$2:$AC$957,MATCH($B32,Screener!$A$2:$A$957,0))),"") | I32: =IFERROR(IF(ISBLANK(INDEX(Screener!$AH$2:$AH$957,MATCH($B32,Screener!$A$2:$A$957,0))),"",INDEX(Screener!$AH$2:$AH$957,MATCH($B32,Screener!$A$2:$A$957,0))),"") | J32: =IFERROR(IF(ISBLANK(INDEX(Screener!$AE$2:$AE$957,MATCH($B32,Screener!$A$2:$A$957,0))),"",INDEX(Screener!$AE$2:$AE$957,MATCH($B32,Screener!$A$2:$A$957,0))),"") | K32: =IFERROR(IF(ISBLANK(INDEX(Screener!$AF$2:$AF$957,MATCH($B32,Screener!$A$2:$A$957,0))),"",INDEX(Screener!$AF$2:$AF$957,MATCH($B32,Screener!$A$2:$A$957,0))),"") | L32: =IFERROR(IF(ISBLANK(INDEX(Screener!$AG$2:$AG$957,MATCH($B32,Screener!$A$2:$A$957,0))),"",INDEX(Screener!$AG$2:$AG$957,MATCH($B32,Screener!$A$2:$A$957,0))),"") | M32: =IFERROR(IF(ISBLANK(INDEX(Screener!$Q$2:$Q$957,MATCH($B32,Screener!$A$2:$A$957,0))),"",INDEX(Screener!$Q$2:$Q$957,MATCH($B32,Screener!$A$2:$A$957,0))),"") | N32: =IFERROR(IF(ISBLANK(INDEX(Screener!$AI$2:$AI$957,MATCH($B32,Screener!$A$2:$A$957,0))),"",INDEX(Screener!$AI$2:$AI$957,MATCH($B32,Screener!$A$2:$A$957,0))),"")
A33: 11 | B33: DLTA | C33: =IFERROR(IF(ISBLANK(INDEX(Screener!$B$2:$B$957,MATCH($B33,Screener!$A$2:$A$957,0))),"",INDEX(Screener!$B$2:$B$957,MATCH($B33,Screener!$A$2:$A$957,0))),"") | D33: =IFERROR(IF(ISBLANK(INDEX(Screener!$C$2:$C$957,MATCH($B33,Screener!$A$2:$A$957,0))),"",INDEX(Screener!$C$2:$C$957,MATCH($B33,Screener!$A$2:$A$957,0))),"") | E33: =IFERROR(IF(ISBLANK(INDEX(Screener!$D$2:$D$957,MATCH($B33,Screener!$A$2:$A$957,0))),"",INDEX(Screener!$D$2:$D$957,MATCH($B33,Screener!$A$2:$A$957,0))),"") | F33: =IFERROR(IF(ISBLANK(INDEX(Screener!$E$2:$E$957,MATCH($B33,Screener!$A$2:$A$957,0))),"",INDEX(Screener!$E$2:$E$957,MATCH($B33,Screener!$A$2:$A$957,0))),"") | G33: =IFERROR(IF(ISBLANK(INDEX(Screener!$AB$2:$AB$957,MATCH($B33,Screener!$A$2:$A$957,0))),"",INDEX(Screener!$AB$2:$AB$957,MATCH($B33,Screener!$A$2:$A$957,0))),"") | H33: =IFERROR(IF(ISBLANK(INDEX(Screener!$AC$2:$AC$957,MATCH($B33,Screener!$A$2:$A$957,0))),"",INDEX(Screener!$AC$2:$AC$957,MATCH($B33,Screener!$A$2:$A$957,0))),"") | I33: =IFERROR(IF(ISBLANK(INDEX(Screener!$AH$2:$AH$957,MATCH($B33,Screener!$A$2:$A$957,0))),"",INDEX(Screener!$AH$2:$AH$957,MATCH($B33,Screener!$A$2:$A$957,0))),"") | J33: =IFERROR(IF(ISBLANK(INDEX(Screener!$AE$2:$AE$957,MATCH($B33,Screener!$A$2:$A$957,0))),"",INDEX(Screener!$AE$2:$AE$957,MATCH($B33,Screener!$A$2:$A$957,0))),"") | K33: =IFERROR(IF(ISBLANK(INDEX(Screener!$AF$2:$AF$957,MATCH($B33,Screener!$A$2:$A$957,0))),"",INDEX(Screener!$AF$2:$AF$957,MATCH($B33,Screener!$A$2:$A$957,0))),"") | L33: =IFERROR(IF(ISBLANK(INDEX(Screener!$AG$2:$AG$957,MATCH($B33,Screener!$A$2:$A$957,0))),"",INDEX(Screener!$AG$2:$AG$957,MATCH($B33,Screener!$A$2:$A$957,0))),"") | M33: =IFERROR(IF(ISBLANK(INDEX(Screener!$Q$2:$Q$957,MATCH($B33,Screener!$A$2:$A$957,0))),"",INDEX(Screener!$Q$2:$Q$957,MATCH($B33,Screener!$A$2:$A$957,0))),"") | N33: =IFERROR(IF(ISBLANK(INDEX(Screener!$AI$2:$AI$957,MATCH($B33,Screener!$A$2:$A$957,0))),"",INDEX(Screener!$AI$2:$AI$957,MATCH($B33,Screener!$A$2:$A$957,0))),"")
A34: 12 | B34: NISP | C34: =IFERROR(IF(ISBLANK(INDEX(Screener!$B$2:$B$957,MATCH($B34,Screener!$A$2:$A$957,0))),"",INDEX(Screener!$B$2:$B$957,MATCH($B34,Screener!$A$2:$A$957,0))),"") | D34: =IFERROR(IF(ISBLANK(INDEX(Screener!$C$2:$C$957,MATCH($B34,Screener!$A$2:$A$957,0))),"",INDEX(Screener!$C$2:$C$957,MATCH($B34,Screener!$A$2:$A$957,0))),"") | E34: =IFERROR(IF(ISBLANK(INDEX(Screener!$D$2:$D$957,MATCH($B34,Screener!$A$2:$A$957,0))),"",INDEX(Screener!$D$2:$D$957,MATCH($B34,Screener!$A$2:$A$957,0))),"") | F34: =IFERROR(IF(ISBLANK(INDEX(Screener!$E$2:$E$957,MATCH($B34,Screener!$A$2:$A$957,0))),"",INDEX(Screener!$E$2:$E$957,MATCH($B34,Screener!$A$2:$A$957,0))),"") | G34: =IFERROR(IF(ISBLANK(INDEX(Screener!$AB$2:$AB$957,MATCH($B34,Screener!$A$2:$A$957,0))),"",INDEX(Screener!$AB$2:$AB$957,MATCH($B34,Screener!$A$2:$A$957,0))),"") | H34: =IFERROR(IF(ISBLANK(INDEX(Screener!$AC$2:$AC$957,MATCH($B34,Screener!$A$2:$A$957,0))),"",INDEX(Screener!$AC$2:$AC$957,MATCH($B34,Screener!$A$2:$A$957,0))),"") | I34: =IFERROR(IF(ISBLANK(INDEX(Screener!$AH$2:$AH$957,MATCH($B34,Screener!$A$2:$A$957,0))),"",INDEX(Screener!$AH$2:$AH$957,MATCH($B34,Screener!$A$2:$A$957,0))),"") | J34: =IFERROR(IF(ISBLANK(INDEX(Screener!$AE$2:$AE$957,MATCH($B34,Screener!$A$2:$A$957,0))),"",INDEX(Screener!$AE$2:$AE$957,MATCH($B34,Screener!$A$2:$A$957,0))),"") | K34: =IFERROR(IF(ISBLANK(INDEX(Screener!$AF$2:$AF$957,MATCH($B34,Screener!$A$2:$A$957,0))),"",INDEX(Screener!$AF$2:$AF$957,MATCH($B34,Screener!$A$2:$A$957,0))),"") | L34: =IFERROR(IF(ISBLANK(INDEX(Screener!$AG$2:$AG$957,MATCH($B34,Screener!$A$2:$A$957,0))),"",INDEX(Screener!$AG$2:$AG$957,MATCH($B34,Screener!$A$2:$A$957,0))),"") | M34: =IFERROR(IF(ISBLANK(INDEX(Screener!$Q$2:$Q$957,MATCH($B34,Screener!$A$2:$A$957,0))),"",INDEX(Screener!$Q$2:$Q$957,MATCH($B34,Screener!$A$2:$A$957,0))),"") | N34: =IFERROR(IF(ISBLANK(INDEX(Screener!$AI$2:$AI$957,MATCH($B34,Screener!$A$2:$A$957,0))),"",INDEX(Screener!$AI$2:$AI$957,MATCH($B34,Screener!$A$2:$A$957,0))),"")
... A37: 15 | B37: ERAL | C37: =IFERROR(IF(ISBLANK(INDEX(Screener!$B$2:$B$957,MATCH($B37,Screener!$A$2:$A$957,0))),"",INDEX(Screener!$B$2:$B$957,MATCH($B37,Screener!$A$2:$A$957,0))),"") | D37: =IFERROR(IF(ISBLANK(INDEX(Screener!$C$2:$C$957,MATCH($B37,Screener!$A$2:$A$957,0))),"",INDEX(Screener!$C$2:$C$957,MATCH($B37,Screener!$A$2:$A$957,0))),"") | E37: =IFERROR(IF(ISBLANK(INDEX(Screener!$D$2:$D$957,MATCH($B37,Screener!$A$2:$A$957,0))),"",INDEX(Screener!$D$2:$D$957,MATCH($B37,Screener!$A$2:$A$957,0))),"") | F37: =IFERROR(IF(ISBLANK(INDEX(Screener!$E$2:$E$957,MATCH($B37,Screener!$A$2:$A$957,0))),"",INDEX(Screener!$E$2:$E$957,MATCH($B37,Screener!$A$2:$A$957,0))),"") | G37: =IFERROR(IF(ISBLANK(INDEX(Screener!$AB$2:$AB$957,MATCH($B37,Screener!$A$2:$A$957,0))),"",INDEX(Screener!$AB$2:$AB$957,MATCH($B37,Screener!$A$2:$A$957,0))),"") | H37: =IFERROR(IF(ISBLANK(INDEX(Screener!$AC$2:$AC$957,MATCH($B37,Screener!$A$2:$A$957,0))),"",INDEX(Screener!$AC$2:$AC$957,MATCH($B37,Screener!$A$2:$A$957,0))),"") | I37: =IFERROR(IF(ISBLANK(INDEX(Screener!$AH$2:$AH$957,MATCH($B37,Screener!$A$2:$A$957,0))),"",INDEX(Screener!$AH$2:$AH$957,MATCH($B37,Screener!$A$2:$A$957,0))),"") | J37: =IFERROR(IF(ISBLANK(INDEX(Screener!$AE$2:$AE$957,MATCH($B37,Screener!$A$2:$A$957,0))),"",INDEX(Screener!$AE$2:$AE$957,MATCH($B37,Screener!$A$2:$A$957,0))),"") | K37: =IFERROR(IF(ISBLANK(INDEX(Screener!$AF$2:$AF$957,MATCH($B37,Screener!$A$2:$A$957,0))),"",INDEX(Screener!$AF$2:$AF$957,MATCH($B37,Screener!$A$2:$A$957,0))),"") | L37: =IFERROR(IF(ISBLANK(INDEX(Screener!$AG$2:$AG$957,MATCH($B37,Screener!$A$2:$A$957,0))),"",INDEX(Screener!$AG$2:$AG$957,MATCH($B37,Screener!$A$2:$A$957,0))),"") | M37: =IFERROR(IF(ISBLANK(INDEX(Screener!$Q$2:$Q$957,MATCH($B37,Screener!$A$2:$A$957,0))),"",INDEX(Screener!$Q$2:$Q$957,MATCH($B37,Screener!$A$2:$A$957,0))),"") | N37: =IFERROR(IF(ISBLANK(INDEX(Screener!$AI$2:$AI$957,MATCH($B37,Screener!$A$2:$A$957,0))),"",INDEX(Screener!$AI$2:$AI$957,MATCH($B37,Screener!$A$2:$A$957,0))),"")
A39: CHEAPEST ON ACQUIRER'S MULTIPLE — lowest EV/EBIT, positive trailing EBIT only
A40: Rank | B40: Ticker | C40: Name | D40: Sector | E40: EV/EBIT | F40: Earnings Yield (EBIT/EV) | G40: ROC (Greenblatt) | H40: F-Score | I40: Altman Z | J40: Composite | K40: Verdict
A41: 1 | B41: CNKO | C41: =IFERROR(IF(ISBLANK(INDEX(Screener!$B$2:$B$957,MATCH($B41,Screener!$A$2:$A$957,0))),"",INDEX(Screener!$B$2:$B$957,MATCH($B41,Screener!$A$2:$A$957,0))),"") | D41: =IFERROR(IF(ISBLANK(INDEX(Screener!$C$2:$C$957,MATCH($B41,Screener!$A$2:$A$957,0))),"",INDEX(Screener!$C$2:$C$957,MATCH($B41,Screener!$A$2:$A$957,0))),"") | E41: =IFERROR(IF(ISBLANK(INDEX(Screener!$I$2:$I$957,MATCH($B41,Screener!$A$2:$A$957,0))),"",INDEX(Screener!$I$2:$I$957,MATCH($B41,Screener!$A$2:$A$957,0))),"") | F41: =IFERROR(IF(ISBLANK(INDEX(Screener!$O$2:$O$957,MATCH($B41,Screener!$A$2:$A$957,0))),"",INDEX(Screener!$O$2:$O$957,MATCH($B41,Screener!$A$2:$A$957,0))),"") | G41: =IFERROR(IF(ISBLANK(INDEX(Screener!$N$2:$N$957,MATCH($B41,Screener!$A$2:$A$957,0))),"",INDEX(Screener!$N$2:$N$957,MATCH($B41,Screener!$A$2:$A$957,0))),"") | H41: =IFERROR(IF(ISBLANK(INDEX(Screener!$Q$2:$Q$957,MATCH($B41,Screener!$A$2:$A$957,0))),"",INDEX(Screener!$Q$2:$Q$957,MATCH($B41,Screener!$A$2:$A$957,0))),"") | I41: =IFERROR(IF(ISBLANK(INDEX(Screener!$R$2:$R$957,MATCH($B41,Screener!$A$2:$A$957,0))),"",INDEX(Screener!$R$2:$R$957,MATCH($B41,Screener!$A$2:$A$957,0))),"") | J41: =IFERROR(IF(ISBLANK(INDEX(Screener!$AH$2:$AH$957,MATCH($B41,Screener!$A$2:$A$957,0))),"",INDEX(Screener!$AH$2:$AH$957,MATCH($B41,Screener!$A$2:$A$957,0))),"") | K41: =IFERROR(IF(ISBLANK(INDEX(Screener!$AI$2:$AI$957,MATCH($B41,Screener!$A$2:$A$957,0))),"",INDEX(Screener!$AI$2:$AI$957,MATCH($B41,Screener!$A$2:$A$957,0))),"")
A42: 2 | B42: LSIP | C42: =IFERROR(IF(ISBLANK(INDEX(Screener!$B$2:$B$957,MATCH($B42,Screener!$A$2:$A$957,0))),"",INDEX(Screener!$B$2:$B$957,MATCH($B42,Screener!$A$2:$A$957,0))),"") | D42: =IFERROR(IF(ISBLANK(INDEX(Screener!$C$2:$C$957,MATCH($B42,Screener!$A$2:$A$957,0))),"",INDEX(Screener!$C$2:$C$957,MATCH($B42,Screener!$A$2:$A$957,0))),"") | E42: =IFERROR(IF(ISBLANK(INDEX(Screener!$I$2:$I$957,MATCH($B42,Screener!$A$2:$A$957,0))),"",INDEX(Screener!$I$2:$I$957,MATCH($B42,Screener!$A$2:$A$957,0))),"") | F42: =IFERROR(IF(ISBLANK(INDEX(Screener!$O$2:$O$957,MATCH($B42,Screener!$A$2:$A$957,0))),"",INDEX(Screener!$O$2:$O$957,MATCH($B42,Screener!$A$2:$A$957,0))),"") | G42: =IFERROR(IF(ISBLANK(INDEX(Screener!$N$2:$N$957,MATCH($B42,Screener!$A$2:$A$957,0))),"",INDEX(Screener!$N$2:$N$957,MATCH($B42,Screener!$A$2:$A$957,0))),"") | H42: =IFERROR(IF(ISBLANK(INDEX(Screener!$Q$2:$Q$957,MATCH($B42,Screener!$A$2:$A$957,0))),"",INDEX(Screener!$Q$2:$Q$957,MATCH($B42,Screener!$A$2:$A$957,0))),"") | I42: =IFERROR(IF(ISBLANK(INDEX(Screener!$R$2:$R$957,MATCH($B42,Screener!$A$2:$A$957,0))),"",INDEX(Screener!$R$2:$R$957,MATCH($B42,Screener!$A$2:$A$957,0))),"") | J42: =IFERROR(IF(ISBLANK(INDEX(Screener!$AH$2:$AH$957,MATCH($B42,Screener!$A$2:$A$957,0))),"",INDEX(Screener!$AH$2:$AH$957,MATCH($B42,Screener!$A$2:$A$957,0))),"") | K42: =IFERROR(IF(ISBLANK(INDEX(Screener!$AI$2:$AI$957,MATCH($B42,Screener!$A$2:$A$957,0))),"",INDEX(Screener!$AI$2:$AI$957,MATCH($B42,Screener!$A$2:$A$957,0))),"")
A43: 3 | B43: RIGS | C43: =IFERROR(IF(ISBLANK(INDEX(Screener!$B$2:$B$957,MATCH($B43,Screener!$A$2:$A$957,0))),"",INDEX(Screener!$B$2:$B$957,MATCH($B43,Screener!$A$2:$A$957,0))),"") | D43: =IFERROR(IF(ISBLANK(INDEX(Screener!$C$2:$C$957,MATCH($B43,Screener!$A$2:$A$957,0))),"",INDEX(Screener!$C$2:$C$957,MATCH($B43,Screener!$A$2:$A$957,0))),"") | E43: =IFERROR(IF(ISBLANK(INDEX(Screener!$I$2:$I$957,MATCH($B43,Screener!$A$2:$A$957,0))),"",INDEX(Screener!$I$2:$I$957,MATCH($B43,Screener!$A$2:$A$957,0))),"") | F43: =IFERROR(IF(ISBLANK(INDEX(Screener!$O$2:$O$957,MATCH($B43,Screener!$A$2:$A$957,0))),"",INDEX(Screener!$O$2:$O$957,MATCH($B43,Screener!$A$2:$A$957,0))),"") | G43: =IFERROR(IF(ISBLANK(INDEX(Screener!$N$2:$N$957,MATCH($B43,Screener!$A$2:$A$957,0))),"",INDEX(Screener!$N$2:$N$957,MATCH($B43,Screener!$A$2:$A$957,0))),"") | H43: =IFERROR(IF(ISBLANK(INDEX(Screener!$Q$2:$Q$957,MATCH($B43,Screener!$A$2:$A$957,0))),"",INDEX(Screener!$Q$2:$Q$957,MATCH($B43,Screener!$A$2:$A$957,0))),"") | I43: =IFERROR(IF(ISBLANK(INDEX(Screener!$R$2:$R$957,MATCH($B43,Screener!$A$2:$A$957,0))),"",INDEX(Screener!$R$2:$R$957,MATCH($B43,Screener!$A$2:$A$957,0))),"") | J43: =IFERROR(IF(ISBLANK(INDEX(Screener!$AH$2:$AH$957,MATCH($B43,Screener!$A$2:$A$957,0))),"",INDEX(Screener!$AH$2:$AH$957,MATCH($B43,Screener!$A$2:$A$957,0))),"") | K43: =IFERROR(IF(ISBLANK(INDEX(Screener!$AI$2:$AI$957,MATCH($B43,Screener!$A$2:$A$957,0))),"",INDEX(Screener!$AI$2:$AI$957,MATCH($B43,Screener!$A$2:$A$957,0))),"")
A44: 4 | B44: SRTG | C44: =IFERROR(IF(ISBLANK(INDEX(Screener!$B$2:$B$957,MATCH($B44,Screener!$A$2:$A$957,0))),"",INDEX(Screener!$B$2:$B$957,MATCH($B44,Screener!$A$2:$A$957,0))),"") | D44: =IFERROR(IF(ISBLANK(INDEX(Screener!$C$2:$C$957,MATCH($B44,Screener!$A$2:$A$957,0))),"",INDEX(Screener!$C$2:$C$957,MATCH($B44,Screener!$A$2:$A$957,0))),"") | E44: =IFERROR(IF(ISBLANK(INDEX(Screener!$I$2:$I$957,MATCH($B44,Screener!$A$2:$A$957,0))),"",INDEX(Screener!$I$2:$I$957,MATCH($B44,Screener!$A$2:$A$957,0))),"") | F44: =IFERROR(IF(ISBLANK(INDEX(Screener!$O$2:$O$957,MATCH($B44,Screener!$A$2:$A$957,0))),"",INDEX(Screener!$O$2:$O$957,MATCH($B44,Screener!$A$2:$A$957,0))),"") | G44: =IFERROR(IF(ISBLANK(INDEX(Screener!$N$2:$N$957,MATCH($B44,Screener!$A$2:$A$957,0))),"",INDEX(Screener!$N$2:$N$957,MATCH($B44,Screener!$A$2:$A$957,0))),"") | H44: =IFERROR(IF(ISBLANK(INDEX(Screener!$Q$2:$Q$957,MATCH($B44,Screener!$A$2:$A$957,0))),"",INDEX(Screener!$Q$2:$Q$957,MATCH($B44,Screener!$A$2:$A$957,0))),"") | I44: =IFERROR(IF(ISBLANK(INDEX(Screener!$R$2:$R$957,MATCH($B44,Screener!$A$2:$A$957,0))),"",INDEX(Screener!$R$2:$R$957,MATCH($B44,Screener!$A$2:$A$957,0))),"") | J44: =IFERROR(IF(ISBLANK(INDEX(Screener!$AH$2:$AH$957,MATCH($B44,Screener!$A$2:$A$957,0))),"",INDEX(Screener!$AH$2:$AH$957,MATCH($B44,Screener!$A$2:$A$957,0))),"") | K44: =IFERROR(IF(ISBLANK(INDEX(Screener!$AI$2:$AI$957,MATCH($B44,Screener!$A$2:$A$957,0))),"",INDEX(Screener!$AI$2:$AI$957,MATCH($B44,Screener!$A$2:$A$957,0))),"")
A45: 5 | B45: TPIA | C45: =IFERROR(IF(ISBLANK(INDEX(Screener!$B$2:$B$957,MATCH($B45,Screener!$A$2:$A$957,0))),"",INDEX(Screener!$B$2:$B$957,MATCH($B45,Screener!$A$2:$A$957,0))),"") | D45: =IFERROR(IF(ISBLANK(INDEX(Screener!$C$2:$C$957,MATCH($B45,Screener!$A$2:$A$957,0))),"",INDEX(Screener!$C$2:$C$957,MATCH($B45,Screener!$A$2:$A$957,0))),"") | E45: =IFERROR(IF(ISBLANK(INDEX(Screener!$I$2:$I$957,MATCH($B45,Screener!$A$2:$A$957,0))),"",INDEX(Screener!$I$2:$I$957,MATCH($B45,Screener!$A$2:$A$957,0))),"") | F45: =IFERROR(IF(ISBLANK(INDEX(Screener!$O$2:$O$957,MATCH($B45,Screener!$A$2:$A$957,0))),"",INDEX(Screener!$O$2:$O$957,MATCH($B45,Screener!$A$2:$A$957,0))),"") | G45: =IFERROR(IF(ISBLANK(INDEX(Screener!$N$2:$N$957,MATCH($B45,Screener!$A$2:$A$957,0))),"",INDEX(Screener!$N$2:$N$957,MATCH($B45,Screener!$A$2:$A$957,0))),"") | H45: =IFERROR(IF(ISBLANK(INDEX(Screener!$Q$2:$Q$957,MATCH($B45,Screener!$A$2:$A$957,0))),"",INDEX(Screener!$Q$2:$Q$957,MATCH($B45,Screener!$A$2:$A$957,0))),"") | I45: =IFERROR(IF(ISBLANK(INDEX(Screener!$R$2:$R$957,MATCH($B45,Screener!$A$2:$A$957,0))),"",INDEX(Screener!$R$2:$R$957,MATCH($B45,Screener!$A$2:$A$957,0))),"") | J45: =IFERROR(IF(ISBLANK(INDEX(Screener!$AH$2:$AH$957,MATCH($B45,Screener!$A$2:$A$957,0))),"",INDEX(Screener!$AH$2:$AH$957,MATCH($B45,Screener!$A$2:$A$957,0))),"") | K45: =IFERROR(IF(ISBLANK(INDEX(Screener!$AI$2:$AI$957,MATCH($B45,Screener!$A$2:$A$957,0))),"",INDEX(Screener!$AI$2:$AI$957,MATCH($B45,Screener!$A$2:$A$957,0))),"")
A46: 6 | B46: IGAR | C46: =IFERROR(IF(ISBLANK(INDEX(Screener!$B$2:$B$957,MATCH($B46,Screener!$A$2:$A$957,0))),"",INDEX(Screener!$B$2:$B$957,MATCH($B46,Screener!$A$2:$A$957,0))),"") | D46: =IFERROR(IF(ISBLANK(INDEX(Screener!$C$2:$C$957,MATCH($B46,Screener!$A$2:$A$957,0))),"",INDEX(Screener!$C$2:$C$957,MATCH($B46,Screener!$A$2:$A$957,0))),"") | E46: =IFERROR(IF(ISBLANK(INDEX(Screener!$I$2:$I$957,MATCH($B46,Screener!$A$2:$A$957,0))),"",INDEX(Screener!$I$2:$I$957,MATCH($B46,Screener!$A$2:$A$957,0))),"") | F46: =IFERROR(IF(ISBLANK(INDEX(Screener!$O$2:$O$957,MATCH($B46,Screener!$A$2:$A$957,0))),"",INDEX(Screener!$O$2:$O$957,MATCH($B46,Screener!$A$2:$A$957,0))),"") | G46: =IFERROR(IF(ISBLANK(INDEX(Screener!$N$2:$N$957,MATCH($B46,Screener!$A$2:$A$957,0))),"",INDEX(Screener!$N$2:$N$957,MATCH($B46,Screener!$A$2:$A$957,0))),"") | H46: =IFERROR(IF(ISBLANK(INDEX(Screener!$Q$2:$Q$957,MATCH($B46,Screener!$A$2:$A$957,0))),"",INDEX(Screener!$Q$2:$Q$957,MATCH($B46,Screener!$A$2:$A$957,0))),"") | I46: =IFERROR(IF(ISBLANK(INDEX(Screener!$R$2:$R$957,MATCH($B46,Screener!$A$2:$A$957,0))),"",INDEX(Screener!$R$2:$R$957,MATCH($B46,Screener!$A$2:$A$957,0))),"") | J46: =IFERROR(IF(ISBLANK(INDEX(Screener!$AH$2:$AH$957,MATCH($B46,Screener!$A$2:$A$957,0))),"",INDEX(Screener!$AH$2:$AH$957,MATCH($B46,Screener!$A$2:$A$957,0))),"") | K46: =IFERROR(IF(ISBLANK(INDEX(Screener!$AI$2:$AI$957,MATCH($B46,Screener!$A$2:$A$957,0))),"",INDEX(Screener!$AI$2:$AI$957,MATCH($B46,Screener!$A$2:$A$957,0))),"")
A47: 7 | B47: SCCO | C47: =IFERROR(IF(ISBLANK(INDEX(Screener!$B$2:$B$957,MATCH($B47,Screener!$A$2:$A$957,0))),"",INDEX(Screener!$B$2:$B$957,MATCH($B47,Screener!$A$2:$A$957,0))),"") | D47: =IFERROR(IF(ISBLANK(INDEX(Screener!$C$2:$C$957,MATCH($B47,Screener!$A$2:$A$957,0))),"",INDEX(Screener!$C$2:$C$957,MATCH($B47,Screener!$A$2:$A$957,0))),"") | E47: =IFERROR(IF(ISBLANK(INDEX(Screener!$I$2:$I$957,MATCH($B47,Screener!$A$2:$A$957,0))),"",INDEX(Screener!$I$2:$I$957,MATCH($B47,Screener!$A$2:$A$957,0))),"") | F47: =IFERROR(IF(ISBLANK(INDEX(Screener!$O$2:$O$957,MATCH($B47,Screener!$A$2:$A$957,0))),"",INDEX(Screener!$O$2:$O$957,MATCH($B47,Screener!$A$2:$A$957,0))),"") | G47: =IFERROR(IF(ISBLANK(INDEX(Screener!$N$2:$N$957,MATCH($B47,Screener!$A$2:$A$957,0))),"",INDEX(Screener!$N$2:$N$957,MATCH($B47,Screener!$A$2:$A$957,0))),"") | H47: =IFERROR(IF(ISBLANK(INDEX(Screener!$Q$2:$Q$957,MATCH($B47,Screener!$A$2:$A$957,0))),"",INDEX(Screener!$Q$2:$Q$957,MATCH($B47,Screener!$A$2:$A$957,0))),"") | I47: =IFERROR(IF(ISBLANK(INDEX(Screener!$R$2:$R$957,MATCH($B47,Screener!$A$2:$A$957,0))),"",INDEX(Screener!$R$2:$R$957,MATCH($B47,Screener!$A$2:$A$957,0))),"") | J47: =IFERROR(IF(ISBLANK(INDEX(Screener!$AH$2:$AH$957,MATCH($B47,Screener!$A$2:$A$957,0))),"",INDEX(Screener!$AH$2:$AH$957,MATCH($B47,Screener!$A$2:$A$957,0))),"") | K47: =IFERROR(IF(ISBLANK(INDEX(Screener!$AI$2:$AI$957,MATCH($B47,Screener!$A$2:$A$957,0))),"",INDEX(Screener!$AI$2:$AI$957,MATCH($B47,Screener!$A$2:$A$957,0))),"")
A48: 8 | B48: BCAP | C48: =IFERROR(IF(ISBLANK(INDEX(Screener!$B$2:$B$957,MATCH($B48,Screener!$A$2:$A$957,0))),"",INDEX(Screener!$B$2:$B$957,MATCH($B48,Screener!$A$2:$A$957,0))),"") | D48: =IFERROR(IF(ISBLANK(INDEX(Screener!$C$2:$C$957,MATCH($B48,Screener!$A$2:$A$957,0))),"",INDEX(Screener!$C$2:$C$957,MATCH($B48,Screener!$A$2:$A$957,0))),"") | E48: =IFERROR(IF(ISBLANK(INDEX(Screener!$I$2:$I$957,MATCH($B48,Screener!$A$2:$A$957,0))),"",INDEX(Screener!$I$2:$I$957,MATCH($B48,Screener!$A$2:$A$957,0))),"") | F48: =IFERROR(IF(ISBLANK(INDEX(Screener!$O$2:$O$957,MATCH($B48,Screener!$A$2:$A$957,0))),"",INDEX(Screener!$O$2:$O$957,MATCH($B48,Screener!$A$2:$A$957,0))),"") | G48: =IFERROR(IF(ISBLANK(INDEX(Screener!$N$2:$N$957,MATCH($B48,Screener!$A$2:$A$957,0))),"",INDEX(Screener!$N$2:$N$957,MATCH($B48,Screener!$A$2:$A$957,0))),"") | H48: =IFERROR(IF(ISBLANK(INDEX(Screener!$Q$2:$Q$957,MATCH($B48,Screener!$A$2:$A$957,0))),"",INDEX(Screener!$Q$2:$Q$957,MATCH($B48,Screener!$A$2:$A$957,0))),"") | I48: =IFERROR(IF(ISBLANK(INDEX(Screener!$R$2:$R$957,MATCH($B48,Screener!$A$2:$A$957,0))),"",INDEX(Screener!$R$2:$R$957,MATCH($B48,Screener!$A$2:$A$957,0))),"") | J48: =IFERROR(IF(ISBLANK(INDEX(Screener!$AH$2:$AH$957,MATCH($B48,Screener!$A$2:$A$957,0))),"",INDEX(Screener!$AH$2:$AH$957,MATCH($B48,Screener!$A$2:$A$957,0))),"") | K48: =IFERROR(IF(ISBLANK(INDEX(Screener!$AI$2:$AI$957,MATCH($B48,Screener!$A$2:$A$957,0))),"",INDEX(Screener!$AI$2:$AI$957,MATCH($B48,Screener!$A$2:$A$957,0))),"")
A49: 9 | B49: SRSN | C49: =IFERROR(IF(ISBLANK(INDEX(Screener!$B$2:$B$957,MATCH($B49,Screener!$A$2:$A$957,0))),"",INDEX(Screener!$B$2:$B$957,MATCH($B49,Screener!$A$2:$A$957,0))),"") | D49: =IFERROR(IF(ISBLANK(INDEX(Screener!$C$2:$C$957,MATCH($B49,Screener!$A$2:$A$957,0))),"",INDEX(Screener!$C$2:$C$957,MATCH($B49,Screener!$A$2:$A$957,0))),"") | E49: =IFERROR(IF(ISBLANK(INDEX(Screener!$I$2:$I$957,MATCH($B49,Screener!$A$2:$A$957,0))),"",INDEX(Screener!$I$2:$I$957,MATCH($B49,Screener!$A$2:$A$957,0))),"") | F49: =IFERROR(IF(ISBLANK(INDEX(Screener!$O$2:$O$957,MATCH($B49,Screener!$A$2:$A$957,0))),"",INDEX(Screener!$O$2:$O$957,MATCH($B49,Screener!$A$2:$A$957,0))),"") | G49: =IFERROR(IF(ISBLANK(INDEX(Screener!$N$2:$N$957,MATCH($B49,Screener!$A$2:$A$957,0))),"",INDEX(Screener!$N$2:$N$957,MATCH($B49,Screener!$A$2:$A$957,0))),"") | H49: =IFERROR(IF(ISBLANK(INDEX(Screener!$Q$2:$Q$957,MATCH($B49,Screener!$A$2:$A$957,0))),"",INDEX(Screener!$Q$2:$Q$957,MATCH($B49,Screener!$A$2:$A$957,0))),"") | I49: =IFERROR(IF(ISBLANK(INDEX(Screener!$R$2:$R$957,MATCH($B49,Screener!$A$2:$A$957,0))),"",INDEX(Screener!$R$2:$R$957,MATCH($B49,Screener!$A$2:$A$957,0))),"") | J49: =IFERROR(IF(ISBLANK(INDEX(Screener!$AH$2:$AH$957,MATCH($B49,Screener!$A$2:$A$957,0))),"",INDEX(Screener!$AH$2:$AH$957,MATCH($B49,Screener!$A$2:$A$957,0))),"") | K49: =IFERROR(IF(ISBLANK(INDEX(Screener!$AI$2:$AI$957,MATCH($B49,Screener!$A$2:$A$957,0))),"",INDEX(Screener!$AI$2:$AI$957,MATCH($B49,Screener!$A$2:$A$957,0))),"")
A50: 10 | B50: ASGR | C50: =IFERROR(IF(ISBLANK(INDEX(Screener!$B$2:$B$957,MATCH($B50,Screener!$A$2:$A$957,0))),"",INDEX(Screener!$B$2:$B$957,MATCH($B50,Screener!$A$2:$A$957,0))),"") | D50: =IFERROR(IF(ISBLANK(INDEX(Screener!$C$2:$C$957,MATCH($B50,Screener!$A$2:$A$957,0))),"",INDEX(Screener!$C$2:$C$957,MATCH($B50,Screener!$A$2:$A$957,0))),"") | E50: =IFERROR(IF(ISBLANK(INDEX(Screener!$I$2:$I$957,MATCH($B50,Screener!$A$2:$A$957,0))),"",INDEX(Screener!$I$2:$I$957,MATCH($B50,Screener!$A$2:$A$957,0))),"") | F50: =IFERROR(IF(ISBLANK(INDEX(Screener!$O$2:$O$957,MATCH($B50,Screener!$A$2:$A$957,0))),"",INDEX(Screener!$O$2:$O$957,MATCH($B50,Screener!$A$2:$A$957,0))),"") | G50: =IFERROR(IF(ISBLANK(INDEX(Screener!$N$2:$N$957,MATCH($B50,Screener!$A$2:$A$957,0))),"",INDEX(Screener!$N$2:$N$957,MATCH($B50,Screener!$A$2:$A$957,0))),"") | H50: =IFERROR(IF(ISBLANK(INDEX(Screener!$Q$2:$Q$957,MATCH($B50,Screener!$A$2:$A$957,0))),"",INDEX(Screener!$Q$2:$Q$957,MATCH($B50,Screener!$A$2:$A$957,0))),"") | I50: =IFERROR(IF(ISBLANK(INDEX(Screener!$R$2:$R$957,MATCH($B50,Screener!$A$2:$A$957,0))),"",INDEX(Screener!$R$2:$R$957,MATCH($B50,Screener!$A$2:$A$957,0))),"") | J50: =IFERROR(IF(ISBLANK(INDEX(Screener!$AH$2:$AH$957,MATCH($B50,Screener!$A$2:$A$957,0))),"",INDEX(Screener!$AH$2:$AH$957,MATCH($B50,Screener!$A$2:$A$957,0))),"") | K50: =IFERROR(IF(ISBLANK(INDEX(Screener!$AI$2:$AI$957,MATCH($B50,Screener!$A$2:$A$957,0))),"",INDEX(Screener!$AI$2:$AI$957,MATCH($B50,Screener!$A$2:$A$957,0))),"")
A52: GRAHAM NET-NETS — market cap below net current asset value
A53: Rank | B53: Ticker | C53: Name | D53: Sector | E53: Price | F53: NCAV/share | G53: Price / NCAV | H53: Market Cap (IDR bn) | I53: F-Score | J53: Composite | K53: Verdict
A54: 1 | B54: LPCK | C54: =IFERROR(IF(ISBLANK(INDEX(Screener!$B$2:$B$957,MATCH($B54,Screener!$A$2:$A$957,0))),"",INDEX(Screener!$B$2:$B$957,MATCH($B54,Screener!$A$2:$A$957,0))),"") | D54: =IFERROR(IF(ISBLANK(INDEX(Screener!$C$2:$C$957,MATCH($B54,Screener!$A$2:$A$957,0))),"",INDEX(Screener!$C$2:$C$957,MATCH($B54,Screener!$A$2:$A$957,0))),"") | E54: =IFERROR(IF(ISBLANK(INDEX(Screener!$E$2:$E$957,MATCH($B54,Screener!$A$2:$A$957,0))),"",INDEX(Screener!$E$2:$E$957,MATCH($B54,Screener!$A$2:$A$957,0))),"") | F54: =IFERROR(IF(ISBLANK(INDEX(Screener!$V$2:$V$957,MATCH($B54,Screener!$A$2:$A$957,0))),"",INDEX(Screener!$V$2:$V$957,MATCH($B54,Screener!$A$2:$A$957,0))),"") | G54: =IF(AND(ISNUMBER($E54),ISNUMBER($F54),$F54<>0),$E54/$F54,"") | H54: =IFERROR(IF(ISBLANK(INDEX(Screener!$F$2:$F$957,MATCH($B54,Screener!$A$2:$A$957,0))),"",INDEX(Screener!$F$2:$F$957,MATCH($B54,Screener!$A$2:$A$957,0))),"") | I54: =IFERROR(IF(ISBLANK(INDEX(Screener!$Q$2:$Q$957,MATCH($B54,Screener!$A$2:$A$957,0))),"",INDEX(Screener!$Q$2:$Q$957,MATCH($B54,Screener!$A$2:$A$957,0))),"") | J54: =IFERROR(IF(ISBLANK(INDEX(Screener!$AH$2:$AH$957,MATCH($B54,Screener!$A$2:$A$957,0))),"",INDEX(Screener!$AH$2:$AH$957,MATCH($B54,Screener!$A$2:$A$957,0))),"") | K54: =IFERROR(IF(ISBLANK(INDEX(Screener!$AI$2:$AI$957,MATCH($B54,Screener!$A$2:$A$957,0))),"",INDEX(Screener!$AI$2:$AI$957,MATCH($B54,Screener!$A$2:$A$957,0))),"")
A55: 2 | B55: MRAT | C55: =IFERROR(IF(ISBLANK(INDEX(Screener!$B$2:$B$957,MATCH($B55,Screener!$A$2:$A$957,0))),"",INDEX(Screener!$B$2:$B$957,MATCH($B55,Screener!$A$2:$A$957,0))),"") | D55: =IFERROR(IF(ISBLANK(INDEX(Screener!$C$2:$C$957,MATCH($B55,Screener!$A$2:$A$957,0))),"",INDEX(Screener!$C$2:$C$957,MATCH($B55,Screener!$A$2:$A$957,0))),"") | E55: =IFERROR(IF(ISBLANK(INDEX(Screener!$E$2:$E$957,MATCH($B55,Screener!$A$2:$A$957,0))),"",INDEX(Screener!$E$2:$E$957,MATCH($B55,Screener!$A$2:$A$957,0))),"") | F55: =IFERROR(IF(ISBLANK(INDEX(Screener!$V$2:$V$957,MATCH($B55,Screener!$A$2:$A$957,0))),"",INDEX(Screener!$V$2:$V$957,MATCH($B55,Screener!$A$2:$A$957,0))),"") | G55: =IF(AND(ISNUMBER($E55),ISNUMBER($F55),$F55<>0),$E55/$F55,"") | H55: =IFERROR(IF(ISBLANK(INDEX(Screener!$F$2:$F$957,MATCH($B55,Screener!$A$2:$A$957,0))),"",INDEX(Screener!$F$2:$F$957,MATCH($B55,Screener!$A$2:$A$957,0))),"") | I55: =IFERROR(IF(ISBLANK(INDEX(Screener!$Q$2:$Q$957,MATCH($B55,Screener!$A$2:$A$957,0))),"",INDEX(Screener!$Q$2:$Q$957,MATCH($B55,Screener!$A$2:$A$957,0))),"") | J55: =IFERROR(IF(ISBLANK(INDEX(Screener!$AH$2:$AH$957,MATCH($B55,Screener!$A$2:$A$957,0))),"",INDEX(Screener!$AH$2:$AH$957,MATCH($B55,Screener!$A$2:$A$957,0))),"") | K55: =IFERROR(IF(ISBLANK(INDEX(Screener!$AI$2:$AI$957,MATCH($B55,Screener!$A$2:$A$957,0))),"",INDEX(Screener!$AI$2:$AI$957,MATCH($B55,Screener!$A$2:$A$957,0))),"")
A56: 3 | B56: IGAR | C56: =IFERROR(IF(ISBLANK(INDEX(Screener!$B$2:$B$957,MATCH($B56,Screener!$A$2:$A$957,0))),"",INDEX(Screener!$B$2:$B$957,MATCH($B56,Screener!$A$2:$A$957,0))),"") | D56: =IFERROR(IF(ISBLANK(INDEX(Screener!$C$2:$C$957,MATCH($B56,Screener!$A$2:$A$957,0))),"",INDEX(Screener!$C$2:$C$957,MATCH($B56,Screener!$A$2:$A$957,0))),"") | E56: =IFERROR(IF(ISBLANK(INDEX(Screener!$E$2:$E$957,MATCH($B56,Screener!$A$2:$A$957,0))),"",INDEX(Screener!$E$2:$E$957,MATCH($B56,Screener!$A$2:$A$957,0))),"") | F56: =IFERROR(IF(ISBLANK(INDEX(Screener!$V$2:$V$957,MATCH($B56,Screener!$A$2:$A$957,0))),"",INDEX(Screener!$V$2:$V$957,MATCH($B56,Screener!$A$2:$A$957,0))),"") | G56: =IF(AND(ISNUMBER($E56),ISNUMBER($F56),$F56<>0),$E56/$F56,"") | H56: =IFERROR(IF(ISBLANK(INDEX(Screener!$F$2:$F$957,MATCH($B56,Screener!$A$2:$A$957,0))),"",INDEX(Screener!$F$2:$F$957,MATCH($B56,Screener!$A$2:$A$957,0))),"") | I56: =IFERROR(IF(ISBLANK(INDEX(Screener!$Q$2:$Q$957,MATCH($B56,Screener!$A$2:$A$957,0))),"",INDEX(Screener!$Q$2:$Q$957,MATCH($B56,Screener!$A$2:$A$957,0))),"") | J56: =IFERROR(IF(ISBLANK(INDEX(Screener!$AH$2:$AH$957,MATCH($B56,Screener!$A$2:$A$957,0))),"",INDEX(Screener!$AH$2:$AH$957,MATCH($B56,Screener!$A$2:$A$957,0))),"") | K56: =IFERROR(IF(ISBLANK(INDEX(Screener!$AI$2:$AI$957,MATCH($B56,Screener!$A$2:$A$957,0))),"",INDEX(Screener!$AI$2:$AI$957,MATCH($B56,Screener!$A$2:$A$957,0))),"")
A57: 4 | B57: LPLI | C57: =IFERROR(IF(ISBLANK(INDEX(Screener!$B$2:$B$957,MATCH($B57,Screener!$A$2:$A$957,0))),"",INDEX(Screener!$B$2:$B$957,MATCH($B57,Screener!$A$2:$A$957,0))),"") | D57: =IFERROR(IF(ISBLANK(INDEX(Screener!$C$2:$C$957,MATCH($B57,Screener!$A$2:$A$957,0))),"",INDEX(Screener!$C$2:$C$957,MATCH($B57,Screener!$A$2:$A$957,0))),"") | E57: =IFERROR(IF(ISBLANK(INDEX(Screener!$E$2:$E$957,MATCH($B57,Screener!$A$2:$A$957,0))),"",INDEX(Screener!$E$2:$E$957,MATCH($B57,Screener!$A$2:$A$957,0))),"") | F57: =IFERROR(IF(ISBLANK(INDEX(Screener!$V$2:$V$957,MATCH($B57,Screener!$A$2:$A$957,0))),"",INDEX(Screener!$V$2:$V$957,MATCH($B57,Screener!$A$2:$A$957,0))),"") | G57: =IF(AND(ISNUMBER($E57),ISNUMBER($F57),$F57<>0),$E57/$F57,"") | H57: =IFERROR(IF(ISBLANK(INDEX(Screener!$F$2:$F$957,MATCH($B57,Screener!$A$2:$A$957,0))),"",INDEX(Screener!$F$2:$F$957,MATCH($B57,Screener!$A$2:$A$957,0))),"") | I57: =IFERROR(IF(ISBLANK(INDEX(Screener!$Q$2:$Q$957,MATCH($B57,Screener!$A$2:$A$957,0))),"",INDEX(Screener!$Q$2:$Q$957,MATCH($B57,Screener!$A$2:$A$957,0))),"") | J57: =IFERROR(IF(ISBLANK(INDEX(Screener!$AH$2:$AH$957,MATCH($B57,Screener!$A$2:$A$957,0))),"",INDEX(Screener!$AH$2:$AH$957,MATCH($B57,Screener!$A$2:$A$957,0))),"") | K57: =IFERROR(IF(ISBLANK(INDEX(Screener!$AI$2:$AI$957,MATCH($B57,Screener!$A$2:$A$957,0))),"",INDEX(Screener!$AI$2:$AI$957,MATCH($B57,Screener!$A$2:$A$957,0))),"")
A58: 5 | B58: MNCN | C58: =IFERROR(IF(ISBLANK(INDEX(Screener!$B$2:$B$957,MATCH($B58,Screener!$A$2:$A$957,0))),"",INDEX(Screener!$B$2:$B$957,MATCH($B58,Screener!$A$2:$A$957,0))),"") | D58: =IFERROR(IF(ISBLANK(INDEX(Screener!$C$2:$C$957,MATCH($B58,Screener!$A$2:$A$957,0))),"",INDEX(Screener!$C$2:$C$957,MATCH($B58,Screener!$A$2:$A$957,0))),"") | E58: =IFERROR(IF(ISBLANK(INDEX(Screener!$E$2:$E$957,MATCH($B58,Screener!$A$2:$A$957,0))),"",INDEX(Screener!$E$2:$E$957,MATCH($B58,Screener!$A$2:$A$957,0))),"") | F58: =IFERROR(IF(ISBLANK(INDEX(Screener!$V$2:$V$957,MATCH($B58,Screener!$A$2:$A$957,0))),"",INDEX(Screener!$V$2:$V$957,MATCH($B58,Screener!$A$2:$A$957,0))),"") | G58: =IF(AND(ISNUMBER($E58),ISNUMBER($F58),$F58<>0),$E58/$F58,"") | H58: =IFERROR(IF(ISBLANK(INDEX(Screener!$F$2:$F$957,MATCH($B58,Screener!$A$2:$A$957,0))),"",INDEX(Screener!$F$2:$F$957,MATCH($B58,Screener!$A$2:$A$957,0))),"") | I58: =IFERROR(IF(ISBLANK(INDEX(Screener!$Q$2:$Q$957,MATCH($B58,Screener!$A$2:$A$957,0))),"",INDEX(Screener!$Q$2:$Q$957,MATCH($B58,Screener!$A$2:$A$957,0))),"") | J58: =IFERROR(IF(ISBLANK(INDEX(Screener!$AH$2:$AH$957,MATCH($B58,Screener!$A$2:$A$957,0))),"",INDEX(Screener!$AH$2:$AH$957,MATCH($B58,Screener!$A$2:$A$957,0))),"") | K58: =IFERROR(IF(ISBLANK(INDEX(Screener!$AI$2:$AI$957,MATCH($B58,Screener!$A$2:$A$957,0))),"",INDEX(Screener!$AI$2:$AI$957,MATCH($B58,Screener!$A$2:$A$957,0))),"")
A59: 6 | B59: KBLI | C59: =IFERROR(IF(ISBLANK(INDEX(Screener!$B$2:$B$957,MATCH($B59,Screener!$A$2:$A$957,0))),"",INDEX(Screener!$B$2:$B$957,MATCH($B59,Screener!$A$2:$A$957,0))),"") | D59: =IFERROR(IF(ISBLANK(INDEX(Screener!$C$2:$C$957,MATCH($B59,Screener!$A$2:$A$957,0))),"",INDEX(Screener!$C$2:$C$957,MATCH($B59,Screener!$A$2:$A$957,0))),"") | E59: =IFERROR(IF(ISBLANK(INDEX(Screener!$E$2:$E$957,MATCH($B59,Screener!$A$2:$A$957,0))),"",INDEX(Screener!$E$2:$E$957,MATCH($B59,Screener!$A$2:$A$957,0))),"") | F59: =IFERROR(IF(ISBLANK(INDEX(Screener!$V$2:$V$957,MATCH($B59,Screener!$A$2:$A$957,0))),"",INDEX(Screener!$V$2:$V$957,MATCH($B59,Screener!$A$2:$A$957,0))),"") | G59: =IF(AND(ISNUMBER($E59),ISNUMBER($F59),$F59<>0),$E59/$F59,"") | H59: =IFERROR(IF(ISBLANK(INDEX(Screener!$F$2:$F$957,MATCH($B59,Screener!$A$2:$A$957,0))),"",INDEX(Screener!$F$2:$F$957,MATCH($B59,Screener!$A$2:$A$957,0))),"") | I59: =IFERROR(IF(ISBLANK(INDEX(Screener!$Q$2:$Q$957,MATCH($B59,Screener!$A$2:$A$957,0))),"",INDEX(Screener!$Q$2:$Q$957,MATCH($B59,Screener!$A$2:$A$957,0))),"") | J59: =IFERROR(IF(ISBLANK(INDEX(Screener!$AH$2:$AH$957,MATCH($B59,Screener!$A$2:$A$957,0))),"",INDEX(Screener!$AH$2:$AH$957,MATCH($B59,Screener!$A$2:$A$957,0))),"") | K59: =IFERROR(IF(ISBLANK(INDEX(Screener!$AI$2:$AI$957,MATCH($B59,Screener!$A$2:$A$957,0))),"",INDEX(Screener!$AI$2:$AI$957,MATCH($B59,Screener!$A$2:$A$957,0))),"")
A60: 7 | B60: RUIS | C60: =IFERROR(IF(ISBLANK(INDEX(Screener!$B$2:$B$957,MATCH($B60,Screener!$A$2:$A$957,0))),"",INDEX(Screener!$B$2:$B$957,MATCH($B60,Screener!$A$2:$A$957,0))),"") | D60: =IFERROR(IF(ISBLANK(INDEX(Screener!$C$2:$C$957,MATCH($B60,Screener!$A$2:$A$957,0))),"",INDEX(Screener!$C$2:$C$957,MATCH($B60,Screener!$A$2:$A$957,0))),"") | E60: =IFERROR(IF(ISBLANK(INDEX(Screener!$E$2:$E$957,MATCH($B60,Screener!$A$2:$A$957,0))),"",INDEX(Screener!$E$2:$E$957,MATCH($B60,Screener!$A$2:$A$957,0))),"") | F60: =IFERROR(IF(ISBLANK(INDEX(Screener!$V$2:$V$957,MATCH($B60,Screener!$A$2:$A$957,0))),"",INDEX(Screener!$V$2:$V$957,MATCH($B60,Screener!$A$2:$A$957,0))),"") | G60: =IF(AND(ISNUMBER($E60),ISNUMBER($F60),$F60<>0),$E60/$F60,"") | H60: =IFERROR(IF(ISBLANK(INDEX(Screener!$F$2:$F$957,MATCH($B60,Screener!$A$2:$A$957,0))),"",INDEX(Screener!$F$2:$F$957,MATCH($B60,Screener!$A$2:$A$957,0))),"") | I60: =IFERROR(IF(ISBLANK(INDEX(Screener!$Q$2:$Q$957,MATCH($B60,Screener!$A$2:$A$957,0))),"",INDEX(Screener!$Q$2:$Q$957,MATCH($B60,Screener!$A$2:$A$957,0))),"") | J60: =IFERROR(IF(ISBLANK(INDEX(Screener!$AH$2:$AH$957,MATCH($B60,Screener!$A$2:$A$957,0))),"",INDEX(Screener!$AH$2:$AH$957,MATCH($B60,Screener!$A$2:$A$957,0))),"") | K60: =IFERROR(IF(ISBLANK(INDEX(Screener!$AI$2:$AI$957,MATCH($B60,Screener!$A$2:$A$957,0))),"",INDEX(Screener!$AI$2:$AI$957,MATCH($B60,Screener!$A$2:$A$957,0))),"")
A61: 8 | B61: BMSR | C61: =IFERROR(IF(ISBLANK(INDEX(Screener!$B$2:$B$957,MATCH($B61,Screener!$A$2:$A$957,0))),"",INDEX(Screener!$B$2:$B$957,MATCH($B61,Screener!$A$2:$A$957,0))),"") | D61: =IFERROR(IF(ISBLANK(INDEX(Screener!$C$2:$C$957,MATCH($B61,Screener!$A$2:$A$957,0))),"",INDEX(Screener!$C$2:$C$957,MATCH($B61,Screener!$A$2:$A$957,0))),"") | E61: =IFERROR(IF(ISBLANK(INDEX(Screener!$E$2:$E$957,MATCH($B61,Screener!$A$2:$A$957,0))),"",INDEX(Screener!$E$2:$E$957,MATCH($B61,Screener!$A$2:$A$957,0))),"") | F61: =IFERROR(IF(ISBLANK(INDEX(Screener!$V$2:$V$957,MATCH($B61,Screener!$A$2:$A$957,0))),"",INDEX(Screener!$V$2:$V$957,MATCH($B61,Screener!$A$2:$A$957,0))),"") | G61: =IF(AND(ISNUMBER($E61),ISNUMBER($F61),$F61<>0),$E61/$F61,"") | H61: =IFERROR(IF(ISBLANK(INDEX(Screener!$F$2:$F$957,MATCH($B61,Screener!$A$2:$A$957,0))),"",INDEX(Screener!$F$2:$F$957,MATCH($B61,Screener!$A$2:$A$957,0))),"") | I61: =IFERROR(IF(ISBLANK(INDEX(Screener!$Q$2:$Q$957,MATCH($B61,Screener!$A$2:$A$957,0))),"",INDEX(Screener!$Q$2:$Q$957,MATCH($B61,Screener!$A$2:$A$957,0))),"") | J61: =IFERROR(IF(ISBLANK(INDEX(Screener!$AH$2:$AH$957,MATCH($B61,Screener!$A$2:$A$957,0))),"",INDEX(Screener!$AH$2:$AH$957,MATCH($B61,Screener!$A$2:$A$957,0))),"") | K61: =IFERROR(IF(ISBLANK(INDEX(Screener!$AI$2:$AI$957,MATCH($B61,Screener!$A$2:$A$957,0))),"",INDEX(Screener!$AI$2:$AI$957,MATCH($B61,Screener!$A$2:$A$957,0))),"")
A62: 9 | B62: BMTR | C62: =IFERROR(IF(ISBLANK(INDEX(Screener!$B$2:$B$957,MATCH($B62,Screener!$A$2:$A$957,0))),"",INDEX(Screener!$B$2:$B$957,MATCH($B62,Screener!$A$2:$A$957,0))),"") | D62: =IFERROR(IF(ISBLANK(INDEX(Screener!$C$2:$C$957,MATCH($B62,Screener!$A$2:$A$957,0))),"",INDEX(Screener!$C$2:$C$957,MATCH($B62,Screener!$A$2:$A$957,0))),"") | E62: =IFERROR(IF(ISBLANK(INDEX(Screener!$E$2:$E$957,MATCH($B62,Screener!$A$2:$A$957,0))),"",INDEX(Screener!$E$2:$E$957,MATCH($B62,Screener!$A$2:$A$957,0))),"") | F62: =IFERROR(IF(ISBLANK(INDEX(Screener!$V$2:$V$957,MATCH($B62,Screener!$A$2:$A$957,0))),"",INDEX(Screener!$V$2:$V$957,MATCH($B62,Screener!$A$2:$A$957,0))),"") | G62: =IF(AND(ISNUMBER($E62),ISNUMBER($F62),$F62<>0),$E62/$F62,"") | H62: =IFERROR(IF(ISBLANK(INDEX(Screener!$F$2:$F$957,MATCH($B62,Screener!$A$2:$A$957,0))),"",INDEX(Screener!$F$2:$F$957,MATCH($B62,Screener!$A$2:$A$957,0))),"") | I62: =IFERROR(IF(ISBLANK(INDEX(Screener!$Q$2:$Q$957,MATCH($B62,Screener!$A$2:$A$957,0))),"",INDEX(Screener!$Q$2:$Q$957,MATCH($B62,Screener!$A$2:$A$957,0))),"") | J62: =IFERROR(IF(ISBLANK(INDEX(Screener!$AH$2:$AH$957,MATCH($B62,Screener!$A$2:$A$957,0))),"",INDEX(Screener!$AH$2:$AH$957,MATCH($B62,Screener!$A$2:$A$957,0))),"") | K62: =IFERROR(IF(ISBLANK(INDEX(Screener!$AI$2:$AI$957,MATCH($B62,Screener!$A$2:$A$957,0))),"",INDEX(Screener!$AI$2:$AI$957,MATCH($B62,Screener!$A$2:$A$957,0))),"")
A63: 10 | B63: DIVA | C63: =IFERROR(IF(ISBLANK(INDEX(Screener!$B$2:$B$957,MATCH($B63,Screener!$A$2:$A$957,0))),"",INDEX(Screener!$B$2:$B$957,MATCH($B63,Screener!$A$2:$A$957,0))),"") | D63: =IFERROR(IF(ISBLANK(INDEX(Screener!$C$2:$C$957,MATCH($B63,Screener!$A$2:$A$957,0))),"",INDEX(Screener!$C$2:$C$957,MATCH($B63,Screener!$A$2:$A$957,0))),"") | E63: =IFERROR(IF(ISBLANK(INDEX(Screener!$E$2:$E$957,MATCH($B63,Screener!$A$2:$A$957,0))),"",INDEX(Screener!$E$2:$E$957,MATCH($B63,Screener!$A$2:$A$957,0))),"") | F63: =IFERROR(IF(ISBLANK(INDEX(Screener!$V$2:$V$957,MATCH($B63,Screener!$A$2:$A$957,0))),"",INDEX(Screener!$V$2:$V$957,MATCH($B63,Screener!$A$2:$A$957,0))),"") | G63: =IF(AND(ISNUMBER($E63),ISNUMBER($F63),$F63<>0),$E63/$F63,"") | H63: =IFERROR(IF(ISBLANK(INDEX(Screener!$F$2:$F$957,MATCH($B63,Screener!$A$2:$A$957,0))),"",INDEX(Screener!$F$2:$F$957,MATCH($B63,Screener!$A$2:$A$957,0))),"") | I63: =IFERROR(IF(ISBLANK(INDEX(Screener!$Q$2:$Q$957,MATCH($B63,Screener!$A$2:$A$957,0))),"",INDEX(Screener!$Q$2:$Q$957,MATCH($B63,Screener!$A$2:$A$957,0))),"") | J63: =IFERROR(IF(ISBLANK(INDEX(Screener!$AH$2:$AH$957,MATCH($B63,Screener!$A$2:$A$957,0))),"",INDEX(Screener!$AH$2:$AH$957,MATCH($B63,Screener!$A$2:$A$957,0))),"") | K63: =IFERROR(IF(ISBLANK(INDEX(Screener!$AI$2:$AI$957,MATCH($B63,Screener!$A$2:$A$957,0))),"",INDEX(Screener!$AI$2:$AI$957,MATCH($B63,Screener!$A$2:$A$957,0))),"")

Sheet Screener
A1: Ticker | B1: Name | C1: Sector | D1: Business Type | E1: Price | F1: Market Cap (IDR bn) | G1: PE (TTM) | H1: PB | I1: EV/EBIT | J1: EV/EBITDA | K1: Div Yield | L1: ROE | M1: ROIC | N1: ROC (Greenblatt) | O1: Earnings Yield (EBIT/EV) | P1: FCF Yield | Q1: F-Score | R1: Altman Z | S1: Current Ratio | T1: Net Debt/Equity | U1: Rev CAGR 3Y | V1: NCAV/share | W1: Net-Net Pass | X1: EPV/share | Y1: IV Bear | Z1: IV Base | AA1: IV Bull | AB1: Blended IV | AC1: MOS | AD1: Upside | AE1: Quality | AF1: Safety | AG1: Value | AH1: Composite | AI1: Verdict | AJ1: Quarters Stale | AK1: Red Flags | AL1: _row in RAW_key_statistics | AM1: _row in RAW_scores | AN1: _row in RAW_idx_stocks | AO1: _row in RAW_analyses
A2: AADI | B2: =IFERROR(IF(ISBLANK(INDEX(RAW_scores!$B$2:$B$957,$AM2)),"",INDEX(RAW_scores!$B$2:$B$957,$AM2)),"") | C2: =IFERROR(IF(ISBLANK(INDEX(RAW_scores!$C$2:$C$957,$AM2)),"",INDEX(RAW_scores!$C$2:$C$957,$AM2)),"") | D2: =IFERROR(IF(ISBLANK(INDEX(RAW_scores!$D$2:$D$957,$AM2)),"",INDEX(RAW_scores!$D$2:$D$957,$AM2)),"") | E2: =IFERROR(IF(ISBLANK(INDEX(RAW_idx_stocks!$F$2:$F$957,$AN2)),"",INDEX(RAW_idx_stocks!$F$2:$F$957,$AN2)),"") | F2: =IFERROR(IF(ISBLANK(INDEX(RAW_key_statistics!$BS$2:$BS$957,$AL2)),"",INDEX(RAW_key_statistics!$BS$2:$BS$957,$AL2)/1000000000),"") | G2: =IFERROR(IF(ISBLANK(INDEX(RAW_key_statistics!$C$2:$C$957,$AL2)),"",INDEX(RAW_key_statistics!$C$2:$C$957,$AL2)),"") | H2: =IFERROR(IF(ISBLANK(INDEX(RAW_key_statistics!$H$2:$H$957,$AL2)),"",INDEX(RAW_key_statistics!$H$2:$H$957,$AL2)),"") | I2: =IFERROR(IF(ISBLANK(INDEX(RAW_key_statistics!$K$2:$K$957,$AL2)),"",INDEX(RAW_key_statistics!$K$2:$K$957,$AL2)),"") | J2: =IFERROR(IF(ISBLANK(INDEX(RAW_key_statistics!$L$2:$L$957,$AL2)),"",INDEX(RAW_key_statistics!$L$2:$L$957,$AL2)),"") | K2: =IFERROR(IF(ISBLANK(INDEX(RAW_key_statistics!$AZ$2:$AZ$957,$AL2)),"",INDEX(RAW_key_statistics!$AZ$2:$AZ$957,$AL2)),"") | L2: =IFERROR(IF(ISBLANK(INDEX(RAW_key_statistics!$AG$2:$AG$957,$AL2)),"",INDEX(RAW_key_statistics!$AG$2:$AG$957,$AL2)),"") | M2: =IFERROR(IF(ISBLANK(INDEX(RAW_key_statistics!$AI$2:$AI$957,$AL2)),"",INDEX(RAW_key_statistics!$AI$2:$AI$957,$AL2)),"") | N2: =IFERROR(IF(ISBLANK(INDEX(RAW_key_statistics!$CI$2:$CI$957,$AL2)),"",INDEX(RAW_key_statistics!$CI$2:$CI$957,$AL2)),"") | O2: =IFERROR(IF(ISBLANK(INDEX(RAW_key_statistics!$CH$2:$CH$957,$AL2)),"",INDEX(RAW_key_statistics!$CH$2:$CH$957,$AL2)),"") | P2: =IFERROR(IF(ISBLANK(INDEX(RAW_key_statistics!$CK$2:$CK$957,$AL2)),"",INDEX(RAW_key_statistics!$CK$2:$CK$957,$AL2)),"") | Q2: =IFERROR(IF(ISBLANK(INDEX(RAW_key_statistics!$BB$2:$BB$957,$AL2)),"",INDEX(RAW_key_statistics!$BB$2:$BB$957,$AL2)),"") | R2: =IFERROR(IF(ISBLANK(INDEX(RAW_key_statistics!$AE$2:$AE$957,$AL2)),"",INDEX(RAW_key_statistics!$AE$2:$AE$957,$AL2)),"") | S2: =IFERROR(IF(ISBLANK(INDEX(RAW_key_statistics!$V$2:$V$957,$AL2)),"",INDEX(RAW_key_statistics!$V$2:$V$957,$AL2)),"") | T2: =IFERROR(IF(ISBLANK(INDEX(RAW_analyses!$N$2:$N$957,$AO2)),"",INDEX(RAW_analyses!$N$2:$N$957,$AO2)),"") | U2: =IFERROR(IF(ISBLANK(INDEX(RAW_key_statistics!$CU$2:$CU$957,$AL2)),"",INDEX(RAW_key_statistics!$CU$2:$CU$957,$AL2)),"") | V2: =IFERROR(IF(ISBLANK(INDEX(RAW_key_statistics!$CM$2:$CM$957,$AL2)),"",INDEX(RAW_key_statistics!$CM$2:$CM$957,$AL2)),"") | W2: =IFERROR(IF(ISBLANK(INDEX(RAW_key_statistics!$CN$2:$CN$957,$AL2)),"",INDEX(RAW_key_statistics!$CN$2:$CN$957,$AL2)),"") | X2: =IFERROR(IF(ISBLANK(INDEX(RAW_key_statistics!$CR$2:$CR$957,$AL2)),"",INDEX(RAW_key_statistics!$CR$2:$CR$957,$AL2)),"") | Y2: =IFERROR(IF(ISBLANK(INDEX(RAW_scores!$R$2:$R$957,$AM2)),"",INDEX(RAW_scores!$R$2:$R$957,$AM2)),"") | Z2: =IFERROR(IF(ISBLANK(INDEX(RAW_scores!$S$2:$S$957,$AM2)),"",INDEX(RAW_scores!$S$2:$S$957,$AM2)),"") | AA2: =IFERROR(IF(ISBLANK(INDEX(RAW_scores!$T$2:$T$957,$AM2)),"",INDEX(RAW_scores!$T$2:$T$957,$AM2)),"") | AB2: =IFERROR(IF(ISBLANK(INDEX(RAW_scores!$X$2:$X$957,$AM2)),"",INDEX(RAW_scores!$X$2:$X$957,$AM2)),"") | AC2: =IFERROR(IF(ISBLANK(INDEX(RAW_scores!$Y$2:$Y$957,$AM2)),"",INDEX(RAW_scores!$Y$2:$Y$957,$AM2)),"") | AD2: =IFERROR(IF(ISBLANK(INDEX(RAW_scores!$Z$2:$Z$957,$AM2)),"",INDEX(RAW_scores!$Z$2:$Z$957,$AM2)),"") | AE2: =IFERROR(IF(ISBLANK(INDEX(RAW_scores!$F$2:$F$957,$AM2)),"",INDEX(RAW_scores!$F$2:$F$957,$AM2)),"") | AF2: =IFERROR(IF(ISBLANK(INDEX(RAW_scores!$G$2:$G$957,$AM2)),"",INDEX(RAW_scores!$G$2:$G$957,$AM2)),"") | AG2: =IFERROR(IF(ISBLANK(INDEX(RAW_scores!$H$2:$H$957,$AM2)),"",INDEX(RAW_scores!$H$2:$H$957,$AM2)),"") | AH2: =IFERROR(IF(ISBLANK(INDEX(RAW_scores!$I$2:$I$957,$AM2)),"",INDEX(RAW_scores!$I$2:$I$957,$AM2)),"") | AI2: =IFERROR(IF(ISBLANK(INDEX(RAW_scores!$AA$2:$AA$957,$AM2)),"",INDEX(RAW_scores!$AA$2:$AA$957,$AM2)),"") | AJ2: =IFERROR(IF(ISBLANK(INDEX(RAW_scores!$AF$2:$AF$957,$AM2)),"",INDEX(RAW_scores!$AF$2:$AF$957,$AM2)),"") | AK2: =IFERROR(IF(ISBLANK(INDEX(RAW_scores!$AC$2:$AC$957,$AM2)),"",INDEX(RAW_scores!$AC$2:$AC$957,$AM2)),"") | AL2: =IFERROR(MATCH($A2,RAW_key_statistics!$A$2:$A$957,0),"") | AM2: =IFERROR(MATCH($A2,RAW_scores!$A$2:$A$957,0),"") | AN2: =IFERROR(MATCH($A2,RAW_idx_stocks!$A$2:$A$957,0),"") | AO2: =IFERROR(MATCH($A2,RAW_analyses!$A$2:$A$957,0),"")
A3: AALI | B3: =IFERROR(IF(ISBLANK(INDEX(RAW_scores!$B$2:$B$957,$AM3)),"",INDEX(RAW_scores!$B$2:$B$957,$AM3)),"") | C3: =IFERROR(IF(ISBLANK(INDEX(RAW_scores!$C$2:$C$957,$AM3)),"",INDEX(RAW_scores!$C$2:$C$957,$AM3)),"") | D3: =IFERROR(IF(ISBLANK(INDEX(RAW_scores!$D$2:$D$957,$AM3)),"",INDEX(RAW_scores!$D$2:$D$957,$AM3)),"") | E3: =IFERROR(IF(ISBLANK(INDEX(RAW_idx_stocks!$F$2:$F$957,$AN3)),"",INDEX(RAW_idx_stocks!$F$2:$F$957,$AN3)),"") | F3: =IFERROR(IF(ISBLANK(INDEX(RAW_key_statistics!$BS$2:$BS$957,$AL3)),"",INDEX(RAW_key_statistics!$BS$2:$BS$957,$AL3)/1000000000),"") | G3: =IFERROR(IF(ISBLANK(INDEX(RAW_key_statistics!$C$2:$C$957,$AL3)),"",INDEX(RAW_key_statistics!$C$2:$C$957,$AL3)),"") | H3: =IFERROR(IF(ISBLANK(INDEX(RAW_key_statistics!$H$2:$H$957,$AL3)),"",INDEX(RAW_key_statistics!$H$2:$H$957,$AL3)),"") | I3: =IFERROR(IF(ISBLANK(INDEX(RAW_key_statistics!$K$2:$K$957,$AL3)),"",INDEX(RAW_key_statistics!$K$2:$K$957,$AL3)),"") | J3: =IFERROR(IF(ISBLANK(INDEX(RAW_key_statistics!$L$2:$L$957,$AL3)),"",INDEX(RAW_key_statistics!$L$2:$L$957,$AL3)),"") | K3: =IFERROR(IF(ISBLANK(INDEX(RAW_key_statistics!$AZ$2:$AZ$957,$AL3)),"",INDEX(RAW_key_statistics!$AZ$2:$AZ$957,$AL3)),"") | L3: =IFERROR(IF(ISBLANK(INDEX(RAW_key_statistics!$AG$2:$AG$957,$AL3)),"",INDEX(RAW_key_statistics!$AG$2:$AG$957,$AL3)),"") | M3: =IFERROR(IF(ISBLANK(INDEX(RAW_key_statistics!$AI$2:$AI$957,$AL3)),"",INDEX(RAW_key_statistics!$AI$2:$AI$957,$AL3)),"") | N3: =IFERROR(IF(ISBLANK(INDEX(RAW_key_statistics!$CI$2:$CI$957,$AL3)),"",INDEX(RAW_key_statistics!$CI$2:$CI$957,$AL3)),"") | O3: =IFERROR(IF(ISBLANK(INDEX(RAW_key_statistics!$CH$2:$CH$957,$AL3)),"",INDEX(RAW_key_statistics!$CH$2:$CH$957,$AL3)),"") | P3: =IFERROR(IF(ISBLANK(INDEX(RAW_key_statistics!$CK$2:$CK$957,$AL3)),"",INDEX(RAW_key_statistics!$CK$2:$CK$957,$AL3)),"") | Q3: =IFERROR(IF(ISBLANK(INDEX(RAW_key_statistics!$BB$2:$BB$957,$AL3)),"",INDEX(RAW_key_statistics!$BB$2:$BB$957,$AL3)),"") | R3: =IFERROR(IF(ISBLANK(INDEX(RAW_key_statistics!$AE$2:$AE$957,$AL3)),"",INDEX(RAW_key_statistics!$AE$2:$AE$957,$AL3)),"") | S3: =IFERROR(IF(ISBLANK(INDEX(RAW_key_statistics!$V$2:$V$957,$AL3)),"",INDEX(RAW_key_statistics!$V$2:$V$957,$AL3)),"") | T3: =IFERROR(IF(ISBLANK(INDEX(RAW_analyses!$N$2:$N$957,$AO3)),"",INDEX(RAW_analyses!$N$2:$N$957,$AO3)),"") | U3: =IFERROR(IF(ISBLANK(INDEX(RAW_key_statistics!$CU$2:$CU$957,$AL3)),"",INDEX(RAW_key_statistics!$CU$2:$CU$957,$AL3)),"") | V3: =IFERROR(IF(ISBLANK(INDEX(RAW_key_statistics!$CM$2:$CM$957,$AL3)),"",INDEX(RAW_key_statistics!$CM$2:$CM$957,$AL3)),"") | W3: =IFERROR(IF(ISBLANK(INDEX(RAW_key_statistics!$CN$2:$CN$957,$AL3)),"",INDEX(RAW_key_statistics!$CN$2:$CN$957,$AL3)),"") | X3: =IFERROR(IF(ISBLANK(INDEX(RAW_key_statistics!$CR$2:$CR$957,$AL3)),"",INDEX(RAW_key_statistics!$CR$2:$CR$957,$AL3)),"") | Y3: =IFERROR(IF(ISBLANK(INDEX(RAW_scores!$R$2:$R$957,$AM3)),"",INDEX(RAW_scores!$R$2:$R$957,$AM3)),"") | Z3: =IFERROR(IF(ISBLANK(INDEX(RAW_scores!$S$2:$S$957,$AM3)),"",INDEX(RAW_scores!$S$2:$S$957,$AM3)),"") | AA3: =IFERROR(IF(ISBLANK(INDEX(RAW_scores!$T$2:$T$957,$AM3)),"",INDEX(RAW_scores!$T$2:$T$957,$AM3)),"") | AB3: =IFERROR(IF(ISBLANK(INDEX(RAW_scores!$X$2:$X$957,$AM3)),"",INDEX(RAW_scores!$X$2:$X$957,$AM3)),"") | AC3: =IFERROR(IF(ISBLANK(INDEX(RAW_scores!$Y$2:$Y$957,$AM3)),"",INDEX(RAW_scores!$Y$2:$Y$957,$AM3)),"") | AD3: =IFERROR(IF(ISBLANK(INDEX(RAW_scores!$Z$2:$Z$957,$AM3)),"",INDEX(RAW_scores!$Z$2:$Z$957,$AM3)),"") | AE3: =IFERROR(IF(ISBLANK(INDEX(RAW_scores!$F$2:$F$957,$AM3)),"",INDEX(RAW_scores!$F$2:$F$957,$AM3)),"") | AF3: =IFERROR(IF(ISBLANK(INDEX(RAW_scores!$G$2:$G$957,$AM3)),"",INDEX(RAW_scores!$G$2:$G$957,$AM3)),"") | AG3: =IFERROR(IF(ISBLANK(INDEX(RAW_scores!$H$2:$H$957,$AM3)),"",INDEX(RAW_scores!$H$2:$H$957,$AM3)),"") | AH3: =IFERROR(IF(ISBLANK(INDEX(RAW_scores!$I$2:$I$957,$AM3)),"",INDEX(RAW_scores!$I$2:$I$957,$AM3)),"") | AI3: =IFERROR(IF(ISBLANK(INDEX(RAW_scores!$AA$2:$AA$957,$AM3)),"",INDEX(RAW_scores!$AA$2:$AA$957,$AM3)),"") | AJ3: =IFERROR(IF(ISBLANK(INDEX(RAW_scores!$AF$2:$AF$957,$AM3)),"",INDEX(RAW_scores!$AF$2:$AF$957,$AM3)),"") | AK3: =IFERROR(IF(ISBLANK(INDEX(RAW_scores!$AC$2:$AC$957,$AM3)),"",INDEX(RAW_scores!$AC$2:$AC$957,$AM3)),"") | AL3: =IFERROR(MATCH($A3,RAW_key_statistics!$A$2:$A$957,0),"") | AM3: =IFERROR(MATCH($A3,RAW_scores!$A$2:$A$957,0),"") | AN3: =IFERROR(MATCH($A3,RAW_idx_stocks!$A$2:$A$957,0),"") | AO3: =IFERROR(MATCH($A3,RAW_analyses!$A$2:$A$957,0),"")
A4: ABBA | B4: =IFERROR(IF(ISBLANK(INDEX(RAW_scores!$B$2:$B$957,$AM4)),"",INDEX(RAW_scores!$B$2:$B$957,$AM4)),"") | C4: =IFERROR(IF(ISBLANK(INDEX(RAW_scores!$C$2:$C$957,$AM4)),"",INDEX(RAW_scores!$C$2:$C$957,$AM4)),"") | D4: =IFERROR(IF(ISBLANK(INDEX(RAW_scores!$D$2:$D$957,$AM4)),"",INDEX(RAW_scores!$D$2:$D$957,$AM4)),"") | E4: =IFERROR(IF(ISBLANK(INDEX(RAW_idx_stocks!$F$2:$F$957,$AN4)),"",INDEX(RAW_idx_stocks!$F$2:$F$957,$AN4)),"") | F4: =IFERROR(IF(ISBLANK(INDEX(RAW_key_statistics!$BS$2:$BS$957,$AL4)),"",INDEX(RAW_key_statistics!$BS$2:$BS$957,$AL4)/1000000000),"") | G4: =IFERROR(IF(ISBLANK(INDEX(RAW_key_statistics!$C$2:$C$957,$AL4)),"",INDEX(RAW_key_statistics!$C$2:$C$957,$AL4)),"") | H4: =IFERROR(IF(ISBLANK(INDEX(RAW_key_statistics!$H$2:$H$957,$AL4)),"",INDEX(RAW_key_statistics!$H$2:$H$957,$AL4)),"") | I4: =IFERROR(IF(ISBLANK(INDEX(RAW_key_statistics!$K$2:$K$957,$AL4)),"",INDEX(RAW_key_statistics!$K$2:$K$957,$AL4)),"") | J4: =IFERROR(IF(ISBLANK(INDEX(RAW_key_statistics!$L$2:$L$957,$AL4)),"",INDEX(RAW_key_statistics!$L$2:$L$957,$AL4)),"") | K4: =IFERROR(IF(ISBLANK(INDEX(RAW_key_statistics!$AZ$2:$AZ$957,$AL4)),"",INDEX(RAW_key_statistics!$AZ$2:$AZ$957,$AL4)),"") | L4: =IFERROR(IF(ISBLANK(INDEX(RAW_key_statistics!$AG$2:$AG$957,$AL4)),"",INDEX(RAW_key_statistics!$AG$2:$AG$957,$AL4)),"") | M4: =IFERROR(IF(ISBLANK(INDEX(RAW_key_statistics!$AI$2:$AI$957,$AL4)),"",INDEX(RAW_key_statistics!$AI$2:$AI$957,$AL4)),"") | N4: =IFERROR(IF(ISBLANK(INDEX(RAW_key_statistics!$CI$2:$CI$957,$AL4)),"",INDEX(RAW_key_statistics!$CI$2:$CI$957,$AL4)),"") | O4: =IFERROR(IF(ISBLANK(INDEX(RAW_key_statistics!$CH$2:$CH$957,$AL4)),"",INDEX(RAW_key_statistics!$CH$2:$CH$957,$AL4)),"") | P4: =IFERROR(IF(ISBLANK(INDEX(RAW_key_statistics!$CK$2:$CK$957,$AL4)),"",INDEX(RAW_key_statistics!$CK$2:$CK$957,$AL4)),"") | Q4: =IFERROR(IF(ISBLANK(INDEX(RAW_key_statistics!$BB$2:$BB$957,$AL4)),"",INDEX(RAW_key_statistics!$BB$2:$BB$957,$AL4)),"") | R4: =IFERROR(IF(ISBLANK(INDEX(RAW_key_statistics!$AE$2:$AE$957,$AL4)),"",INDEX(RAW_key_statistics!$AE$2:$AE$957,$AL4)),"") | S4: =IFERROR(IF(ISBLANK(INDEX(RAW_key_statistics!$V$2:$V$957,$AL4)),"",INDEX(RAW_key_statistics!$V$2:$V$957,$AL4)),"") | T4: =IFERROR(IF(ISBLANK(INDEX(RAW_analyses!$N$2:$N$957,$AO4)),"",INDEX(RAW_analyses!$N$2:$N$957,$AO4)),"") | U4: =IFERROR(IF(ISBLANK(INDEX(RAW_key_statistics!$CU$2:$CU$957,$AL4)),"",INDEX(RAW_key_statistics!$CU$2:$CU$957,$AL4)),"") | V4: =IFERROR(IF(ISBLANK(INDEX(RAW_key_statistics!$CM$2:$CM$957,$AL4)),"",INDEX(RAW_key_statistics!$CM$2:$CM$957,$AL4)),"") | W4: =IFERROR(IF(ISBLANK(INDEX(RAW_key_statistics!$CN$2:$CN$957,$AL4)),"",INDEX(RAW_key_statistics!$CN$2:$CN$957,$AL4)),"") | X4: =IFERROR(IF(ISBLANK(INDEX(RAW_key_statistics!$CR$2:$CR$957,$AL4)),"",INDEX(RAW_key_statistics!$CR$2:$CR$957,$AL4)),"") | Y4: =IFERROR(IF(ISBLANK(INDEX(RAW_scores!$R$2:$R$957,$AM4)),"",INDEX(RAW_scores!$R$2:$R$957,$AM4)),"") | Z4: =IFERROR(IF(ISBLANK(INDEX(RAW_scores!$S$2:$S$957,$AM4)),"",INDEX(RAW_scores!$S$2:$S$957,$AM4)),"") | AA4: =IFERROR(IF(ISBLANK(INDEX(RAW_scores!$T$2:$T$957,$AM4)),"",INDEX(RAW_scores!$T$2:$T$957,$AM4)),"") | AB4: =IFERROR(IF(ISBLANK(INDEX(RAW_scores!$X$2:$X$957,$AM4)),"",INDEX(RAW_scores!$X$2:$X$957,$AM4)),"") | AC4: =IFERROR(IF(ISBLANK(INDEX(RAW_scores!$Y$2:$Y$957,$AM4)),"",INDEX(RAW_scores!$Y$2:$Y$957,$AM4)),"") | AD4: =IFERROR(IF(ISBLANK(INDEX(RAW_scores!$Z$2:$Z$957,$AM4)),"",INDEX(RAW_scores!$Z$2:$Z$957,$AM4)),"") | AE4: =IFERROR(IF(ISBLANK(INDEX(RAW_scores!$F$2:$F$957,$AM4)),"",INDEX(RAW_scores!$F$2:$F$957,$AM4)),"") | AF4: =IFERROR(IF(ISBLANK(INDEX(RAW_scores!$G$2:$G$957,$AM4)),"",INDEX(RAW_scores!$G$2:$G$957,$AM4)),"") | AG4: =IFERROR(IF(ISBLANK(INDEX(RAW_scores!$H$2:$H$957,$AM4)),"",INDEX(RAW_scores!$H$2:$H$957,$AM4)),"") | AH4: =IFERROR(IF(ISBLANK(INDEX(RAW_scores!$I$2:$I$957,$AM4)),"",INDEX(RAW_scores!$I$2:$I$957,$AM4)),"") | AI4: =IFERROR(IF(ISBLANK(INDEX(RAW_scores!$AA$2:$AA$957,$AM4)),"",INDEX(RAW_scores!$AA$2:$AA$957,$AM4)),"") | AJ4: =IFERROR(IF(ISBLANK(INDEX(RAW_scores!$AF$2:$AF$957,$AM4)),"",INDEX(RAW_scores!$AF$2:$AF$957,$AM4)),"") | AK4: =IFERROR(IF(ISBLANK(INDEX(RAW_scores!$AC$2:$AC$957,$AM4)),"",INDEX(RAW_scores!$AC$2:$AC$957,$AM4)),"") | AL4: =IFERROR(MATCH($A4,RAW_key_statistics!$A$2:$A$957,0),"") | AM4: =IFERROR(MATCH($A4,RAW_scores!$A$2:$A$957,0),"") | AN4: =IFERROR(MATCH($A4,RAW_idx_stocks!$A$2:$A$957,0),"") | AO4: =IFERROR(MATCH($A4,RAW_analyses!$A$2:$A$957,0),"")
A5: ABDA | B5: =IFERROR(IF(ISBLANK(INDEX(RAW_scores!$B$2:$B$957,$AM5)),"",INDEX(RAW_scores!$B$2:$B$957,$AM5)),"") | C5: =IFERROR(IF(ISBLANK(INDEX(RAW_scores!$C$2:$C$957,$AM5)),"",INDEX(RAW_scores!$C$2:$C$957,$AM5)),"") | D5: =IFERROR(IF(ISBLANK(INDEX(RAW_scores!$D$2:$D$957,$AM5)),"",INDEX(RAW_scores!$D$2:$D$957,$AM5)),"") | E5: =IFERROR(IF(ISBLANK(INDEX(RAW_idx_stocks!$F$2:$F$957,$AN5)),"",INDEX(RAW_idx_stocks!$F$2:$F$957,$AN5)),"") | F5: =IFERROR(IF(ISBLANK(INDEX(RAW_key_statistics!$BS$2:$BS$957,$AL5)),"",INDEX(RAW_key_statistics!$BS$2:$BS$957,$AL5)/1000000000),"") | G5: =IFERROR(IF(ISBLANK(INDEX(RAW_key_statistics!$C$2:$C$957,$AL5)),"",INDEX(RAW_key_statistics!$C$2:$C$957,$AL5)),"") | H5: =IFERROR(IF(ISBLANK(INDEX(RAW_key_statistics!$H$2:$H$957,$AL5)),"",INDEX(RAW_key_statistics!$H$2:$H$957,$AL5)),"") | I5: =IFERROR(IF(ISBLANK(INDEX(RAW_key_statistics!$K$2:$K$957,$AL5)),"",INDEX(RAW_key_statistics!$K$2:$K$957,$AL5)),"") | J5: =IFERROR(IF(ISBLANK(INDEX(RAW_key_statistics!$L$2:$L$957,$AL5)),"",INDEX(RAW_key_statistics!$L$2:$L$957,$AL5)),"") | K5: =IFERROR(IF(ISBLANK(INDEX(RAW_key_statistics!$AZ$2:$AZ$957,$AL5)),"",INDEX(RAW_key_statistics!$AZ$2:$AZ$957,$AL5)),"") | L5: =IFERROR(IF(ISBLANK(INDEX(RAW_key_statistics!$AG$2:$AG$957,$AL5)),"",INDEX(RAW_key_statistics!$AG$2:$AG$957,$AL5)),"") | M5: =IFERROR(IF(ISBLANK(INDEX(RAW_key_statistics!$AI$2:$AI$957,$AL5)),"",INDEX(RAW_key_statistics!$AI$2:$AI$957,$AL5)),"") | N5: =IFERROR(IF(ISBLANK(INDEX(RAW_key_statistics!$CI$2:$CI$957,$AL5)),"",INDEX(RAW_key_statistics!$CI$2:$CI$957,$AL5)),"") | O5: =IFERROR(IF(ISBLANK(INDEX(RAW_key_statistics!$CH$2:$CH$957,$AL5)),"",INDEX(RAW_key_statistics!$CH$2:$CH$957,$AL5)),"") | P5: =IFERROR(IF(ISBLANK(INDEX(RAW_key_statistics!$CK$2:$CK$957,$AL5)),"",INDEX(RAW_key_statistics!$CK$2:$CK$957,$AL5)),"") | Q5: =IFERROR(IF(ISBLANK(INDEX(RAW_key_statistics!$BB$2:$BB$957,$AL5)),"",INDEX(RAW_key_statistics!$BB$2:$BB$957,$AL5)),"") | R5: =IFERROR(IF(ISBLANK(INDEX(RAW_key_statistics!$AE$2:$AE$957,$AL5)),"",INDEX(RAW_key_statistics!$AE$2:$AE$957,$AL5)),"") | S5: =IFERROR(IF(ISBLANK(INDEX(RAW_key_statistics!$V$2:$V$957,$AL5)),"",INDEX(RAW_key_statistics!$V$2:$V$957,$AL5)),"") | T5: =IFERROR(IF(ISBLANK(INDEX(RAW_analyses!$N$2:$N$957,$AO5)),"",INDEX(RAW_analyses!$N$2:$N$957,$AO5)),"") | U5: =IFERROR(IF(ISBLANK(INDEX(RAW_key_statistics!$CU$2:$CU$957,$AL5)),"",INDEX(RAW_key_statistics!$CU$2:$CU$957,$AL5)),"") | V5: =IFERROR(IF(ISBLANK(INDEX(RAW_key_statistics!$CM$2:$CM$957,$AL5)),"",INDEX(RAW_key_statistics!$CM$2:$CM$957,$AL5)),"") | W5: =IFERROR(IF(ISBLANK(INDEX(RAW_key_statistics!$CN$2:$CN$957,$AL5)),"",INDEX(RAW_key_statistics!$CN$2:$CN$957,$AL5)),"") | X5: =IFERROR(IF(ISBLANK(INDEX(RAW_key_statistics!$CR$2:$CR$957,$AL5)),"",INDEX(RAW_key_statistics!$CR$2:$CR$957,$AL5)),"") | Y5: =IFERROR(IF(ISBLANK(INDEX(RAW_scores!$R$2:$R$957,$AM5)),"",INDEX(RAW_scores!$R$2:$R$957,$AM5)),"") | Z5: =IFERROR(IF(ISBLANK(INDEX(RAW_scores!$S$2:$S$957,$AM5)),"",INDEX(RAW_scores!$S$2:$S$957,$AM5)),"") | AA5: =IFERROR(IF(ISBLANK(INDEX(RAW_scores!$T$2:$T$957,$AM5)),"",INDEX(RAW_scores!$T$2:$T$957,$AM5)),"") | AB5: =IFERROR(IF(ISBLANK(INDEX(RAW_scores!$X$2:$X$957,$AM5)),"",INDEX(RAW_scores!$X$2:$X$957,$AM5)),"") | AC5: =IFERROR(IF(ISBLANK(INDEX(RAW_scores!$Y$2:$Y$957,$AM5)),"",INDEX(RAW_scores!$Y$2:$Y$957,$AM5)),"") | AD5: =IFERROR(IF(ISBLANK(INDEX(RAW_scores!$Z$2:$Z$957,$AM5)),"",INDEX(RAW_scores!$Z$2:$Z$957,$AM5)),"") | AE5: =IFERROR(IF(ISBLANK(INDEX(RAW_scores!$F$2:$F$957,$AM5)),"",INDEX(RAW_scores!$F$2:$F$957,$AM5)),"") | AF5: =IFERROR(IF(ISBLANK(INDEX(RAW_scores!$G$2:$G$957,$AM5)),"",INDEX(RAW_scores!$G$2:$G$957,$AM5)),"") | AG5: =IFERROR(IF(ISBLANK(INDEX(RAW_scores!$H$2:$H$957,$AM5)),"",INDEX(RAW_scores!$H$2:$H$957,$AM5)),"") | AH5: =IFERROR(IF(ISBLANK(INDEX(RAW_scores!$I$2:$I$957,$AM5)),"",INDEX(RAW_scores!$I$2:$I$957,$AM5)),"") | AI5: =IFERROR(IF(ISBLANK(INDEX(RAW_scores!$AA$2:$AA$957,$AM5)),"",INDEX(RAW_scores!$AA$2:$AA$957,$AM5)),"") | AJ5: =IFERROR(IF(ISBLANK(INDEX(RAW_scores!$AF$2:$AF$957,$AM5)),"",INDEX(RAW_scores!$AF$2:$AF$957,$AM5)),"") | AK5: =IFERROR(IF(ISBLANK(INDEX(RAW_scores!$AC$2:$AC$957,$AM5)),"",INDEX(RAW_scores!$AC$2:$AC$957,$AM5)),"") | AL5: =IFERROR(MATCH($A5,RAW_key_statistics!$A$2:$A$957,0),"") | AM5: =IFERROR(MATCH($A5,RAW_scores!$A$2:$A$957,0),"") | AN5: =IFERROR(MATCH($A5,RAW_idx_stocks!$A$2:$A$957,0),"") | AO5: =IFERROR(MATCH($A5,RAW_analyses!$A$2:$A$957,0),"")
A6: ABMM | B6: =IFERROR(IF(ISBLANK(INDEX(RAW_scores!$B$2:$B$957,$AM6)),"",INDEX(RAW_scores!$B$2:$B$957,$AM6)),"") | C6: =IFERROR(IF(ISBLANK(INDEX(RAW_scores!$C$2:$C$957,$AM6)),"",INDEX(RAW_scores!$C$2:$C$957,$AM6)),"") | D6: =IFERROR(IF(ISBLANK(INDEX(RAW_scores!$D$2:$D$957,$AM6)),"",INDEX(RAW_scores!$D$2:$D$957,$AM6)),"") | E6: =IFERROR(IF(ISBLANK(INDEX(RAW_idx_stocks!$F$2:$F$957,$AN6)),"",INDEX(RAW_idx_stocks!$F$2:$F$957,$AN6)),"") | F6: =IFERROR(IF(ISBLANK(INDEX(RAW_key_statistics!$BS$2:$BS$957,$AL6)),"",INDEX(RAW_key_statistics!$BS$2:$BS$957,$AL6)/1000000000),"") | G6: =IFERROR(IF(ISBLANK(INDEX(RAW_key_statistics!$C$2:$C$957,$AL6)),"",INDEX(RAW_key_statistics!$C$2:$C$957,$AL6)),"") | H6: =IFERROR(IF(ISBLANK(INDEX(RAW_key_statistics!$H$2:$H$957,$AL6)),"",INDEX(RAW_key_statistics!$H$2:$H$957,$AL6)),"") | I6: =IFERROR(IF(ISBLANK(INDEX(RAW_key_statistics!$K$2:$K$957,$AL6)),"",INDEX(RAW_key_statistics!$K$2:$K$957,$AL6)),"") | J6: =IFERROR(IF(ISBLANK(INDEX(RAW_key_statistics!$L$2:$L$957,$AL6)),"",INDEX(RAW_key_statistics!$L$2:$L$957,$AL6)),"") | K6: =IFERROR(IF(ISBLANK(INDEX(RAW_key_statistics!$AZ$2:$AZ$957,$AL6)),"",INDEX(RAW_key_statistics!$AZ$2:$AZ$957,$AL6)),"") | L6: =IFERROR(IF(ISBLANK(INDEX(RAW_key_statistics!$AG$2:$AG$957,$AL6)),"",INDEX(RAW_key_statistics!$AG$2:$AG$957,$AL6)),"") | M6: =IFERROR(IF(ISBLANK(INDEX(RAW_key_statistics!$AI$2:$AI$957,$AL6)),"",INDEX(RAW_key_statistics!$AI$2:$AI$957,$AL6)),"") | N6: =IFERROR(IF(ISBLANK(INDEX(RAW_key_statistics!$CI$2:$CI$957,$AL6)),"",INDEX(RAW_key_statistics!$CI$2:$CI$957,$AL6)),"") | O6: =IFERROR(IF(ISBLANK(INDEX(RAW_key_statistics!$CH$2:$CH$957,$AL6)),"",INDEX(RAW_key_statistics!$CH$2:$CH$957,$AL6)),"") | P6: =IFERROR(IF(ISBLANK(INDEX(RAW_key_statistics!$CK$2:$CK$957,$AL6)),"",INDEX(RAW_key_statistics!$CK$2:$CK$957,$AL6)),"") | Q6: =IFERROR(IF(ISBLANK(INDEX(RAW_key_statistics!$BB$2:$BB$957,$AL6)),"",INDEX(RAW_key_statistics!$BB$2:$BB$957,$AL6)),"") | R6: =IFERROR(IF(ISBLANK(INDEX(RAW_key_statistics!$AE$2:$AE$957,$AL6)),"",INDEX(RAW_key_statistics!$AE$2:$AE$957,$AL6)),"") | S6: =IFERROR(IF(ISBLANK(INDEX(RAW_key_statistics!$V$2:$V$957,$AL6)),"",INDEX(RAW_key_statistics!$V$2:$V$957,$AL6)),"") | T6: =IFERROR(IF(ISBLANK(INDEX(RAW_analyses!$N$2:$N$957,$AO6)),"",INDEX(RAW_analyses!$N$2:$N$957,$AO6)),"") | U6: =IFERROR(IF(ISBLANK(INDEX(RAW_key_statistics!$CU$2:$CU$957,$AL6)),"",INDEX(RAW_key_statistics!$CU$2:$CU$957,$AL6)),"") | V6: =IFERROR(IF(ISBLANK(INDEX(RAW_key_statistics!$CM$2:$CM$957,$AL6)),"",INDEX(RAW_key_statistics!$CM$2:$CM$957,$AL6)),"") | W6: =IFERROR(IF(ISBLANK(INDEX(RAW_key_statistics!$CN$2:$CN$957,$AL6)),"",INDEX(RAW_key_statistics!$CN$2:$CN$957,$AL6)),"") | X6: =IFERROR(IF(ISBLANK(INDEX(RAW_key_statistics!$CR$2:$CR$957,$AL6)),"",INDEX(RAW_key_statistics!$CR$2:$CR$957,$AL6)),"") | Y6: =IFERROR(IF(ISBLANK(INDEX(RAW_scores!$R$2:$R$957,$AM6)),"",INDEX(RAW_scores!$R$2:$R$957,$AM6)),"") | Z6: =IFERROR(IF(ISBLANK(INDEX(RAW_scores!$S$2:$S$957,$AM6)),"",INDEX(RAW_scores!$S$2:$S$957,$AM6)),"") | AA6: =IFERROR(IF(ISBLANK(INDEX(RAW_scores!$T$2:$T$957,$AM6)),"",INDEX(RAW_scores!$T$2:$T$957,$AM6)),"") | AB6: =IFERROR(IF(ISBLANK(INDEX(RAW_scores!$X$2:$X$957,$AM6)),"",INDEX(RAW_scores!$X$2:$X$957,$AM6)),"") | AC6: =IFERROR(IF(ISBLANK(INDEX(RAW_scores!$Y$2:$Y$957,$AM6)),"",INDEX(RAW_scores!$Y$2:$Y$957,$AM6)),"") | AD6: =IFERROR(IF(ISBLANK(INDEX(RAW_scores!$Z$2:$Z$957,$AM6)),"",INDEX(RAW_scores!$Z$2:$Z$957,$AM6)),"") | AE6: =IFERROR(IF(ISBLANK(INDEX(RAW_scores!$F$2:$F$957,$AM6)),"",INDEX(RAW_scores!$F$2:$F$957,$AM6)),"") | AF6: =IFERROR(IF(ISBLANK(INDEX(RAW_scores!$G$2:$G$957,$AM6)),"",INDEX(RAW_scores!$G$2:$G$957,$AM6)),"") | AG6: =IFERROR(IF(ISBLANK(INDEX(RAW_scores!$H$2:$H$957,$AM6)),"",INDEX(RAW_scores!$H$2:$H$957,$AM6)),"") | AH6: =IFERROR(IF(ISBLANK(INDEX(RAW_scores!$I$2:$I$957,$AM6)),"",INDEX(RAW_scores!$I$2:$I$957,$AM6)),"") | AI6: =IFERROR(IF(ISBLANK(INDEX(RAW_scores!$AA$2:$AA$957,$AM6)),"",INDEX(RAW_scores!$AA$2:$AA$957,$AM6)),"") | AJ6: =IFERROR(IF(ISBLANK(INDEX(RAW_scores!$AF$2:$AF$957,$AM6)),"",INDEX(RAW_scores!$AF$2:$AF$957,$AM6)),"") | AK6: =IFERROR(IF(ISBLANK(INDEX(RAW_scores!$AC$2:$AC$957,$AM6)),"",INDEX(RAW_scores!$AC$2:$AC$957,$AM6)),"") | AL6: =IFERROR(MATCH($A6,RAW_key_statistics!$A$2:$A$957,0),"") | AM6: =IFERROR(MATCH($A6,RAW_scores!$A$2:$A$957,0),"") | AN6: =IFERROR(MATCH($A6,RAW_idx_stocks!$A$2:$A$957,0),"") | AO6: =IFERROR(MATCH($A6,RAW_analyses!$A$2:$A$957,0),"")
A7: ACES | B7: =IFERROR(IF(ISBLANK(INDEX(RAW_scores!$B$2:$B$957,$AM7)),"",INDEX(RAW_scores!$B$2:$B$957,$AM7)),"") | C7: =IFERROR(IF(ISBLANK(INDEX(RAW_scores!$C$2:$C$957,$AM7)),"",INDEX(RAW_scores!$C$2:$C$957,$AM7)),"") | D7: =IFERROR(IF(ISBLANK(INDEX(RAW_scores!$D$2:$D$957,$AM7)),"",INDEX(RAW_scores!$D$2:$D$957,$AM7)),"") | E7: =IFERROR(IF(ISBLANK(INDEX(RAW_idx_stocks!$F$2:$F$957,$AN7)),"",INDEX(RAW_idx_stocks!$F$2:$F$957,$AN7)),"") | F7: =IFERROR(IF(ISBLANK(INDEX(RAW_key_statistics!$BS$2:$BS$957,$AL7)),"",INDEX(RAW_key_statistics!$BS$2:$BS$957,$AL7)/1000000000),"") | G7: =IFERROR(IF(ISBLANK(INDEX(RAW_key_statistics!$C$2:$C$957,$AL7)),"",INDEX(RAW_key_statistics!$C$2:$C$957,$AL7)),"") | H7: =IFERROR(IF(ISBLANK(INDEX(RAW_key_statistics!$H$2:$H$957,$AL7)),"",INDEX(RAW_key_statistics!$H$2:$H$957,$AL7)),"") | I7: =IFERROR(IF(ISBLANK(INDEX(RAW_key_statistics!$K$2:$K$957,$AL7)),"",INDEX(RAW_key_statistics!$K$2:$K$957,$AL7)),"") | J7: =IFERROR(IF(ISBLANK(INDEX(RAW_key_statistics!$L$2:$L$957,$AL7)),"",INDEX(RAW_key_statistics!$L$2:$L$957,$AL7)),"") | K7: =IFERROR(IF(ISBLANK(INDEX(RAW_key_statistics!$AZ$2:$AZ$957,$AL7)),"",INDEX(RAW_key_statistics!$AZ$2:$AZ$957,$AL7)),"") | L7: =IFERROR(IF(ISBLANK(INDEX(RAW_key_statistics!$AG$2:$AG$957,$AL7)),"",INDEX(RAW_key_statistics!$AG$2:$AG$957,$AL7)),"") | M7: =IFERROR(IF(ISBLANK(INDEX(RAW_key_statistics!$AI$2:$AI$957,$AL7)),"",INDEX(RAW_key_statistics!$AI$2:$AI$957,$AL7)),"") | N7: =IFERROR(IF(ISBLANK(INDEX(RAW_key_statistics!$CI$2:$CI$957,$AL7)),"",INDEX(RAW_key_statistics!$CI$2:$CI$957,$AL7)),"") | O7: =IFERROR(IF(ISBLANK(INDEX(RAW_key_statistics!$CH$2:$CH$957,$AL7)),"",INDEX(RAW_key_statistics!$CH$2:$CH$957,$AL7)),"") | P7: =IFERROR(IF(ISBLANK(INDEX(RAW_key_statistics!$CK$2:$CK$957,$AL7)),"",INDEX(RAW_key_statistics!$CK$2:$CK$957,$AL7)),"") | Q7: =IFERROR(IF(ISBLANK(INDEX(RAW_key_statistics!$BB$2:$BB$957,$AL7)),"",INDEX(RAW_key_statistics!$BB$2:$BB$957,$AL7)),"") | R7: =IFERROR(IF(ISBLANK(INDEX(RAW_key_statistics!$AE$2:$AE$957,$AL7)),"",INDEX(RAW_key_statistics!$AE$2:$AE$957,$AL7)),"") | S7: =IFERROR(IF(ISBLANK(INDEX(RAW_key_statistics!$V$2:$V$957,$AL7)),"",INDEX(RAW_key_statistics!$V$2:$V$957,$AL7)),"") | T7: =IFERROR(IF(ISBLANK(INDEX(RAW_analyses!$N$2:$N$957,$AO7)),"",INDEX(RAW_analyses!$N$2:$N$957,$AO7)),"") | U7: =IFERROR(IF(ISBLANK(INDEX(RAW_key_statistics!$CU$2:$CU$957,$AL7)),"",INDEX(RAW_key_statistics!$CU$2:$CU$957,$AL7)),"") | V7: =IFERROR(IF(ISBLANK(INDEX(RAW_key_statistics!$CM$2:$CM$957,$AL7)),"",INDEX(RAW_key_statistics!$CM$2:$CM$957,$AL7)),"") | W7: =IFERROR(IF(ISBLANK(INDEX(RAW_key_statistics!$CN$2:$CN$957,$AL7)),"",INDEX(RAW_key_statistics!$CN$2:$CN$957,$AL7)),"") | X7: =IFERROR(IF(ISBLANK(INDEX(RAW_key_statistics!$CR$2:$CR$957,$AL7)),"",INDEX(RAW_key_statistics!$CR$2:$CR$957,$AL7)),"") | Y7: =IFERROR(IF(ISBLANK(INDEX(RAW_scores!$R$2:$R$957,$AM7)),"",INDEX(RAW_scores!$R$2:$R$957,$AM7)),"") | Z7: =IFERROR(IF(ISBLANK(INDEX(RAW_scores!$S$2:$S$957,$AM7)),"",INDEX(RAW_scores!$S$2:$S$957,$AM7)),"") | AA7: =IFERROR(IF(ISBLANK(INDEX(RAW_scores!$T$2:$T$957,$AM7)),"",INDEX(RAW_scores!$T$2:$T$957,$AM7)),"") | AB7: =IFERROR(IF(ISBLANK(INDEX(RAW_scores!$X$2:$X$957,$AM7)),"",INDEX(RAW_scores!$X$2:$X$957,$AM7)),"") | AC7: =IFERROR(IF(ISBLANK(INDEX(RAW_scores!$Y$2:$Y$957,$AM7)),"",INDEX(RAW_scores!$Y$2:$Y$957,$AM7)),"") | AD7: =IFERROR(IF(ISBLANK(INDEX(RAW_scores!$Z$2:$Z$957,$AM7)),"",INDEX(RAW_scores!$Z$2:$Z$957,$AM7)),"") | AE7: =IFERROR(IF(ISBLANK(INDEX(RAW_scores!$F$2:$F$957,$AM7)),"",INDEX(RAW_scores!$F$2:$F$957,$AM7)),"") | AF7: =IFERROR(IF(ISBLANK(INDEX(RAW_scores!$G$2:$G$957,$AM7)),"",INDEX(RAW_scores!$G$2:$G$957,$AM7)),"") | AG7: =IFERROR(IF(ISBLANK(INDEX(RAW_scores!$H$2:$H$957,$AM7)),"",INDEX(RAW_scores!$H$2:$H$957,$AM7)),"") | AH7: =IFERROR(IF(ISBLANK(INDEX(RAW_scores!$I$2:$I$957,$AM7)),"",INDEX(RAW_scores!$I$2:$I$957,$AM7)),"") | AI7: =IFERROR(IF(ISBLANK(INDEX(RAW_scores!$AA$2:$AA$957,$AM7)),"",INDEX(RAW_scores!$AA$2:$AA$957,$AM7)),"") | AJ7: =IFERROR(IF(ISBLANK(INDEX(RAW_scores!$AF$2:$AF$957,$AM7)),"",INDEX(RAW_scores!$AF$2:$AF$957,$AM7)),"") | AK7: =IFERROR(IF(ISBLANK(INDEX(RAW_scores!$AC$2:$AC$957,$AM7)),"",INDEX(RAW_scores!$AC$2:$AC$957,$AM7)),"") | AL7: =IFERROR(MATCH($A7,RAW_key_statistics!$A$2:$A$957,0),"") | AM7: =IFERROR(MATCH($A7,RAW_scores!$A$2:$A$957,0),"") | AN7: =IFERROR(MATCH($A7,RAW_idx_stocks!$A$2:$A$957,0),"") | AO7: =IFERROR(MATCH($A7,RAW_analyses!$A$2:$A$957,0),"")
A8: ACRO | B8: =IFERROR(IF(ISBLANK(INDEX(RAW_scores!$B$2:$B$957,$AM8)),"",INDEX(RAW_scores!$B$2:$B$957,$AM8)),"") | C8: =IFERROR(IF(ISBLANK(INDEX(RAW_scores!$C$2:$C$957,$AM8)),"",INDEX(RAW_scores!$C$2:$C$957,$AM8)),"") | D8: =IFERROR(IF(ISBLANK(INDEX(RAW_scores!$D$2:$D$957,$AM8)),"",INDEX(RAW_scores!$D$2:$D$957,$AM8)),"") | E8: =IFERROR(IF(ISBLANK(INDEX(RAW_idx_stocks!$F$2:$F$957,$AN8)),"",INDEX(RAW_idx_stocks!$F$2:$F$957,$AN8)),"") | F8: =IFERROR(IF(ISBLANK(INDEX(RAW_key_statistics!$BS$2:$BS$957,$AL8)),"",INDEX(RAW_key_statistics!$BS$2:$BS$957,$AL8)/1000000000),"") | G8: =IFERROR(IF(ISBLANK(INDEX(RAW_key_statistics!$C$2:$C$957,$AL8)),"",INDEX(RAW_key_statistics!$C$2:$C$957,$AL8)),"") | H8: =IFERROR(IF(ISBLANK(INDEX(RAW_key_statistics!$H$2:$H$957,$AL8)),"",INDEX(RAW_key_statistics!$H$2:$H$957,$AL8)),"") | I8: =IFERROR(IF(ISBLANK(INDEX(RAW_key_statistics!$K$2:$K$957,$AL8)),"",INDEX(RAW_key_statistics!$K$2:$K$957,$AL8)),"") | J8: =IFERROR(IF(ISBLANK(INDEX(RAW_key_statistics!$L$2:$L$957,$AL8)),"",INDEX(RAW_key_statistics!$L$2:$L$957,$AL8)),"") | K8: =IFERROR(IF(ISBLANK(INDEX(RAW_key_statistics!$AZ$2:$AZ$957,$AL8)),"",INDEX(RAW_key_statistics!$AZ$2:$AZ$957,$AL8)),"") | L8: =IFERROR(IF(ISBLANK(INDEX(RAW_key_statistics!$AG$2:$AG$957,$AL8)),"",INDEX(RAW_key_statistics!$AG$2:$AG$957,$AL8)),"") | M8: =IFERROR(IF(ISBLANK(INDEX(RAW_key_statistics!$AI$2:$AI$957,$AL8)),"",INDEX(RAW_key_statistics!$AI$2:$AI$957,$AL8)),"") | N8: =IFERROR(IF(ISBLANK(INDEX(RAW_key_statistics!$CI$2:$CI$957,$AL8)),"",INDEX(RAW_key_statistics!$CI$2:$CI$957,$AL8)),"") | O8: =IFERROR(IF(ISBLANK(INDEX(RAW_key_statistics!$CH$2:$CH$957,$AL8)),"",INDEX(RAW_key_statistics!$CH$2:$CH$957,$AL8)),"") | P8: =IFERROR(IF(ISBLANK(INDEX(RAW_key_statistics!$CK$2:$CK$957,$AL8)),"",INDEX(RAW_key_statistics!$CK$2:$CK$957,$AL8)),"") | Q8: =IFERROR(IF(ISBLANK(INDEX(RAW_key_statistics!$BB$2:$BB$957,$AL8)),"",INDEX(RAW_key_statistics!$BB$2:$BB$957,$AL8)),"") | R8: =IFERROR(IF(ISBLANK(INDEX(RAW_key_statistics!$AE$2:$AE$957,$AL8)),"",INDEX(RAW_key_statistics!$AE$2:$AE$957,$AL8)),"") | S8: =IFERROR(IF(ISBLANK(INDEX(RAW_key_statistics!$V$2:$V$957,$AL8)),"",INDEX(RAW_key_statistics!$V$2:$V$957,$AL8)),"") | T8: =IFERROR(IF(ISBLANK(INDEX(RAW_analyses!$N$2:$N$957,$AO8)),"",INDEX(RAW_analyses!$N$2:$N$957,$AO8)),"") | U8: =IFERROR(IF(ISBLANK(INDEX(RAW_key_statistics!$CU$2:$CU$957,$AL8)),"",INDEX(RAW_key_statistics!$CU$2:$CU$957,$AL8)),"") | V8: =IFERROR(IF(ISBLANK(INDEX(RAW_key_statistics!$CM$2:$CM$957,$AL8)),"",INDEX(RAW_key_statistics!$CM$2:$CM$957,$AL8)),"") | W8: =IFERROR(IF(ISBLANK(INDEX(RAW_key_statistics!$CN$2:$CN$957,$AL8)),"",INDEX(RAW_key_statistics!$CN$2:$CN$957,$AL8)),"") | X8: =IFERROR(IF(ISBLANK(INDEX(RAW_key_statistics!$CR$2:$CR$957,$AL8)),"",INDEX(RAW_key_statistics!$CR$2:$CR$957,$AL8)),"") | Y8: =IFERROR(IF(ISBLANK(INDEX(RAW_scores!$R$2:$R$957,$AM8)),"",INDEX(RAW_scores!$R$2:$R$957,$AM8)),"") | Z8: =IFERROR(IF(ISBLANK(INDEX(RAW_scores!$S$2:$S$957,$AM8)),"",INDEX(RAW_scores!$S$2:$S$957,$AM8)),"") | AA8: =IFERROR(IF(ISBLANK(INDEX(RAW_scores!$T$2:$T$957,$AM8)),"",INDEX(RAW_scores!$T$2:$T$957,$AM8)),"") | AB8: =IFERROR(IF(ISBLANK(INDEX(RAW_scores!$X$2:$X$957,$AM8)),"",INDEX(RAW_scores!$X$2:$X$957,$AM8)),"") | AC8: =IFERROR(IF(ISBLANK(INDEX(RAW_scores!$Y$2:$Y$957,$AM8)),"",INDEX(RAW_scores!$Y$2:$Y$957,$AM8)),"") | AD8: =IFERROR(IF(ISBLANK(INDEX(RAW_scores!$Z$2:$Z$957,$AM8)),"",INDEX(RAW_scores!$Z$2:$Z$957,$AM8)),"") | AE8: =IFERROR(IF(ISBLANK(INDEX(RAW_scores!$F$2:$F$957,$AM8)),"",INDEX(RAW_scores!$F$2:$F$957,$AM8)),"") | AF8: =IFERROR(IF(ISBLANK(INDEX(RAW_scores!$G$2:$G$957,$AM8)),"",INDEX(RAW_scores!$G$2:$G$957,$AM8)),"") | AG8: =IFERROR(IF(ISBLANK(INDEX(RAW_scores!$H$2:$H$957,$AM8)),"",INDEX(RAW_scores!$H$2:$H$957,$AM8)),"") | AH8: =IFERROR(IF(ISBLANK(INDEX(RAW_scores!$I$2:$I$957,$AM8)),"",INDEX(RAW_scores!$I$2:$I$957,$AM8)),"") | AI8: =IFERROR(IF(ISBLANK(INDEX(RAW_scores!$AA$2:$AA$957,$AM8)),"",INDEX(RAW_scores!$AA$2:$AA$957,$AM8)),"") | AJ8: =IFERROR(IF(ISBLANK(INDEX(RAW_scores!$AF$2:$AF$957,$AM8)),"",INDEX(RAW_scores!$AF$2:$AF$957,$AM8)),"") | AK8: =IFERROR(IF(ISBLANK(INDEX(RAW_scores!$AC$2:$AC$957,$AM8)),"",INDEX(RAW_scores!$AC$2:$AC$957,$AM8)),"") | AL8: =IFERROR(MATCH($A8,RAW_key_statistics!$A$2:$A$957,0),"") | AM8: =IFERROR(MATCH($A8,RAW_scores!$A$2:$A$957,0),"") | AN8: =IFERROR(MATCH($A8,RAW_idx_stocks!$A$2:$A$957,0),"") | AO8: =IFERROR(MATCH($A8,RAW_analyses!$A$2:$A$957,0),"")
A9: ACST | B9: =IFERROR(IF(ISBLANK(INDEX(RAW_scores!$B$2:$B$957,$AM9)),"",INDEX(RAW_scores!$B$2:$B$957,$AM9)),"") | C9: =IFERROR(IF(ISBLANK(INDEX(RAW_scores!$C$2:$C$957,$AM9)),"",INDEX(RAW_scores!$C$2:$C$957,$AM9)),"") | D9: =IFERROR(IF(ISBLANK(INDEX(RAW_scores!$D$2:$D$957,$AM9)),"",INDEX(RAW_scores!$D$2:$D$957,$AM9)),"") | E9: =IFERROR(IF(ISBLANK(INDEX(RAW_idx_stocks!$F$2:$F$957,$AN9)),"",INDEX(RAW_idx_stocks!$F$2:$F$957,$AN9)),"") | F9: =IFERROR(IF(ISBLANK(INDEX(RAW_key_statistics!$BS$2:$BS$957,$AL9)),"",INDEX(RAW_key_statistics!$BS$2:$BS$957,$AL9)/1000000000),"") | G9: =IFERROR(IF(ISBLANK(INDEX(RAW_key_statistics!$C$2:$C$957,$AL9)),"",INDEX(RAW_key_statistics!$C$2:$C$957,$AL9)),"") | H9: =IFERROR(IF(ISBLANK(INDEX(RAW_key_statistics!$H$2:$H$957,$AL9)),"",INDEX(RAW_key_statistics!$H$2:$H$957,$AL9)),"") | I9: =IFERROR(IF(ISBLANK(INDEX(RAW_key_statistics!$K$2:$K$957,$AL9)),"",INDEX(RAW_key_statistics!$K$2:$K$957,$AL9)),"") | J9: =IFERROR(IF(ISBLANK(INDEX(RAW_key_statistics!$L$2:$L$957,$AL9)),"",INDEX(RAW_key_statistics!$L$2:$L$957,$AL9)),"") | K9: =IFERROR(IF(ISBLANK(INDEX(RAW_key_statistics!$AZ$2:$AZ$957,$AL9)),"",INDEX(RAW_key_statistics!$AZ$2:$AZ$957,$AL9)),"") | L9: =IFERROR(IF(ISBLANK(INDEX(RAW_key_statistics!$AG$2:$AG$957,$AL9)),"",INDEX(RAW_key_statistics!$AG$2:$AG$957,$AL9)),"") | M9: =IFERROR(IF(ISBLANK(INDEX(RAW_key_statistics!$AI$2:$AI$957,$AL9)),"",INDEX(RAW_key_statistics!$AI$2:$AI$957,$AL9)),"") | N9: =IFERROR(IF(ISBLANK(INDEX(RAW_key_statistics!$CI$2:$CI$957,$AL9)),"",INDEX(RAW_key_statistics!$CI$2:$CI$957,$AL9)),"") | O9: =IFERROR(IF(ISBLANK(INDEX(RAW_key_statistics!$CH$2:$CH$957,$AL9)),"",INDEX(RAW_key_statistics!$CH$2:$CH$957,$AL9)),"") | P9: =IFERROR(IF(ISBLANK(INDEX(RAW_key_statistics!$CK$2:$CK$957,$AL9)),"",INDEX(RAW_key_statistics!$CK$2:$CK$957,$AL9)),"") | Q9: =IFERROR(IF(ISBLANK(INDEX(RAW_key_statistics!$BB$2:$BB$957,$AL9)),"",INDEX(RAW_key_statistics!$BB$2:$BB$957,$AL9)),"") | R9: =IFERROR(IF(ISBLANK(INDEX(RAW_key_statistics!$AE$2:$AE$957,$AL9)),"",INDEX(RAW_key_statistics!$AE$2:$AE$957,$AL9)),"") | S9: =IFERROR(IF(ISBLANK(INDEX(RAW_key_statistics!$V$2:$V$957,$AL9)),"",INDEX(RAW_key_statistics!$V$2:$V$957,$AL9)),"") | T9: =IFERROR(IF(ISBLANK(INDEX(RAW_analyses!$N$2:$N$957,$AO9)),"",INDEX(RAW_analyses!$N$2:$N$957,$AO9)),"") | U9: =IFERROR(IF(ISBLANK(INDEX(RAW_key_statistics!$CU$2:$CU$957,$AL9)),"",INDEX(RAW_key_statistics!$CU$2:$CU$957,$AL9)),"") | V9: =IFERROR(IF(ISBLANK(INDEX(RAW_key_statistics!$CM$2:$CM$957,$AL9)),"",INDEX(RAW_key_statistics!$CM$2:$CM$957,$AL9)),"") | W9: =IFERROR(IF(ISBLANK(INDEX(RAW_key_statistics!$CN$2:$CN$957,$AL9)),"",INDEX(RAW_key_statistics!$CN$2:$CN$957,$AL9)),"") | X9: =IFERROR(IF(ISBLANK(INDEX(RAW_key_statistics!$CR$2:$CR$957,$AL9)),"",INDEX(RAW_key_statistics!$CR$2:$CR$957,$AL9)),"") | Y9: =IFERROR(IF(ISBLANK(INDEX(RAW_scores!$R$2:$R$957,$AM9)),"",INDEX(RAW_scores!$R$2:$R$957,$AM9)),"") | Z9: =IFERROR(IF(ISBLANK(INDEX(RAW_scores!$S$2:$S$957,$AM9)),"",INDEX(RAW_scores!$S$2:$S$957,$AM9)),"") | AA9: =IFERROR(IF(ISBLANK(INDEX(RAW_scores!$T$2:$T$957,$AM9)),"",INDEX(RAW_scores!$T$2:$T$957,$AM9)),"") | AB9: =IFERROR(IF(ISBLANK(INDEX(RAW_scores!$X$2:$X$957,$AM9)),"",INDEX(RAW_scores!$X$2:$X$957,$AM9)),"") | AC9: =IFERROR(IF(ISBLANK(INDEX(RAW_scores!$Y$2:$Y$957,$AM9)),"",INDEX(RAW_scores!$Y$2:$Y$957,$AM9)),"") | AD9: =IFERROR(IF(ISBLANK(INDEX(RAW_scores!$Z$2:$Z$957,$AM9)),"",INDEX(RAW_scores!$Z$2:$Z$957,$AM9)),"") | AE9: =IFERROR(IF(ISBLANK(INDEX(RAW_scores!$F$2:$F$957,$AM9)),"",INDEX(RAW_scores!$F$2:$F$957,$AM9)),"") | AF9: =IFERROR(IF(ISBLANK(INDEX(RAW_scores!$G$2:$G$957,$AM9)),"",INDEX(RAW_scores!$G$2:$G$957,$AM9)),"") | AG9: =IFERROR(IF(ISBLANK(INDEX(RAW_scores!$H$2:$H$957,$AM9)),"",INDEX(RAW_scores!$H$2:$H$957,$AM9)),"") | AH9: =IFERROR(IF(ISBLANK(INDEX(RAW_scores!$I$2:$I$957,$AM9)),"",INDEX(RAW_scores!$I$2:$I$957,$AM9)),"") | AI9: =IFERROR(IF(ISBLANK(INDEX(RAW_scores!$AA$2:$AA$957,$AM9)),"",INDEX(RAW_scores!$AA$2:$AA$957,$AM9)),"") | AJ9: =IFERROR(IF(ISBLANK(INDEX(RAW_scores!$AF$2:$AF$957,$AM9)),"",INDEX(RAW_scores!$AF$2:$AF$957,$AM9)),"") | AK9: =IFERROR(IF(ISBLANK(INDEX(RAW_scores!$AC$2:$AC$957,$AM9)),"",INDEX(RAW_scores!$AC$2:$AC$957,$AM9)),"") | AL9: =IFERROR(MATCH($A9,RAW_key_statistics!$A$2:$A$957,0),"") | AM9: =IFERROR(MATCH($A9,RAW_scores!$A$2:$A$957,0),"") | AN9: =IFERROR(MATCH($A9,RAW_idx_stocks!$A$2:$A$957,0),"") | AO9: =IFERROR(MATCH($A9,RAW_analyses!$A$2:$A$957,0),"")
A10: ADCP | B10: =IFERROR(IF(ISBLANK(INDEX(RAW_scores!$B$2:$B$957,$AM10)),"",INDEX(RAW_scores!$B$2:$B$957,$AM10)),"") | C10: =IFERROR(IF(ISBLANK(INDEX(RAW_scores!$C$2:$C$957,$AM10)),"",INDEX(RAW_scores!$C$2:$C$957,$AM10)),"") | D10: =IFERROR(IF(ISBLANK(INDEX(RAW_scores!$D$2:$D$957,$AM10)),"",INDEX(RAW_scores!$D$2:$D$957,$AM10)),"") | E10: =IFERROR(IF(ISBLANK(INDEX(RAW_idx_stocks!$F$2:$F$957,$AN10)),"",INDEX(RAW_idx_stocks!$F$2:$F$957,$AN10)),"") | F10: =IFERROR(IF(ISBLANK(INDEX(RAW_key_statistics!$BS$2:$BS$957,$AL10)),"",INDEX(RAW_key_statistics!$BS$2:$BS$957,$AL10)/1000000000),"") | G10: =IFERROR(IF(ISBLANK(INDEX(RAW_key_statistics!$C$2:$C$957,$AL10)),"",INDEX(RAW_key_statistics!$C$2:$C$957,$AL10)),"") | H10: =IFERROR(IF(ISBLANK(INDEX(RAW_key_statistics!$H$2:$H$957,$AL10)),"",INDEX(RAW_key_statistics!$H$2:$H$957,$AL10)),"") | I10: =IFERROR(IF(ISBLANK(INDEX(RAW_key_statistics!$K$2:$K$957,$AL10)),"",INDEX(RAW_key_statistics!$K$2:$K$957,$AL10)),"") | J10: =IFERROR(IF(ISBLANK(INDEX(RAW_key_statistics!$L$2:$L$957,$AL10)),"",INDEX(RAW_key_statistics!$L$2:$L$957,$AL10)),"") | K10: =IFERROR(IF(ISBLANK(INDEX(RAW_key_statistics!$AZ$2:$AZ$957,$AL10)),"",INDEX(RAW_key_statistics!$AZ$2:$AZ$957,$AL10)),"") | L10: =IFERROR(IF(ISBLANK(INDEX(RAW_key_statistics!$AG$2:$AG$957,$AL10)),"",INDEX(RAW_key_statistics!$AG$2:$AG$957,$AL10)),"") | M10: =IFERROR(IF(ISBLANK(INDEX(RAW_key_statistics!$AI$2:$AI$957,$AL10)),"",INDEX(RAW_key_statistics!$AI$2:$AI$957,$AL10)),"") | N10: =IFERROR(IF(ISBLANK(INDEX(RAW_key_statistics!$CI$2:$CI$957,$AL10)),"",INDEX(RAW_key_statistics!$CI$2:$CI$957,$AL10)),"") | O10: =IFERROR(IF(ISBLANK(INDEX(RAW_key_statistics!$CH$2:$CH$957,$AL10)),"",INDEX(RAW_key_statistics!$CH$2:$CH$957,$AL10)),"") | P10: =IFERROR(IF(ISBLANK(INDEX(RAW_key_statistics!$CK$2:$CK$957,$AL10)),"",INDEX(RAW_key_statistics!$CK$2:$CK$957,$AL10)),"") | Q10: =IFERROR(IF(ISBLANK(INDEX(RAW_key_statistics!$BB$2:$BB$957,$AL10)),"",INDEX(RAW_key_statistics!$BB$2:$BB$957,$AL10)),"") | R10: =IFERROR(IF(ISBLANK(INDEX(RAW_key_statistics!$AE$2:$AE$957,$AL10)),"",INDEX(RAW_key_statistics!$AE$2:$AE$957,$AL10)),"") | S10: =IFERROR(IF(ISBLANK(INDEX(RAW_key_statistics!$V$2:$V$957,$AL10)),"",INDEX(RAW_key_statistics!$V$2:$V$957,$AL10)),"") | T10: =IFERROR(IF(ISBLANK(INDEX(RAW_analyses!$N$2:$N$957,$AO10)),"",INDEX(RAW_analyses!$N$2:$N$957,$AO10)),"") | U10: =IFERROR(IF(ISBLANK(INDEX(RAW_key_statistics!$CU$2:$CU$957,$AL10)),"",INDEX(RAW_key_statistics!$CU$2:$CU$957,$AL10)),"") | V10: =IFERROR(IF(ISBLANK(INDEX(RAW_key_statistics!$CM$2:$CM$957,$AL10)),"",INDEX(RAW_key_statistics!$CM$2:$CM$957,$AL10)),"") | W10: =IFERROR(IF(ISBLANK(INDEX(RAW_key_statistics!$CN$2:$CN$957,$AL10)),"",INDEX(RAW_key_statistics!$CN$2:$CN$957,$AL10)),"") | X10: =IFERROR(IF(ISBLANK(INDEX(RAW_key_statistics!$CR$2:$CR$957,$AL10)),"",INDEX(RAW_key_statistics!$CR$2:$CR$957,$AL10)),"") | Y10: =IFERROR(IF(ISBLANK(INDEX(RAW_scores!$R$2:$R$957,$AM10)),"",INDEX(RAW_scores!$R$2:$R$957,$AM10)),"") | Z10: =IFERROR(IF(ISBLANK(INDEX(RAW_scores!$S$2:$S$957,$AM10)),"",INDEX(RAW_scores!$S$2:$S$957,$AM10)),"") | AA10: =IFERROR(IF(ISBLANK(INDEX(RAW_scores!$T$2:$T$957,$AM10)),"",INDEX(RAW_scores!$T$2:$T$957,$AM10)),"") | AB10: =IFERROR(IF(ISBLANK(INDEX(RAW_scores!$X$2:$X$957,$AM10)),"",INDEX(RAW_scores!$X$2:$X$957,$AM10)),"") | AC10: =IFERROR(IF(ISBLANK(INDEX(RAW_scores!$Y$2:$Y$957,$AM10)),"",INDEX(RAW_scores!$Y$2:$Y$957,$AM10)),"") | AD10: =IFERROR(IF(ISBLANK(INDEX(RAW_scores!$Z$2:$Z$957,$AM10)),"",INDEX(RAW_scores!$Z$2:$Z$957,$AM10)),"") | AE10: =IFERROR(IF(ISBLANK(INDEX(RAW_scores!$F$2:$F$957,$AM10)),"",INDEX(RAW_scores!$F$2:$F$957,$AM10)),"") | AF10: =IFERROR(IF(ISBLANK(INDEX(RAW_scores!$G$2:$G$957,$AM10)),"",INDEX(RAW_scores!$G$2:$G$957,$AM10)),"") | AG10: =IFERROR(IF(ISBLANK(INDEX(RAW_scores!$H$2:$H$957,$AM10)),"",INDEX(RAW_scores!$H$2:$H$957,$AM10)),"") | AH10: =IFERROR(IF(ISBLANK(INDEX(RAW_scores!$I$2:$I$957,$AM10)),"",INDEX(RAW_scores!$I$2:$I$957,$AM10)),"") | AI10: =IFERROR(IF(ISBLANK(INDEX(RAW_scores!$AA$2:$AA$957,$AM10)),"",INDEX(RAW_scores!$AA$2:$AA$957,$AM10)),"") | AJ10: =IFERROR(IF(ISBLANK(INDEX(RAW_scores!$AF$2:$AF$957,$AM10)),"",INDEX(RAW_scores!$AF$2:$AF$957,$AM10)),"") | AK10: =IFERROR(IF(ISBLANK(INDEX(RAW_scores!$AC$2:$AC$957,$AM10)),"",INDEX(RAW_scores!$AC$2:$AC$957,$AM10)),"") | AL10: =IFERROR(MATCH($A10,RAW_key_statistics!$A$2:$A$957,0),"") | AM10: =IFERROR(MATCH($A10,RAW_scores!$A$2:$A$957,0),"") | AN10: =IFERROR(MATCH($A10,RAW_idx_stocks!$A$2:$A$957,0),"") | AO10: =IFERROR(MATCH($A10,RAW_analyses!$A$2:$A$957,0),"")
A11: ADES | B11: =IFERROR(IF(ISBLANK(INDEX(RAW_scores!$B$2:$B$957,$AM11)),"",INDEX(RAW_scores!$B$2:$B$957,$AM11)),"") | C11: =IFERROR(IF(ISBLANK(INDEX(RAW_scores!$C$2:$C$957,$AM11)),"",INDEX(RAW_scores!$C$2:$C$957,$AM11)),"") | D11: =IFERROR(IF(ISBLANK(INDEX(RAW_scores!$D$2:$D$957,$AM11)),"",INDEX(RAW_scores!$D$2:$D$957,$AM11)),"") | E11: =IFERROR(IF(ISBLANK(INDEX(RAW_idx_stocks!$F$2:$F$957,$AN11)),"",INDEX(RAW_idx_stocks!$F$2:$F$957,$AN11)),"") | F11: =IFERROR(IF(ISBLANK(INDEX(RAW_key_statistics!$BS$2:$BS$957,$AL11)),"",INDEX(RAW_key_statistics!$BS$2:$BS$957,$AL11)/1000000000),"") | G11: =IFERROR(IF(ISBLANK(INDEX(RAW_key_statistics!$C$2:$C$957,$AL11)),"",INDEX(RAW_key_statistics!$C$2:$C$957,$AL11)),"") | H11: =IFERROR(IF(ISBLANK(INDEX(RAW_key_statistics!$H$2:$H$957,$AL11)),"",INDEX(RAW_key_statistics!$H$2:$H$957,$AL11)),"") | I11: =IFERROR(IF(ISBLANK(INDEX(RAW_key_statistics!$K$2:$K$957,$AL11)),"",INDEX(RAW_key_statistics!$K$2:$K$957,$AL11)),"") | J11: =IFERROR(IF(ISBLANK(INDEX(RAW_key_statistics!$L$2:$L$957,$AL11)),"",INDEX(RAW_key_statistics!$L$2:$L$957,$AL11)),"") | K11: =IFERROR(IF(ISBLANK(INDEX(RAW_key_statistics!$AZ$2:$AZ$957,$AL11)),"",INDEX(RAW_key_statistics!$AZ$2:$AZ$957,$AL11)),"") | L11: =IFERROR(IF(ISBLANK(INDEX(RAW_key_statistics!$AG$2:$AG$957,$AL11)),"",INDEX(RAW_key_statistics!$AG$2:$AG$957,$AL11)),"") | M11: =IFERROR(IF(ISBLANK(INDEX(RAW_key_statistics!$AI$2:$AI$957,$AL11)),"",INDEX(RAW_key_statistics!$AI$2:$AI$957,$AL11)),"") | N11: =IFERROR(IF(ISBLANK(INDEX(RAW_key_statistics!$CI$2:$CI$957,$AL11)),"",INDEX(RAW_key_statistics!$CI$2:$CI$957,$AL11)),"") | O11: =IFERROR(IF(ISBLANK(INDEX(RAW_key_statistics!$CH$2:$CH$957,$AL11)),"",INDEX(RAW_key_statistics!$CH$2:$CH$957,$AL11)),"") | P11: =IFERROR(IF(ISBLANK(INDEX(RAW_key_statistics!$CK$2:$CK$957,$AL11)),"",INDEX(RAW_key_statistics!$CK$2:$CK$957,$AL11)),"") | Q11: =IFERROR(IF(ISBLANK(INDEX(RAW_key_statistics!$BB$2:$BB$957,$AL11)),"",INDEX(RAW_key_statistics!$BB$2:$BB$957,$AL11)),"") | R11: =IFERROR(IF(ISBLANK(INDEX(RAW_key_statistics!$AE$2:$AE$957,$AL11)),"",INDEX(RAW_key_statistics!$AE$2:$AE$957,$AL11)),"") | S11: =IFERROR(IF(ISBLANK(INDEX(RAW_key_statistics!$V$2:$V$957,$AL11)),"",INDEX(RAW_key_statistics!$V$2:$V$957,$AL11)),"") | T11: =IFERROR(IF(ISBLANK(INDEX(RAW_analyses!$N$2:$N$957,$AO11)),"",INDEX(RAW_analyses!$N$2:$N$957,$AO11)),"") | U11: =IFERROR(IF(ISBLANK(INDEX(RAW_key_statistics!$CU$2:$CU$957,$AL11)),"",INDEX(RAW_key_statistics!$CU$2:$CU$957,$AL11)),"") | V11: =IFERROR(IF(ISBLANK(INDEX(RAW_key_statistics!$CM$2:$CM$957,$AL11)),"",INDEX(RAW_key_statistics!$CM$2:$CM$957,$AL11)),"") | W11: =IFERROR(IF(ISBLANK(INDEX(RAW_key_statistics!$CN$2:$CN$957,$AL11)),"",INDEX(RAW_key_statistics!$CN$2:$CN$957,$AL11)),"") | X11: =IFERROR(IF(ISBLANK(INDEX(RAW_key_statistics!$CR$2:$CR$957,$AL11)),"",INDEX(RAW_key_statistics!$CR$2:$CR$957,$AL11)),"") | Y11: =IFERROR(IF(ISBLANK(INDEX(RAW_scores!$R$2:$R$957,$AM11)),"",INDEX(RAW_scores!$R$2:$R$957,$AM11)),"") | Z11: =IFERROR(IF(ISBLANK(INDEX(RAW_scores!$S$2:$S$957,$AM11)),"",INDEX(RAW_scores!$S$2:$S$957,$AM11)),"") | AA11: =IFERROR(IF(ISBLANK(INDEX(RAW_scores!$T$2:$T$957,$AM11)),"",INDEX(RAW_scores!$T$2:$T$957,$AM11)),"") | AB11: =IFERROR(IF(ISBLANK(INDEX(RAW_scores!$X$2:$X$957,$AM11)),"",INDEX(RAW_scores!$X$2:$X$957,$AM11)),"") | AC11: =IFERROR(IF(ISBLANK(INDEX(RAW_scores!$Y$2:$Y$957,$AM11)),"",INDEX(RAW_scores!$Y$2:$Y$957,$AM11)),"") | AD11: =IFERROR(IF(ISBLANK(INDEX(RAW_scores!$Z$2:$Z$957,$AM11)),"",INDEX(RAW_scores!$Z$2:$Z$957,$AM11)),"") | AE11: =IFERROR(IF(ISBLANK(INDEX(RAW_scores!$F$2:$F$957,$AM11)),"",INDEX(RAW_scores!$F$2:$F$957,$AM11)),"") | AF11: =IFERROR(IF(ISBLANK(INDEX(RAW_scores!$G$2:$G$957,$AM11)),"",INDEX(RAW_scores!$G$2:$G$957,$AM11)),"") | AG11: =IFERROR(IF(ISBLANK(INDEX(RAW_scores!$H$2:$H$957,$AM11)),"",INDEX(RAW_scores!$H$2:$H$957,$AM11)),"") | AH11: =IFERROR(IF(ISBLANK(INDEX(RAW_scores!$I$2:$I$957,$AM11)),"",INDEX(RAW_scores!$I$2:$I$957,$AM11)),"") | AI11: =IFERROR(IF(ISBLANK(INDEX(RAW_scores!$AA$2:$AA$957,$AM11)),"",INDEX(RAW_scores!$AA$2:$AA$957,$AM11)),"") | AJ11: =IFERROR(IF(ISBLANK(INDEX(RAW_scores!$AF$2:$AF$957,$AM11)),"",INDEX(RAW_scores!$AF$2:$AF$957,$AM11)),"") | AK11: =IFERROR(IF(ISBLANK(INDEX(RAW_scores!$AC$2:$AC$957,$AM11)),"",INDEX(RAW_scores!$AC$2:$AC$957,$AM11)),"") | AL11: =IFERROR(MATCH($A11,RAW_key_statistics!$A$2:$A$957,0),"") | AM11: =IFERROR(MATCH($A11,RAW_scores!$A$2:$A$957,0),"") | AN11: =IFERROR(MATCH($A11,RAW_idx_stocks!$A$2:$A$957,0),"") | AO11: =IFERROR(MATCH($A11,RAW_analyses!$A$2:$A$957,0),"")
A12: ADHI | B12: =IFERROR(IF(ISBLANK(INDEX(RAW_scores!$B$2:$B$957,$AM12)),"",INDEX(RAW_scores!$B$2:$B$957,$AM12)),"") | C12: =IFERROR(IF(ISBLANK(INDEX(RAW_scores!$C$2:$C$957,$AM12)),"",INDEX(RAW_scores!$C$2:$C$957,$AM12)),"") | D12: =IFERROR(IF(ISBLANK(INDEX(RAW_scores!$D$2:$D$957,$AM12)),"",INDEX(RAW_scores!$D$2:$D$957,$AM12)),"") | E12: =IFERROR(IF(ISBLANK(INDEX(RAW_idx_stocks!$F$2:$F$957,$AN12)),"",INDEX(RAW_idx_stocks!$F$2:$F$957,$AN12)),"") | F12: =IFERROR(IF(ISBLANK(INDEX(RAW_key_statistics!$BS$2:$BS$957,$AL12)),"",INDEX(RAW_key_statistics!$BS$2:$BS$957,$AL12)/1000000000),"") | G12: =IFERROR(IF(ISBLANK(INDEX(RAW_key_statistics!$C$2:$C$957,$AL12)),"",INDEX(RAW_key_statistics!$C$2:$C$957,$AL12)),"") | H12: =IFERROR(IF(ISBLANK(INDEX(RAW_key_statistics!$H$2:$H$957,$AL12)),"",INDEX(RAW_key_statistics!$H$2:$H$957,$AL12)),"") | I12: =IFERROR(IF(ISBLANK(INDEX(RAW_key_statistics!$K$2:$K$957,$AL12)),"",INDEX(RAW_key_statistics!$K$2:$K$957,$AL12)),"") | J12: =IFERROR(IF(ISBLANK(INDEX(RAW_key_statistics!$L$2:$L$957,$AL12)),"",INDEX(RAW_key_statistics!$L$2:$L$957,$AL12)),"") | K12: =IFERROR(IF(ISBLANK(INDEX(RAW_key_statistics!$AZ$2:$AZ$957,$AL12)),"",INDEX(RAW_key_statistics!$AZ$2:$AZ$957,$AL12)),"") | L12: =IFERROR(IF(ISBLANK(INDEX(RAW_key_statistics!$AG$2:$AG$957,$AL12)),"",INDEX(RAW_key_statistics!$AG$2:$AG$957,$AL12)),"") | M12: =IFERROR(IF(ISBLANK(INDEX(RAW_key_statistics!$AI$2:$AI$957,$AL12)),"",INDEX(RAW_key_statistics!$AI$2:$AI$957,$AL12)),"") | N12: =IFERROR(IF(ISBLANK(INDEX(RAW_key_statistics!$CI$2:$CI$957,$AL12)),"",INDEX(RAW_key_statistics!$CI$2:$CI$957,$AL12)),"") | O12: =IFERROR(IF(ISBLANK(INDEX(RAW_key_statistics!$CH$2:$CH$957,$AL12)),"",INDEX(RAW_key_statistics!$CH$2:$CH$957,$AL12)),"") | P12: =IFERROR(IF(ISBLANK(INDEX(RAW_key_statistics!$CK$2:$CK$957,$AL12)),"",INDEX(RAW_key_statistics!$CK$2:$CK$957,$AL12)),"") | Q12: =IFERROR(IF(ISBLANK(INDEX(RAW_key_statistics!$BB$2:$BB$957,$AL12)),"",INDEX(RAW_key_statistics!$BB$2:$BB$957,$AL12)),"") | R12: =IFERROR(IF(ISBLANK(INDEX(RAW_key_statistics!$AE$2:$AE$957,$AL12)),"",INDEX(RAW_key_statistics!$AE$2:$AE$957,$AL12)),"") | S12: =IFERROR(IF(ISBLANK(INDEX(RAW_key_statistics!$V$2:$V$957,$AL12)),"",INDEX(RAW_key_statistics!$V$2:$V$957,$AL12)),"") | T12: =IFERROR(IF(ISBLANK(INDEX(RAW_analyses!$N$2:$N$957,$AO12)),"",INDEX(RAW_analyses!$N$2:$N$957,$AO12)),"") | U12: =IFERROR(IF(ISBLANK(INDEX(RAW_key_statistics!$CU$2:$CU$957,$AL12)),"",INDEX(RAW_key_statistics!$CU$2:$CU$957,$AL12)),"") | V12: =IFERROR(IF(ISBLANK(INDEX(RAW_key_statistics!$CM$2:$CM$957,$AL12)),"",INDEX(RAW_key_statistics!$CM$2:$CM$957,$AL12)),"") | W12: =IFERROR(IF(ISBLANK(INDEX(RAW_key_statistics!$CN$2:$CN$957,$AL12)),"",INDEX(RAW_key_statistics!$CN$2:$CN$957,$AL12)),"") | X12: =IFERROR(IF(ISBLANK(INDEX(RAW_key_statistics!$CR$2:$CR$957,$AL12)),"",INDEX(RAW_key_statistics!$CR$2:$CR$957,$AL12)),"") | Y12: =IFERROR(IF(ISBLANK(INDEX(RAW_scores!$R$2:$R$957,$AM12)),"",INDEX(RAW_scores!$R$2:$R$957,$AM12)),"") | Z12: =IFERROR(IF(ISBLANK(INDEX(RAW_scores!$S$2:$S$957,$AM12)),"",INDEX(RAW_scores!$S$2:$S$957,$AM12)),"") | AA12: =IFERROR(IF(ISBLANK(INDEX(RAW_scores!$T$2:$T$957,$AM12)),"",INDEX(RAW_scores!$T$2:$T$957,$AM12)),"") | AB12: =IFERROR(IF(ISBLANK(INDEX(RAW_scores!$X$2:$X$957,$AM12)),"",INDEX(RAW_scores!$X$2:$X$957,$AM12)),"") | AC12: =IFERROR(IF(ISBLANK(INDEX(RAW_scores!$Y$2:$Y$957,$AM12)),"",INDEX(RAW_scores!$Y$2:$Y$957,$AM12)),"") | AD12: =IFERROR(IF(ISBLANK(INDEX(RAW_scores!$Z$2:$Z$957,$AM12)),"",INDEX(RAW_scores!$Z$2:$Z$957,$AM12)),"") | AE12: =IFERROR(IF(ISBLANK(INDEX(RAW_scores!$F$2:$F$957,$AM12)),"",INDEX(RAW_scores!$F$2:$F$957,$AM12)),"") | AF12: =IFERROR(IF(ISBLANK(INDEX(RAW_scores!$G$2:$G$957,$AM12)),"",INDEX(RAW_scores!$G$2:$G$957,$AM12)),"") | AG12: =IFERROR(IF(ISBLANK(INDEX(RAW_scores!$H$2:$H$957,$AM12)),"",INDEX(RAW_scores!$H$2:$H$957,$AM12)),"") | AH12: =IFERROR(IF(ISBLANK(INDEX(RAW_scores!$I$2:$I$957,$AM12)),"",INDEX(RAW_scores!$I$2:$I$957,$AM12)),"") | AI12: =IFERROR(IF(ISBLANK(INDEX(RAW_scores!$AA$2:$AA$957,$AM12)),"",INDEX(RAW_scores!$AA$2:$AA$957,$AM12)),"") | AJ12: =IFERROR(IF(ISBLANK(INDEX(RAW_scores!$AF$2:$AF$957,$AM12)),"",INDEX(RAW_scores!$AF$2:$AF$957,$AM12)),"") | AK12: =IFERROR(IF(ISBLANK(INDEX(RAW_scores!$AC$2:$AC$957,$AM12)),"",INDEX(RAW_scores!$AC$2:$AC$957,$AM12)),"") | AL12: =IFERROR(MATCH($A12,RAW_key_statistics!$A$2:$A$957,0),"") | AM12: =IFERROR(MATCH($A12,RAW_scores!$A$2:$A$957,0),"") | AN12: =IFERROR(MATCH($A12,RAW_idx_stocks!$A$2:$A$957,0),"") | AO12: =IFERROR(MATCH($A12,RAW_analyses!$A$2:$A$957,0),"")
A13: ADMF | B13: =IFERROR(IF(ISBLANK(INDEX(RAW_scores!$B$2:$B$957,$AM13)),"",INDEX(RAW_scores!$B$2:$B$957,$AM13)),"") | C13: =IFERROR(IF(ISBLANK(INDEX(RAW_scores!$C$2:$C$957,$AM13)),"",INDEX(RAW_scores!$C$2:$C$957,$AM13)),"") | D13: =IFERROR(IF(ISBLANK(INDEX(RAW_scores!$D$2:$D$957,$AM13)),"",INDEX(RAW_scores!$D$2:$D$957,$AM13)),"") | E13: =IFERROR(IF(ISBLANK(INDEX(RAW_idx_stocks!$F$2:$F$957,$AN13)),"",INDEX(RAW_idx_stocks!$F$2:$F$957,$AN13)),"") | F13: =IFERROR(IF(ISBLANK(INDEX(RAW_key_statistics!$BS$2:$BS$957,$AL13)),"",INDEX(RAW_key_statistics!$BS$2:$BS$957,$AL13)/1000000000),"") | G13: =IFERROR(IF(ISBLANK(INDEX(RAW_key_statistics!$C$2:$C$957,$AL13)),"",INDEX(RAW_key_statistics!$C$2:$C$957,$AL13)),"") | H13: =IFERROR(IF(ISBLANK(INDEX(RAW_key_statistics!$H$2:$H$957,$AL13)),"",INDEX(RAW_key_statistics!$H$2:$H$957,$AL13)),"") | I13: =IFERROR(IF(ISBLANK(INDEX(RAW_key_statistics!$K$2:$K$957,$AL13)),"",INDEX(RAW_key_statistics!$K$2:$K$957,$AL13)),"") | J13: =IFERROR(IF(ISBLANK(INDEX(RAW_key_statistics!$L$2:$L$957,$AL13)),"",INDEX(RAW_key_statistics!$L$2:$L$957,$AL13)),"") | K13: =IFERROR(IF(ISBLANK(INDEX(RAW_key_statistics!$AZ$2:$AZ$957,$AL13)),"",INDEX(RAW_key_statistics!$AZ$2:$AZ$957,$AL13)),"") | L13: =IFERROR(IF(ISBLANK(INDEX(RAW_key_statistics!$AG$2:$AG$957,$AL13)),"",INDEX(RAW_key_statistics!$AG$2:$AG$957,$AL13)),"") | M13: =IFERROR(IF(ISBLANK(INDEX(RAW_key_statistics!$AI$2:$AI$957,$AL13)),"",INDEX(RAW_key_statistics!$AI$2:$AI$957,$AL13)),"") | N13: =IFERROR(IF(ISBLANK(INDEX(RAW_key_statistics!$CI$2:$CI$957,$AL13)),"",INDEX(RAW_key_statistics!$CI$2:$CI$957,$AL13)),"") | O13: =IFERROR(IF(ISBLANK(INDEX(RAW_key_statistics!$CH$2:$CH$957,$AL13)),"",INDEX(RAW_key_statistics!$CH$2:$CH$957,$AL13)),"") | P13: =IFERROR(IF(ISBLANK(INDEX(RAW_key_statistics!$CK$2:$CK$957,$AL13)),"",INDEX(RAW_key_statistics!$CK$2:$CK$957,$AL13)),"") | Q13: =IFERROR(IF(ISBLANK(INDEX(RAW_key_statistics!$BB$2:$BB$957,$AL13)),"",INDEX(RAW_key_statistics!$BB$2:$BB$957,$AL13)),"") | R13: =IFERROR(IF(ISBLANK(INDEX(RAW_key_statistics!$AE$2:$AE$957,$AL13)),"",INDEX(RAW_key_statistics!$AE$2:$AE$957,$AL13)),"") | S13: =IFERROR(IF(ISBLANK(INDEX(RAW_key_statistics!$V$2:$V$957,$AL13)),"",INDEX(RAW_key_statistics!$V$2:$V$957,$AL13)),"") | T13: =IFERROR(IF(ISBLANK(INDEX(RAW_analyses!$N$2:$N$957,$AO13)),"",INDEX(RAW_analyses!$N$2:$N$957,$AO13)),"") | U13: =IFERROR(IF(ISBLANK(INDEX(RAW_key_statistics!$CU$2:$CU$957,$AL13)),"",INDEX(RAW_key_statistics!$CU$2:$CU$957,$AL13)),"") | V13: =IFERROR(IF(ISBLANK(INDEX(RAW_key_statistics!$CM$2:$CM$957,$AL13)),"",INDEX(RAW_key_statistics!$CM$2:$CM$957,$AL13)),"") | W13: =IFERROR(IF(ISBLANK(INDEX(RAW_key_statistics!$CN$2:$CN$957,$AL13)),"",INDEX(RAW_key_statistics!$CN$2:$CN$957,$AL13)),"") | X13: =IFERROR(IF(ISBLANK(INDEX(RAW_key_statistics!$CR$2:$CR$957,$AL13)),"",INDEX(RAW_key_statistics!$CR$2:$CR$957,$AL13)),"") | Y13: =IFERROR(IF(ISBLANK(INDEX(RAW_scores!$R$2:$R$957,$AM13)),"",INDEX(RAW_scores!$R$2:$R$957,$AM13)),"") | Z13: =IFERROR(IF(ISBLANK(INDEX(RAW_scores!$S$2:$S$957,$AM13)),"",INDEX(RAW_scores!$S$2:$S$957,$AM13)),"") | AA13: =IFERROR(IF(ISBLANK(INDEX(RAW_scores!$T$2:$T$957,$AM13)),"",INDEX(RAW_scores!$T$2:$T$957,$AM13)),"") | AB13: =IFERROR(IF(ISBLANK(INDEX(RAW_scores!$X$2:$X$957,$AM13)),"",INDEX(RAW_scores!$X$2:$X$957,$AM13)),"") | AC13: =IFERROR(IF(ISBLANK(INDEX(RAW_scores!$Y$2:$Y$957,$AM13)),"",INDEX(RAW_scores!$Y$2:$Y$957,$AM13)),"") | AD13: =IFERROR(IF(ISBLANK(INDEX(RAW_scores!$Z$2:$Z$957,$AM13)),"",INDEX(RAW_scores!$Z$2:$Z$957,$AM13)),"") | AE13: =IFERROR(IF(ISBLANK(INDEX(RAW_scores!$F$2:$F$957,$AM13)),"",INDEX(RAW_scores!$F$2:$F$957,$AM13)),"") | AF13: =IFERROR(IF(ISBLANK(INDEX(RAW_scores!$G$2:$G$957,$AM13)),"",INDEX(RAW_scores!$G$2:$G$957,$AM13)),"") | AG13: =IFERROR(IF(ISBLANK(INDEX(RAW_scores!$H$2:$H$957,$AM13)),"",INDEX(RAW_scores!$H$2:$H$957,$AM13)),"") | AH13: =IFERROR(IF(ISBLANK(INDEX(RAW_scores!$I$2:$I$957,$AM13)),"",INDEX(RAW_scores!$I$2:$I$957,$AM13)),"") | AI13: =IFERROR(IF(ISBLANK(INDEX(RAW_scores!$AA$2:$AA$957,$AM13)),"",INDEX(RAW_scores!$AA$2:$AA$957,$AM13)),"") | AJ13: =IFERROR(IF(ISBLANK(INDEX(RAW_scores!$AF$2:$AF$957,$AM13)),"",INDEX(RAW_scores!$AF$2:$AF$957,$AM13)),"") | AK13: =IFERROR(IF(ISBLANK(INDEX(RAW_scores!$AC$2:$AC$957,$AM13)),"",INDEX(RAW_scores!$AC$2:$AC$957,$AM13)),"") | AL13: =IFERROR(MATCH($A13,RAW_key_statistics!$A$2:$A$957,0),"") | AM13: =IFERROR(MATCH($A13,RAW_scores!$A$2:$A$957,0),"") | AN13: =IFERROR(MATCH($A13,RAW_idx_stocks!$A$2:$A$957,0),"") | AO13: =IFERROR(MATCH($A13,RAW_analyses!$A$2:$A$957,0),"")
... A957: ZYRX | B957: =IFERROR(IF(ISBLANK(INDEX(RAW_scores!$B$2:$B$957,$AM957)),"",INDEX(RAW_scores!$B$2:$B$957,$AM957)),"") | C957: =IFERROR(IF(ISBLANK(INDEX(RAW_scores!$C$2:$C$957,$AM957)),"",INDEX(RAW_scores!$C$2:$C$957,$AM957)),"") | D957: =IFERROR(IF(ISBLANK(INDEX(RAW_scores!$D$2:$D$957,$AM957)),"",INDEX(RAW_scores!$D$2:$D$957,$AM957)),"") | E957: =IFERROR(IF(ISBLANK(INDEX(RAW_idx_stocks!$F$2:$F$957,$AN957)),"",INDEX(RAW_idx_stocks!$F$2:$F$957,$AN957)),"") | F957: =IFERROR(IF(ISBLANK(INDEX(RAW_key_statistics!$BS$2:$BS$957,$AL957)),"",INDEX(RAW_key_statistics!$BS$2:$BS$957,$AL957)/1000000000),"") | G957: =IFERROR(IF(ISBLANK(INDEX(RAW_key_statistics!$C$2:$C$957,$AL957)),"",INDEX(RAW_key_statistics!$C$2:$C$957,$AL957)),"") | H957: =IFERROR(IF(ISBLANK(INDEX(RAW_key_statistics!$H$2:$H$957,$AL957)),"",INDEX(RAW_key_statistics!$H$2:$H$957,$AL957)),"") | I957: =IFERROR(IF(ISBLANK(INDEX(RAW_key_statistics!$K$2:$K$957,$AL957)),"",INDEX(RAW_key_statistics!$K$2:$K$957,$AL957)),"") | J957: =IFERROR(IF(ISBLANK(INDEX(RAW_key_statistics!$L$2:$L$957,$AL957)),"",INDEX(RAW_key_statistics!$L$2:$L$957,$AL957)),"") | K957: =IFERROR(IF(ISBLANK(INDEX(RAW_key_statistics!$AZ$2:$AZ$957,$AL957)),"",INDEX(RAW_key_statistics!$AZ$2:$AZ$957,$AL957)),"") | L957: =IFERROR(IF(ISBLANK(INDEX(RAW_key_statistics!$AG$2:$AG$957,$AL957)),"",INDEX(RAW_key_statistics!$AG$2:$AG$957,$AL957)),"") | M957: =IFERROR(IF(ISBLANK(INDEX(RAW_key_statistics!$AI$2:$AI$957,$AL957)),"",INDEX(RAW_key_statistics!$AI$2:$AI$957,$AL957)),"") | N957: =IFERROR(IF(ISBLANK(INDEX(RAW_key_statistics!$CI$2:$CI$957,$AL957)),"",INDEX(RAW_key_statistics!$CI$2:$CI$957,$AL957)),"") | O957: =IFERROR(IF(ISBLANK(INDEX(RAW_key_statistics!$CH$2:$CH$957,$AL957)),"",INDEX(RAW_key_statistics!$CH$2:$CH$957,$AL957)),"") | P957: =IFERROR(IF(ISBLANK(INDEX(RAW_key_statistics!$CK$2:$CK$957,$AL957)),"",INDEX(RAW_key_statistics!$CK$2:$CK$957,$AL957)),"") | Q957: =IFERROR(IF(ISBLANK(INDEX(RAW_key_statistics!$BB$2:$BB$957,$AL957)),"",INDEX(RAW_key_statistics!$BB$2:$BB$957,$AL957)),"") | R957: =IFERROR(IF(ISBLANK(INDEX(RAW_key_statistics!$AE$2:$AE$957,$AL957)),"",INDEX(RAW_key_statistics!$AE$2:$AE$957,$AL957)),"") | S957: =IFERROR(IF(ISBLANK(INDEX(RAW_key_statistics!$V$2:$V$957,$AL957)),"",INDEX(RAW_key_statistics!$V$2:$V$957,$AL957)),"") | T957: =IFERROR(IF(ISBLANK(INDEX(RAW_analyses!$N$2:$N$957,$AO957)),"",INDEX(RAW_analyses!$N$2:$N$957,$AO957)),"") | U957: =IFERROR(IF(ISBLANK(INDEX(RAW_key_statistics!$CU$2:$CU$957,$AL957)),"",INDEX(RAW_key_statistics!$CU$2:$CU$957,$AL957)),"") | V957: =IFERROR(IF(ISBLANK(INDEX(RAW_key_statistics!$CM$2:$CM$957,$AL957)),"",INDEX(RAW_key_statistics!$CM$2:$CM$957,$AL957)),"") | W957: =IFERROR(IF(ISBLANK(INDEX(RAW_key_statistics!$CN$2:$CN$957,$AL957)),"",INDEX(RAW_key_statistics!$CN$2:$CN$957,$AL957)),"") | X957: =IFERROR(IF(ISBLANK(INDEX(RAW_key_statistics!$CR$2:$CR$957,$AL957)),"",INDEX(RAW_key_statistics!$CR$2:$CR$957,$AL957)),"") | Y957: =IFERROR(IF(ISBLANK(INDEX(RAW_scores!$R$2:$R$957,$AM957)),"",INDEX(RAW_scores!$R$2:$R$957,$AM957)),"") | Z957: =IFERROR(IF(ISBLANK(INDEX(RAW_scores!$S$2:$S$957,$AM957)),"",INDEX(RAW_scores!$S$2:$S$957,$AM957)),"") | AA957: =IFERROR(IF(ISBLANK(INDEX(RAW_scores!$T$2:$T$957,$AM957)),"",INDEX(RAW_scores!$T$2:$T$957,$AM957)),"") | AB957: =IFERROR(IF(ISBLANK(INDEX(RAW_scores!$X$2:$X$957,$AM957)),"",INDEX(RAW_scores!$X$2:$X$957,$AM957)),"") | AC957: =IFERROR(IF(ISBLANK(INDEX(RAW_scores!$Y$2:$Y$957,$AM957)),"",INDEX(RAW_scores!$Y$2:$Y$957,$AM957)),"") | AD957: =IFERROR(IF(ISBLANK(INDEX(RAW_scores!$Z$2:$Z$957,$AM957)),"",INDEX(RAW_scores!$Z$2:$Z$957,$AM957)),"") | AE957: =IFERROR(IF(ISBLANK(INDEX(RAW_scores!$F$2:$F$957,$AM957)),"",INDEX(RAW_scores!$F$2:$F$957,$AM957)),"") | AF957: =IFERROR(IF(ISBLANK(INDEX(RAW_scores!$G$2:$G$957,$AM957)),"",INDEX(RAW_scores!$G$2:$G$957,$AM957)),"") | AG957: =IFERROR(IF(ISBLANK(INDEX(RAW_scores!$H$2:$H$957,$AM957)),"",INDEX(RAW_scores!$H$2:$H$957,$AM957)),"") | AH957: =IFERROR(IF(ISBLANK(INDEX(RAW_scores!$I$2:$I$957,$AM957)),"",INDEX(RAW_scores!$I$2:$I$957,$AM957)),"") | AI957: =IFERROR(IF(ISBLANK(INDEX(RAW_scores!$AA$2:$AA$957,$AM957)),"",INDEX(RAW_scores!$AA$2:$AA$957,$AM957)),"") | AJ957: =IFERROR(IF(ISBLANK(INDEX(RAW_scores!$AF$2:$AF$957,$AM957)),"",INDEX(RAW_scores!$AF$2:$AF$957,$AM957)),"") | AK957: =IFERROR(IF(ISBLANK(INDEX(RAW_scores!$AC$2:$AC$957,$AM957)),"",INDEX(RAW_scores!$AC$2:$AC$957,$AM957)),"") | AL957: =IFERROR(MATCH($A957,RAW_key_statistics!$A$2:$A$957,0),"") | AM957: =IFERROR(MATCH($A957,RAW_scores!$A$2:$A$957,0),"") | AN957: =IFERROR(MATCH($A957,RAW_idx_stocks!$A$2:$A$957,0),"") | AO957: =IFERROR(MATCH($A957,RAW_analyses!$A$2:$A$957,0),"")

Sheet Company
A1: COMPANY DRILLDOWN | N1: helper: row in RAW_key_statistics | O1: =IFERROR(MATCH($B$2,RAW_key_statistics!$A$2:$A$957,0),"")
A2: Ticker (INPUT) | B2: DKFT | C2: <-- the ONLY input cell on this sheet | N2: helper: row in RAW_scores | O2: =IFERROR(MATCH($B$2,RAW_scores!$A$2:$A$957,0),"")
N3: helper: row in RAW_idx_stocks | O3: =IFERROR(MATCH($B$2,RAW_idx_stocks!$A$2:$A$957,0),"")
A4: IDENTITY | N4: helper: row in RAW_analyses | O4: =IFERROR(MATCH($B$2,RAW_analyses!$A$2:$A$957,0),"")
A5: Name | B5: =IFERROR(IF(ISBLANK(INDEX(RAW_scores!$B$2:$B$957,$O$2)),"",INDEX(RAW_scores!$B$2:$B$957,$O$2)),"")
A6: Sector | B6: =IFERROR(IF(ISBLANK(INDEX(RAW_scores!$C$2:$C$957,$O$2)),"",INDEX(RAW_scores!$C$2:$C$957,$O$2)),"")
A7: Business Type | B7: =IFERROR(IF(ISBLANK(INDEX(RAW_scores!$D$2:$D$957,$O$2)),"",INDEX(RAW_scores!$D$2:$D$957,$O$2)),"")
A8: Statement currency | B8: =IFERROR(IF(ISBLANK(INDEX(RAW_key_statistics!$DZ$2:$DZ$957,$O$1)),"",INDEX(RAW_key_statistics!$DZ$2:$DZ$957,$O$1)),"")
A9: Price (IDR) | B9: =IFERROR(IF(ISBLANK(INDEX(RAW_idx_stocks!$F$2:$F$957,$O$3)),"",INDEX(RAW_idx_stocks!$F$2:$F$957,$O$3)),"")
A10: Market cap (IDR bn) | B10: =IFERROR(IF(ISBLANK(INDEX(RAW_key_statistics!$BS$2:$BS$957,$O$1)),"",INDEX(RAW_key_statistics!$BS$2:$BS$957,$O$1)/1000000000),"")
A11: Shares outstanding | B11: =IFERROR(IF(ISBLANK(INDEX(RAW_key_statistics!$BU$2:$BU$957,$O$1)),"",INDEX(RAW_key_statistics!$BU$2:$BU$957,$O$1)),"")
A12: Latest filing date | B12: =IFERROR(IF(ISBLANK(INDEX(RAW_key_statistics!$DX$2:$DX$957,$O$1)),"",INDEX(RAW_key_statistics!$DX$2:$DX$957,$O$1)),"")
A13: Quarters stale | B13: =IFERROR(IF(ISBLANK(INDEX(RAW_key_statistics!$DY$2:$DY$957,$O$1)),"",INDEX(RAW_key_statistics!$DY$2:$DY$957,$O$1)),"")
A14: Beta | B14: =IFERROR(IF(ISBLANK(INDEX(RAW_key_statistics!$CG$2:$CG$957,$O$1)),"",INDEX(RAW_key_statistics!$CG$2:$CG$957,$O$1)),"")
A16: VALUATION — EVERY LENS SIDE BY SIDE
A17: Lens | B17: Value per share | C17: MOS vs price | D17: Upside
A18: DCF — bear | B18: =IFERROR(IF(ISBLANK(INDEX(RAW_scores!$R$2:$R$957,$O$2)),"",INDEX(RAW_scores!$R$2:$R$957,$O$2)),"") | C18: =IF(AND(ISNUMBER(B18),B18>0,ISNUMBER($B$9)),1-$B$9/B18,"") | D18: =IF(AND(ISNUMBER(B18),B18>0,ISNUMBER($B$9),$B$9>0),B18/$B$9-1,"")
A19: DCF — base | B19: =IFERROR(IF(ISBLANK(INDEX(RAW_scores!$S$2:$S$957,$O$2)),"",INDEX(RAW_scores!$S$2:$S$957,$O$2)),"") | C19: =IF(AND(ISNUMBER(B19),B19>0,ISNUMBER($B$9)),1-$B$9/B19,"") | D19: =IF(AND(ISNUMBER(B19),B19>0,ISNUMBER($B$9),$B$9>0),B19/$B$9-1,"")
A20: DCF — bull | B20: =IFERROR(IF(ISBLANK(INDEX(RAW_scores!$T$2:$T$957,$O$2)),"",INDEX(RAW_scores!$T$2:$T$957,$O$2)),"") | C20: =IF(AND(ISNUMBER(B20),B20>0,ISNUMBER($B$9)),1-$B$9/B20,"") | D20: =IF(AND(ISNUMBER(B20),B20>0,ISNUMBER($B$9),$B$9>0),B20/$B$9-1,"")
A21: Earnings Power Value (EPV) | B21: =IFERROR(IF(ISBLANK(INDEX(RAW_key_statistics!$CR$2:$CR$957,$O$1)),"",INDEX(RAW_key_statistics!$CR$2:$CR$957,$O$1)),"") | C21: =IF(AND(ISNUMBER(B21),B21>0,ISNUMBER($B$9)),1-$B$9/B21,"") | D21: =IF(AND(ISNUMBER(B21),B21>0,ISNUMBER($B$9),$B$9>0),B21/$B$9-1,"")
A22: Comparables (peer multiples) | B22: =IFERROR(IF(ISBLANK(INDEX(RAW_scores!$AD$2:$AD$957,$O$2)),"",INDEX(RAW_scores!$AD$2:$AD$957,$O$2)),"") | C22: =IF(AND(ISNUMBER(B22),B22>0,ISNUMBER($B$9)),1-$B$9/B22,"") | D22: =IF(AND(ISNUMBER(B22),B22>0,ISNUMBER($B$9),$B$9>0),B22/$B$9-1,"")
A23: Justified P/B | B23: =IFERROR(IF(ISBLANK(INDEX(RAW_scores!$AE$2:$AE$957,$O$2)),"",INDEX(RAW_scores!$AE$2:$AE$957,$O$2)),"") | C23: =IF(AND(ISNUMBER(B23),B23>0,ISNUMBER($B$9)),1-$B$9/B23,"") | D23: =IF(AND(ISNUMBER(B23),B23>0,ISNUMBER($B$9),$B$9>0),B23/$B$9-1,"")
A24: Graham NCAV | B24: =IFERROR(IF(ISBLANK(INDEX(RAW_key_statistics!$CM$2:$CM$957,$O$1)),"",INDEX(RAW_key_statistics!$CM$2:$CM$957,$O$1)),"") | C24: =IF(AND(ISNUMBER(B24),B24>0,ISNUMBER($B$9)),1-$B$9/B24,"") | D24: =IF(AND(ISNUMBER(B24),B24>0,ISNUMBER($B$9),$B$9>0),B24/$B$9-1,"")
A25: Blended IV (scoring engine) | B25: =IFERROR(IF(ISBLANK(INDEX(RAW_scores!$X$2:$X$957,$O$2)),"",INDEX(RAW_scores!$X$2:$X$957,$O$2)),"") | C25: =IFERROR(IF(ISBLANK(INDEX(RAW_scores!$Y$2:$Y$957,$O$2)),"",INDEX(RAW_scores!$Y$2:$Y$957,$O$2)),"") | D25: =IFERROR(IF(ISBLANK(INDEX(RAW_scores!$Z$2:$Z$957,$O$2)),"",INDEX(RAW_scores!$Z$2:$Z$957,$O$2)),"")
A26: Price test only (MOS vs Setup thresholds) | B26: =IF(NOT(ISNUMBER($C$25)),"n/a",IF($C$25>=Setup!$B$9,"BUY",IF($C$25>=Setup!$B$10,"WATCH","SKIP"))) | C26: Thresholds live on Setup!B9 / Setup!B10
A27: VERDICT (price + quality + safety + flags) | B27: =IFERROR(IF(ISBLANK(INDEX(RAW_scores!$AA$2:$AA$957,$O$2)),"",INDEX(RAW_scores!$AA$2:$AA$957,$O$2)),"")
A29: QUALITY
A30: Return on equity (TTM) | B30: =IFERROR(IF(ISBLANK(INDEX(RAW_key_statistics!$AG$2:$AG$957,$O$1)),"",INDEX(RAW_key_statistics!$AG$2:$AG$957,$O$1)),"")
A31: Return on assets (TTM) | B31: =IFERROR(IF(ISBLANK(INDEX(RAW_key_statistics!$AF$2:$AF$957,$O$1)),"",INDEX(RAW_key_statistics!$AF$2:$AF$957,$O$1)),"")
A32: Return on invested capital (TTM) | B32: =IFERROR(IF(ISBLANK(INDEX(RAW_key_statistics!$AI$2:$AI$957,$O$1)),"",INDEX(RAW_key_statistics!$AI$2:$AI$957,$O$1)),"")
A33: Return on capital (Greenblatt) | B33: =IFERROR(IF(ISBLANK(INDEX(RAW_key_statistics!$CI$2:$CI$957,$O$1)),"",INDEX(RAW_key_statistics!$CI$2:$CI$957,$O$1)),"")
A34: Gross profit margin (quarter) | B34: =IFERROR(IF(ISBLANK(INDEX(RAW_key_statistics!$AQ$2:$AQ$957,$O$1)),"",INDEX(RAW_key_statistics!$AQ$2:$AQ$957,$O$1)),"")
A35: Operating profit margin (quarter) | B35: =IFERROR(IF(ISBLANK(INDEX(RAW_key_statistics!$AR$2:$AR$957,$O$1)),"",INDEX(RAW_key_statistics!$AR$2:$AR$957,$O$1)),"")
A36: Net profit margin (quarter) | B36: =IFERROR(IF(ISBLANK(INDEX(RAW_key_statistics!$AS$2:$AS$957,$O$1)),"",INDEX(RAW_key_statistics!$AS$2:$AS$957,$O$1)),"")
A37: Gross margin 5Y average | B37: =IFERROR(IF(ISBLANK(INDEX(RAW_key_statistics!$CY$2:$CY$957,$O$1)),"",INDEX(RAW_key_statistics!$CY$2:$CY$957,$O$1)),"")
A38: EBIT margin 5Y average | B38: =IFERROR(IF(ISBLANK(INDEX(RAW_key_statistics!$CZ$2:$CZ$957,$O$1)),"",INDEX(RAW_key_statistics!$CZ$2:$CZ$957,$O$1)),"")
A39: ROE 5Y average | B39: =IFERROR(IF(ISBLANK(INDEX(RAW_key_statistics!$DA$2:$DA$957,$O$1)),"",INDEX(RAW_key_statistics!$DA$2:$DA$957,$O$1)),"")
A40: Revenue CAGR 3Y | B40: =IFERROR(IF(ISBLANK(INDEX(RAW_key_statistics!$CU$2:$CU$957,$O$1)),"",INDEX(RAW_key_statistics!$CU$2:$CU$957,$O$1)),"")
A41: Revenue CAGR 5Y | B41: =IFERROR(IF(ISBLANK(INDEX(RAW_key_statistics!$CV$2:$CV$957,$O$1)),"",INDEX(RAW_key_statistics!$CV$2:$CV$957,$O$1)),"")
A42: Cash conversion (OCF / net income) | B42: =IFERROR(IF(AND(ISNUMBER(INDEX(RAW_key_statistics!$CB$2:$CB$957,$O$1)),ISNUMBER(INDEX(RAW_key_statistics!$BN$2:$BN$957,$O$1)),INDEX(RAW_key_statistics!$BN$2:$BN$957,$O$1)<>0),INDEX(RAW_key_statistics!$CB$2:$CB$957,$O$1)/INDEX(RAW_key_statistics!$BN$2:$BN$957,$O$1),""),"")
A44: SAFETY
A45: Current ratio | B45: =IFERROR(IF(ISBLANK(INDEX(RAW_key_statistics!$V$2:$V$957,$O$1)),"",INDEX(RAW_key_statistics!$V$2:$V$957,$O$1)),"")
A46: Working capital (IDR bn) | B46: =IFERROR(IF(ISBLANK(INDEX(RAW_key_statistics!$BR$2:$BR$957,$O$1)),"",INDEX(RAW_key_statistics!$BR$2:$BR$957,$O$1)/1000000000),"")
A47: Interest coverage (TTM) | B47: =IFERROR(IF(ISBLANK(INDEX(RAW_key_statistics!$AC$2:$AC$957,$O$1)),"",INDEX(RAW_key_statistics!$AC$2:$AC$957,$O$1)),"")
A48: Altman Z-Score (modified) | B48: =IFERROR(IF(ISBLANK(INDEX(RAW_key_statistics!$AE$2:$AE$957,$O$1)),"",INDEX(RAW_key_statistics!$AE$2:$AE$957,$O$1)),"")
A49: Net debt / equity | B49: =IFERROR(IF(ISBLANK(INDEX(RAW_analyses!$N$2:$N$957,$O$4)),"",INDEX(RAW_analyses!$N$2:$N$957,$O$4)),"")
A50: Total debt (IDR bn) | B50: =IFERROR(IF(ISBLANK(INDEX(RAW_key_statistics!$BW$2:$BW$957,$O$1)),"",INDEX(RAW_key_statistics!$BW$2:$BW$957,$O$1)/1000000000),"")
A51: Net debt (IDR bn) | B51: =IFERROR(IF(ISBLANK(INDEX(RAW_key_statistics!$BX$2:$BX$957,$O$1)),"",INDEX(RAW_key_statistics!$BX$2:$BX$957,$O$1)/1000000000),"")
A52: Net debt / EBITDA | B52: =IFERROR(IF(AND(ISNUMBER(INDEX(RAW_key_statistics!$BX$2:$BX$957,$O$1)),ISNUMBER(INDEX(RAW_key_statistics!$BM$2:$BM$957,$O$1)),INDEX(RAW_key_statistics!$BM$2:$BM$957,$O$1)<>0),INDEX(RAW_key_statistics!$BX$2:$BX$957,$O$1)/INDEX(RAW_key_statistics!$BM$2:$BM$957,$O$1),""),"")
A53: Cost of equity (CAPM: RF + Beta x ERP) | B53: =IFERROR(IF(ISNUMBER($B$14),Setup!$B$7+$B$14*Setup!$B$8,Setup!$B$7+Setup!$B$8),"") | C53: Uses Setup!B7 (risk free) and Setup!B8 (ERP); falls back to beta = 1 when beta is unavailable.
A54: EPV cross-check per share (Setup tax + WACC) | B54: =IFERROR(IF(AND(ISNUMBER(INDEX(RAW_key_statistics!$CO$2:$CO$957,$O$1)),ISNUMBER(INDEX(RAW_key_statistics!$BU$2:$BU$957,$O$1)),INDEX(RAW_key_statistics!$BU$2:$BU$957,$O$1)>0,Setup!$B$5>0),INDEX(RAW_key_statistics!$CO$2:$CO$957,$O$1)*(1-Setup!$B$4)/Setup!$B$5/INDEX(RAW_key_statistics!$BU$2:$BU$957,$O$1),""),"") | C54: Normalised 5Y EBIT x (1 - Setup!B4) / Setup!B5 / shares. Compare with the EPV lens above.
A56: PIOTROSKI F-SCORE — 9 SIGNALS
A57: Signal | B57: Raw (1/0) | C57: Result | D57: What it tests
A58: ROA Positive | B58: =IFERROR(IF(ISBLANK(INDEX(RAW_key_statistics!$DE$2:$DE$957,$O$1)),"",INDEX(RAW_key_statistics!$DE$2:$DE$957,$O$1)),"") | C58: =IF(NOT(ISNUMBER(B58)),"n/a",IF(B58=1,"PASS","FAIL")) | D58: Return on assets positive
A59: CFO Positive | B59: =IFERROR(IF(ISBLANK(INDEX(RAW_key_statistics!$DF$2:$DF$957,$O$1)),"",INDEX(RAW_key_statistics!$DF$2:$DF$957,$O$1)),"") | C59: =IF(NOT(ISNUMBER(B59)),"n/a",IF(B59=1,"PASS","FAIL")) | D59: Operating cash flow positive
A60: ROA Improving | B60: =IFERROR(IF(ISBLANK(INDEX(RAW_key_statistics!$DG$2:$DG$957,$O$1)),"",INDEX(RAW_key_statistics!$DG$2:$DG$957,$O$1)),"") | C60: =IF(NOT(ISNUMBER(B60)),"n/a",IF(B60=1,"PASS","FAIL")) | D60: ROA improving year on year
A61: Accruals | B61: =IFERROR(IF(ISBLANK(INDEX(RAW_key_statistics!$DH$2:$DH$957,$O$1)),"",INDEX(RAW_key_statistics!$DH$2:$DH$957,$O$1)),"") | C61: =IF(NOT(ISNUMBER(B61)),"n/a",IF(B61=1,"PASS","FAIL")) | D61: Operating cash flow exceeds net income (quality of earnings)
A62: Leverage Falling | B62: =IFERROR(IF(ISBLANK(INDEX(RAW_key_statistics!$DI$2:$DI$957,$O$1)),"",INDEX(RAW_key_statistics!$DI$2:$DI$957,$O$1)),"") | C62: =IF(NOT(ISNUMBER(B62)),"n/a",IF(B62=1,"PASS","FAIL")) | D62: Long-term leverage falling
A63: Current Ratio Improving | B63: =IFERROR(IF(ISBLANK(INDEX(RAW_key_statistics!$DJ$2:$DJ$957,$O$1)),"",INDEX(RAW_key_statistics!$DJ$2:$DJ$957,$O$1)),"") | C63: =IF(NOT(ISNUMBER(B63)),"n/a",IF(B63=1,"PASS","FAIL")) | D63: Current ratio improving
A64: No Dilution | B64: =IFERROR(IF(ISBLANK(INDEX(RAW_key_statistics!$DK$2:$DK$957,$O$1)),"",INDEX(RAW_key_statistics!$DK$2:$DK$957,$O$1)),"") | C64: =IF(NOT(ISNUMBER(B64)),"n/a",IF(B64=1,"PASS","FAIL")) | D64: No share issuance
A65: Gross Margin Improving | B65: =IFERROR(IF(ISBLANK(INDEX(RAW_key_statistics!$DL$2:$DL$957,$O$1)),"",INDEX(RAW_key_statistics!$DL$2:$DL$957,$O$1)),"") | C65: =IF(NOT(ISNUMBER(B65)),"n/a",IF(B65=1,"PASS","FAIL")) | D65: Gross margin improving
A66: Asset Turnover Improving | B66: =IFERROR(IF(ISBLANK(INDEX(RAW_key_statistics!$DM$2:$DM$957,$O$1)),"",INDEX(RAW_key_statistics!$DM$2:$DM$957,$O$1)),"") | C66: =IF(NOT(ISNUMBER(B66)),"n/a",IF(B66=1,"PASS","FAIL")) | D66: Asset turnover improving
A67: F-Score total (0-9) | B67: =IFERROR(IF(ISBLANK(INDEX(RAW_key_statistics!$BB$2:$BB$957,$O$1)),"",INDEX(RAW_key_statistics!$BB$2:$BB$957,$O$1)),"") | C67: =SUM(B58:B66) | D67: Column C re-adds the nine signals as a cross-check on the scraper's own F-Score.
A69: VERDICT NARRATIVE
A70: Reasons | B70: =IFERROR(IF(ISBLANK(INDEX(RAW_scores!$AB$2:$AB$957,$O$2)),"",INDEX(RAW_scores!$AB$2:$AB$957,$O$2)),"")
A71: Red flags | B71: =IFERROR(IF(ISBLANK(INDEX(RAW_scores!$AC$2:$AC$957,$O$2)),"",INDEX(RAW_scores!$AC$2:$AC$957,$O$2)),"")
A73: ANNUAL HISTORY — LAST 4 REPORTED YEARS (IDR bn)
A74: Matched on the RAW_history_annual helper key 'Ticker|Period End'; two-condition lookups need one concatenated key because array formulas are not portable.
A75: Line item | B75: =IFERROR(INDEX(RAW_history_annual!$C$2:$C$2684,MATCH($B$2&"|R4",RAW_history_annual!$AG$2:$AG$2684,0)),"") | C75: =IFERROR(INDEX(RAW_history_annual!$C$2:$C$2684,MATCH($B$2&"|R3",RAW_history_annual!$AG$2:$AG$2684,0)),"") | D75: =IFERROR(INDEX(RAW_history_annual!$C$2:$C$2684,MATCH($B$2&"|R2",RAW_history_annual!$AG$2:$AG$2684,0)),"") | E75: =IFERROR(INDEX(RAW_history_annual!$C$2:$C$2684,MATCH($B$2&"|R1",RAW_history_annual!$AG$2:$AG$2684,0)),"")
A76: Revenue | B76: =IFERROR(INDEX(RAW_history_annual!$D$2:$D$2684,MATCH($B$2&"|"&B$75,RAW_history_annual!$AF$2:$AF$2684,0))/1000000000,"") | C76: =IFERROR(INDEX(RAW_history_annual!$D$2:$D$2684,MATCH($B$2&"|"&C$75,RAW_history_annual!$AF$2:$AF$2684,0))/1000000000,"") | D76: =IFERROR(INDEX(RAW_history_annual!$D$2:$D$2684,MATCH($B$2&"|"&D$75,RAW_history_annual!$AF$2:$AF$2684,0))/1000000000,"") | E76: =IFERROR(INDEX(RAW_history_annual!$D$2:$D$2684,MATCH($B$2&"|"&E$75,RAW_history_annual!$AF$2:$AF$2684,0))/1000000000,"")
A77: Gross Profit | B77: =IFERROR(INDEX(RAW_history_annual!$F$2:$F$2684,MATCH($B$2&"|"&B$75,RAW_history_annual!$AF$2:$AF$2684,0))/1000000000,"") | C77: =IFERROR(INDEX(RAW_history_annual!$F$2:$F$2684,MATCH($B$2&"|"&C$75,RAW_history_annual!$AF$2:$AF$2684,0))/1000000000,"") | D77: =IFERROR(INDEX(RAW_history_annual!$F$2:$F$2684,MATCH($B$2&"|"&D$75,RAW_history_annual!$AF$2:$AF$2684,0))/1000000000,"") | E77: =IFERROR(INDEX(RAW_history_annual!$F$2:$F$2684,MATCH($B$2&"|"&E$75,RAW_history_annual!$AF$2:$AF$2684,0))/1000000000,"")
A78: EBIT | B78: =IFERROR(INDEX(RAW_history_annual!$H$2:$H$2684,MATCH($B$2&"|"&B$75,RAW_history_annual!$AF$2:$AF$2684,0))/1000000000,"") | C78: =IFERROR(INDEX(RAW_history_annual!$H$2:$H$2684,MATCH($B$2&"|"&C$75,RAW_history_annual!$AF$2:$AF$2684,0))/1000000000,"") | D78: =IFERROR(INDEX(RAW_history_annual!$H$2:$H$2684,MATCH($B$2&"|"&D$75,RAW_history_annual!$AF$2:$AF$2684,0))/1000000000,"") | E78: =IFERROR(INDEX(RAW_history_annual!$H$2:$H$2684,MATCH($B$2&"|"&E$75,RAW_history_annual!$AF$2:$AF$2684,0))/1000000000,"")
A79: Net Income | B79: =IFERROR(INDEX(RAW_history_annual!$J$2:$J$2684,MATCH($B$2&"|"&B$75,RAW_history_annual!$AF$2:$AF$2684,0))/1000000000,"") | C79: =IFERROR(INDEX(RAW_history_annual!$J$2:$J$2684,MATCH($B$2&"|"&C$75,RAW_history_annual!$AF$2:$AF$2684,0))/1000000000,"") | D79: =IFERROR(INDEX(RAW_history_annual!$J$2:$J$2684,MATCH($B$2&"|"&D$75,RAW_history_annual!$AF$2:$AF$2684,0))/1000000000,"") | E79: =IFERROR(INDEX(RAW_history_annual!$J$2:$J$2684,MATCH($B$2&"|"&E$75,RAW_history_annual!$AF$2:$AF$2684,0))/1000000000,"")
A80: Operating Cash Flow | B80: =IFERROR(INDEX(RAW_history_annual!$AC$2:$AC$2684,MATCH($B$2&"|"&B$75,RAW_history_annual!$AF$2:$AF$2684,0))/1000000000,"") | C80: =IFERROR(INDEX(RAW_history_annual!$AC$2:$AC$2684,MATCH($B$2&"|"&C$75,RAW_history_annual!$AF$2:$AF$2684,0))/1000000000,"") | D80: =IFERROR(INDEX(RAW_history_annual!$AC$2:$AC$2684,MATCH($B$2&"|"&D$75,RAW_history_annual!$AF$2:$AF$2684,0))/1000000000,"") | E80: =IFERROR(INDEX(RAW_history_annual!$AC$2:$AC$2684,MATCH($B$2&"|"&E$75,RAW_history_annual!$AF$2:$AF$2684,0))/1000000000,"")
A81: Free Cash Flow | B81: =IFERROR(INDEX(RAW_history_annual!$AE$2:$AE$2684,MATCH($B$2&"|"&B$75,RAW_history_annual!$AF$2:$AF$2684,0))/1000000000,"") | C81: =IFERROR(INDEX(RAW_history_annual!$AE$2:$AE$2684,MATCH($B$2&"|"&C$75,RAW_history_annual!$AF$2:$AF$2684,0))/1000000000,"") | D81: =IFERROR(INDEX(RAW_history_annual!$AE$2:$AE$2684,MATCH($B$2&"|"&D$75,RAW_history_annual!$AF$2:$AF$2684,0))/1000000000,"") | E81: =IFERROR(INDEX(RAW_history_annual!$AE$2:$AE$2684,MATCH($B$2&"|"&E$75,RAW_history_annual!$AF$2:$AF$2684,0))/1000000000,"")
A82: Total Assets | B82: =IFERROR(INDEX(RAW_history_annual!$O$2:$O$2684,MATCH($B$2&"|"&B$75,RAW_history_annual!$AF$2:$AF$2684,0))/1000000000,"") | C82: =IFERROR(INDEX(RAW_history_annual!$O$2:$O$2684,MATCH($B$2&"|"&C$75,RAW_history_annual!$AF$2:$AF$2684,0))/1000000000,"") | D82: =IFERROR(INDEX(RAW_history_annual!$O$2:$O$2684,MATCH($B$2&"|"&D$75,RAW_history_annual!$AF$2:$AF$2684,0))/1000000000,"") | E82: =IFERROR(INDEX(RAW_history_annual!$O$2:$O$2684,MATCH($B$2&"|"&E$75,RAW_history_annual!$AF$2:$AF$2684,0))/1000000000,"")
A83: Shareholders' Equity | B83: =IFERROR(INDEX(RAW_history_annual!$Q$2:$Q$2684,MATCH($B$2&"|"&B$75,RAW_history_annual!$AF$2:$AF$2684,0))/1000000000,"") | C83: =IFERROR(INDEX(RAW_history_annual!$Q$2:$Q$2684,MATCH($B$2&"|"&C$75,RAW_history_annual!$AF$2:$AF$2684,0))/1000000000,"") | D83: =IFERROR(INDEX(RAW_history_annual!$Q$2:$Q$2684,MATCH($B$2&"|"&D$75,RAW_history_annual!$AF$2:$AF$2684,0))/1000000000,"") | E83: =IFERROR(INDEX(RAW_history_annual!$Q$2:$Q$2684,MATCH($B$2&"|"&E$75,RAW_history_annual!$AF$2:$AF$2684,0))/1000000000,"")

Sheet Scenario
A1: SCENARIO — LIVE DISCOUNTED CASH FLOW
A2: Yellow cells are inputs. They pre-fill from the selected ticker but you may type over any of them; nothing downstream is hardcoded.
A3: INPUTS
A4: Ticker | B4: DKFT | C4: Any ticker present on the Screener sheet.
A5: Current price (IDR) | B5: =IFERROR(IF(ISBLANK(INDEX(RAW_idx_stocks!$F$2:$F$957,MATCH($B$4,RAW_idx_stocks!$A$2:$A$957,0))),"",INDEX(RAW_idx_stocks!$F$2:$F$957,MATCH($B$4,RAW_idx_stocks!$A$2:$A$957,0))),"") | C5: Live from RAW_idx_stocks — not an input.
A6: Base free cash flow (IDR) | B6: =IFERROR(IF(ISBLANK(INDEX(RAW_key_statistics!$CD$2:$CD$957,MATCH($B$4,RAW_key_statistics!$A$2:$A$957,0))),"",INDEX(RAW_key_statistics!$CD$2:$CD$957,MATCH($B$4,RAW_key_statistics!$A$2:$A$957,0))),"") | C6: Trailing-twelve-month FCF. Override with a normalised figure if TTM is distorted.
A7: Growth — year 1 | B7: =IFERROR(MAX(-0.1,MIN(0.15,IFERROR(IF(ISBLANK(INDEX(RAW_key_statistics!$CU$2:$CU$957,MATCH($B$4,RAW_key_statistics!$A$2:$A$957,0))),"",INDEX(RAW_key_statistics!$CU$2:$CU$957,MATCH($B$4,RAW_key_statistics!$A$2:$A$957,0))),""))),0.05) | C7: Seeded from Revenue CAGR 3Y, clamped to -10%..+15%.
A8: Growth — year 2 | B8: =$B$7+($B$12-$B$7)*1/5 | C8: Linear fade from year 1 toward terminal growth (1/5 of the way).
A9: Growth — year 3 | B9: =$B$7+($B$12-$B$7)*2/5 | C9: Linear fade from year 1 toward terminal growth (2/5 of the way).
A10: Growth — year 4 | B10: =$B$7+($B$12-$B$7)*3/5 | C10: Linear fade from year 1 toward terminal growth (3/5 of the way).
A11: Growth — year 5 | B11: =$B$7+($B$12-$B$7)*4/5 | C11: Linear fade from year 1 toward terminal growth (4/5 of the way).
A12: Terminal growth | B12: =Setup!$B$6 | C12: Defaults to Setup!B6. Must stay below WACC.
A13: WACC (discount rate) | B13: =Setup!$B$5 | C13: Defaults to Setup!B5. Compare with the CAPM cost of equity on Company.
A14: Net debt (IDR) | B14: =IFERROR(IF(ISBLANK(INDEX(RAW_key_statistics!$BX$2:$BX$957,MATCH($B$4,RAW_key_statistics!$A$2:$A$957,0))),"",INDEX(RAW_key_statistics!$BX$2:$BX$957,MATCH($B$4,RAW_key_statistics!$A$2:$A$957,0))),"") | C14: Subtracted from enterprise value. Negative = net cash.
A15: Shares outstanding | B15: =IFERROR(IF(ISBLANK(INDEX(RAW_key_statistics!$BU$2:$BU$957,MATCH($B$4,RAW_key_statistics!$A$2:$A$957,0))),"",INDEX(RAW_key_statistics!$BU$2:$BU$957,MATCH($B$4,RAW_key_statistics!$A$2:$A$957,0))),"") | C15: Diluted share count would be more conservative — override if you have it.
A18: 5-YEAR PROJECTION (every cell a formula off the inputs above)
A19: Year | B19: Growth | C19: Free cash flow (IDR) | D19: Discount factor | E19: PV of FCF (IDR)
A20: 1 | B20: =$B$7 | C20: =$B$6*(1+B20) | D20: =1/(1+$B$13)^A20 | E20: =C20*D20
A21: 2 | B21: =$B$8 | C21: =C20*(1+B21) | D21: =1/(1+$B$13)^A21 | E21: =C21*D21
A22: 3 | B22: =$B$9 | C22: =C21*(1+B22) | D22: =1/(1+$B$13)^A22 | E22: =C22*D22
A23: 4 | B23: =$B$10 | C23: =C22*(1+B23) | D23: =1/(1+$B$13)^A23 | E23: =C23*D23
A24: 5 | B24: =$B$11 | C24: =C23*(1+B24) | D24: =1/(1+$B$13)^A24 | E24: =C24*D24
A26: Terminal value (Gordon growth) | C26: =IF($B$13<=$B$12,NA(),C24*(1+$B$12)/($B$13-$B$12)) | D26: =D24 | E26: =C26*D26 | F26: A not-available result here means WACC <= terminal growth, for which the Gordon perpetuity does not converge.
A28: OUTPUT
A29: Enterprise value (IDR) | B29: =SUM(E20:E24)+E26
A30: Less: net debt (IDR) | B30: =$B$14
A31: Equity value (IDR) | B31: =B29-B30
A32: Shares outstanding | B32: =$B$15
A33: Value per share (IDR) | B33: =IFERROR(IF(B32>0,B31/B32,""),"")
A34: Current price (IDR) | B34: =$B$5
A35: Margin of safety | B35: =IF(AND(ISNUMBER(B33),B33>0,ISNUMBER(B34)),1-B34/B33,"")
A36: Upside to value | B36: =IF(AND(ISNUMBER(B33),ISNUMBER(B34),B34>0),B33/B34-1,"")
A37: Price test only (MOS vs Setup thresholds) | B37: =IF(NOT(ISNUMBER(B35)),"n/a",IF(B35>=Setup!$B$9,"BUY",IF(B35>=Setup!$B$10,"WATCH","SKIP"))) | C37: Thresholds live on Setup!B9 / Setup!B10.

Sheet Sensitivity
A1: SENSITIVITY
A2: Both grids recompute value per share cell by cell from the Scenario inputs. No Excel data tables are used — Google Sheets has no equivalent.
A3: Cells reading "n/m" are combinations where WACC <= terminal growth, for which the Gordon perpetuity is not meaningful.
A5: VALUE PER SHARE — WACC (rows) x TERMINAL GROWTH (columns)
A6: WACC \ g | B6: =Scenario!$B$12-0.0200 | C6: =Scenario!$B$12-0.0100 | D6: =Scenario!$B$12+0 | E6: =Scenario!$B$12+0.0100 | F6: =Scenario!$B$12+0.0200
A7: =Scenario!$B$13-0.0300 | B7: =IF($A7<=B$6,"n/m",IFERROR(IF(Scenario!$B$15>0,((Scenario!$C$20/(1+$A7)^1+Scenario!$C$21/(1+$A7)^2+Scenario!$C$22/(1+$A7)^3+Scenario!$C$23/(1+$A7)^4+Scenario!$C$24/(1+$A7)^5+(Scenario!$C$24*(1+B$6)/($A7-B$6))/(1+$A7)^5)-Scenario!$B$14)/Scenario!$B$15,""),"")) | C7: =IF($A7<=C$6,"n/m",IFERROR(IF(Scenario!$B$15>0,((Scenario!$C$20/(1+$A7)^1+Scenario!$C$21/(1+$A7)^2+Scenario!$C$22/(1+$A7)^3+Scenario!$C$23/(1+$A7)^4+Scenario!$C$24/(1+$A7)^5+(Scenario!$C$24*(1+C$6)/($A7-C$6))/(1+$A7)^5)-Scenario!$B$14)/Scenario!$B$15,""),"")) | D7: =IF($A7<=D$6,"n/m",IFERROR(IF(Scenario!$B$15>0,((Scenario!$C$20/(1+$A7)^1+Scenario!$C$21/(1+$A7)^2+Scenario!$C$22/(1+$A7)^3+Scenario!$C$23/(1+$A7)^4+Scenario!$C$24/(1+$A7)^5+(Scenario!$C$24*(1+D$6)/($A7-D$6))/(1+$A7)^5)-Scenario!$B$14)/Scenario!$B$15,""),"")) | E7: =IF($A7<=E$6,"n/m",IFERROR(IF(Scenario!$B$15>0,((Scenario!$C$20/(1+$A7)^1+Scenario!$C$21/(1+$A7)^2+Scenario!$C$22/(1+$A7)^3+Scenario!$C$23/(1+$A7)^4+Scenario!$C$24/(1+$A7)^5+(Scenario!$C$24*(1+E$6)/($A7-E$6))/(1+$A7)^5)-Scenario!$B$14)/Scenario!$B$15,""),"")) | F7: =IF($A7<=F$6,"n/m",IFERROR(IF(Scenario!$B$15>0,((Scenario!$C$20/(1+$A7)^1+Scenario!$C$21/(1+$A7)^2+Scenario!$C$22/(1+$A7)^3+Scenario!$C$23/(1+$A7)^4+Scenario!$C$24/(1+$A7)^5+(Scenario!$C$24*(1+F$6)/($A7-F$6))/(1+$A7)^5)-Scenario!$B$14)/Scenario!$B$15,""),""))
A8: =Scenario!$B$13-0.0200 | B8: =IF($A8<=B$6,"n/m",IFERROR(IF(Scenario!$B$15>0,((Scenario!$C$20/(1+$A8)^1+Scenario!$C$21/(1+$A8)^2+Scenario!$C$22/(1+$A8)^3+Scenario!$C$23/(1+$A8)^4+Scenario!$C$24/(1+$A8)^5+(Scenario!$C$24*(1+B$6)/($A8-B$6))/(1+$A8)^5)-Scenario!$B$14)/Scenario!$B$15,""),"")) | C8: =IF($A8<=C$6,"n/m",IFERROR(IF(Scenario!$B$15>0,((Scenario!$C$20/(1+$A8)^1+Scenario!$C$21/(1+$A8)^2+Scenario!$C$22/(1+$A8)^3+Scenario!$C$23/(1+$A8)^4+Scenario!$C$24/(1+$A8)^5+(Scenario!$C$24*(1+C$6)/($A8-C$6))/(1+$A8)^5)-Scenario!$B$14)/Scenario!$B$15,""),"")) | D8: =IF($A8<=D$6,"n/m",IFERROR(IF(Scenario!$B$15>0,((Scenario!$C$20/(1+$A8)^1+Scenario!$C$21/(1+$A8)^2+Scenario!$C$22/(1+$A8)^3+Scenario!$C$23/(1+$A8)^4+Scenario!$C$24/(1+$A8)^5+(Scenario!$C$24*(1+D$6)/($A8-D$6))/(1+$A8)^5)-Scenario!$B$14)/Scenario!$B$15,""),"")) | E8: =IF($A8<=E$6,"n/m",IFERROR(IF(Scenario!$B$15>0,((Scenario!$C$20/(1+$A8)^1+Scenario!$C$21/(1+$A8)^2+Scenario!$C$22/(1+$A8)^3+Scenario!$C$23/(1+$A8)^4+Scenario!$C$24/(1+$A8)^5+(Scenario!$C$24*(1+E$6)/($A8-E$6))/(1+$A8)^5)-Scenario!$B$14)/Scenario!$B$15,""),"")) | F8: =IF($A8<=F$6,"n/m",IFERROR(IF(Scenario!$B$15>0,((Scenario!$C$20/(1+$A8)^1+Scenario!$C$21/(1+$A8)^2+Scenario!$C$22/(1+$A8)^3+Scenario!$C$23/(1+$A8)^4+Scenario!$C$24/(1+$A8)^5+(Scenario!$C$24*(1+F$6)/($A8-F$6))/(1+$A8)^5)-Scenario!$B$14)/Scenario!$B$15,""),""))
A9: =Scenario!$B$13-0.0100 | B9: =IF($A9<=B$6,"n/m",IFERROR(IF(Scenario!$B$15>0,((Scenario!$C$20/(1+$A9)^1+Scenario!$C$21/(1+$A9)^2+Scenario!$C$22/(1+$A9)^3+Scenario!$C$23/(1+$A9)^4+Scenario!$C$24/(1+$A9)^5+(Scenario!$C$24*(1+B$6)/($A9-B$6))/(1+$A9)^5)-Scenario!$B$14)/Scenario!$B$15,""),"")) | C9: =IF($A9<=C$6,"n/m",IFERROR(IF(Scenario!$B$15>0,((Scenario!$C$20/(1+$A9)^1+Scenario!$C$21/(1+$A9)^2+Scenario!$C$22/(1+$A9)^3+Scenario!$C$23/(1+$A9)^4+Scenario!$C$24/(1+$A9)^5+(Scenario!$C$24*(1+C$6)/($A9-C$6))/(1+$A9)^5)-Scenario!$B$14)/Scenario!$B$15,""),"")) | D9: =IF($A9<=D$6,"n/m",IFERROR(IF(Scenario!$B$15>0,((Scenario!$C$20/(1+$A9)^1+Scenario!$C$21/(1+$A9)^2+Scenario!$C$22/(1+$A9)^3+Scenario!$C$23/(1+$A9)^4+Scenario!$C$24/(1+$A9)^5+(Scenario!$C$24*(1+D$6)/($A9-D$6))/(1+$A9)^5)-Scenario!$B$14)/Scenario!$B$15,""),"")) | E9: =IF($A9<=E$6,"n/m",IFERROR(IF(Scenario!$B$15>0,((Scenario!$C$20/(1+$A9)^1+Scenario!$C$21/(1+$A9)^2+Scenario!$C$22/(1+$A9)^3+Scenario!$C$23/(1+$A9)^4+Scenario!$C$24/(1+$A9)^5+(Scenario!$C$24*(1+E$6)/($A9-E$6))/(1+$A9)^5)-Scenario!$B$14)/Scenario!$B$15,""),"")) | F9: =IF($A9<=F$6,"n/m",IFERROR(IF(Scenario!$B$15>0,((Scenario!$C$20/(1+$A9)^1+Scenario!$C$21/(1+$A9)^2+Scenario!$C$22/(1+$A9)^3+Scenario!$C$23/(1+$A9)^4+Scenario!$C$24/(1+$A9)^5+(Scenario!$C$24*(1+F$6)/($A9-F$6))/(1+$A9)^5)-Scenario!$B$14)/Scenario!$B$15,""),""))
A10: =Scenario!$B$13+0 | B10: =IF($A10<=B$6,"n/m",IFERROR(IF(Scenario!$B$15>0,((Scenario!$C$20/(1+$A10)^1+Scenario!$C$21/(1+$A10)^2+Scenario!$C$22/(1+$A10)^3+Scenario!$C$23/(1+$A10)^4+Scenario!$C$24/(1+$A10)^5+(Scenario!$C$24*(1+B$6)/($A10-B$6))/(1+$A10)^5)-Scenario!$B$14)/Scenario!$B$15,""),"")) | C10: =IF($A10<=C$6,"n/m",IFERROR(IF(Scenario!$B$15>0,((Scenario!$C$20/(1+$A10)^1+Scenario!$C$21/(1+$A10)^2+Scenario!$C$22/(1+$A10)^3+Scenario!$C$23/(1+$A10)^4+Scenario!$C$24/(1+$A10)^5+(Scenario!$C$24*(1+C$6)/($A10-C$6))/(1+$A10)^5)-Scenario!$B$14)/Scenario!$B$15,""),"")) | D10: =IF($A10<=D$6,"n/m",IFERROR(IF(Scenario!$B$15>0,((Scenario!$C$20/(1+$A10)^1+Scenario!$C$21/(1+$A10)^2+Scenario!$C$22/(1+$A10)^3+Scenario!$C$23/(1+$A10)^4+Scenario!$C$24/(1+$A10)^5+(Scenario!$C$24*(1+D$6)/($A10-D$6))/(1+$A10)^5)-Scenario!$B$14)/Scenario!$B$15,""),"")) | E10: =IF($A10<=E$6,"n/m",IFERROR(IF(Scenario!$B$15>0,((Scenario!$C$20/(1+$A10)^1+Scenario!$C$21/(1+$A10)^2+Scenario!$C$22/(1+$A10)^3+Scenario!$C$23/(1+$A10)^4+Scenario!$C$24/(1+$A10)^5+(Scenario!$C$24*(1+E$6)/($A10-E$6))/(1+$A10)^5)-Scenario!$B$14)/Scenario!$B$15,""),"")) | F10: =IF($A10<=F$6,"n/m",IFERROR(IF(Scenario!$B$15>0,((Scenario!$C$20/(1+$A10)^1+Scenario!$C$21/(1+$A10)^2+Scenario!$C$22/(1+$A10)^3+Scenario!$C$23/(1+$A10)^4+Scenario!$C$24/(1+$A10)^5+(Scenario!$C$24*(1+F$6)/($A10-F$6))/(1+$A10)^5)-Scenario!$B$14)/Scenario!$B$15,""),""))
A11: =Scenario!$B$13+0.0100 | B11: =IF($A11<=B$6,"n/m",IFERROR(IF(Scenario!$B$15>0,((Scenario!$C$20/(1+$A11)^1+Scenario!$C$21/(1+$A11)^2+Scenario!$C$22/(1+$A11)^3+Scenario!$C$23/(1+$A11)^4+Scenario!$C$24/(1+$A11)^5+(Scenario!$C$24*(1+B$6)/($A11-B$6))/(1+$A11)^5)-Scenario!$B$14)/Scenario!$B$15,""),"")) | C11: =IF($A11<=C$6,"n/m",IFERROR(IF(Scenario!$B$15>0,((Scenario!$C$20/(1+$A11)^1+Scenario!$C$21/(1+$A11)^2+Scenario!$C$22/(1+$A11)^3+Scenario!$C$23/(1+$A11)^4+Scenario!$C$24/(1+$A11)^5+(Scenario!$C$24*(1+C$6)/($A11-C$6))/(1+$A11)^5)-Scenario!$B$14)/Scenario!$B$15,""),"")) | D11: =IF($A11<=D$6,"n/m",IFERROR(IF(Scenario!$B$15>0,((Scenario!$C$20/(1+$A11)^1+Scenario!$C$21/(1+$A11)^2+Scenario!$C$22/(1+$A11)^3+Scenario!$C$23/(1+$A11)^4+Scenario!$C$24/(1+$A11)^5+(Scenario!$C$24*(1+D$6)/($A11-D$6))/(1+$A11)^5)-Scenario!$B$14)/Scenario!$B$15,""),"")) | E11: =IF($A11<=E$6,"n/m",IFERROR(IF(Scenario!$B$15>0,((Scenario!$C$20/(1+$A11)^1+Scenario!$C$21/(1+$A11)^2+Scenario!$C$22/(1+$A11)^3+Scenario!$C$23/(1+$A11)^4+Scenario!$C$24/(1+$A11)^5+(Scenario!$C$24*(1+E$6)/($A11-E$6))/(1+$A11)^5)-Scenario!$B$14)/Scenario!$B$15,""),"")) | F11: =IF($A11<=F$6,"n/m",IFERROR(IF(Scenario!$B$15>0,((Scenario!$C$20/(1+$A11)^1+Scenario!$C$21/(1+$A11)^2+Scenario!$C$22/(1+$A11)^3+Scenario!$C$23/(1+$A11)^4+Scenario!$C$24/(1+$A11)^5+(Scenario!$C$24*(1+F$6)/($A11-F$6))/(1+$A11)^5)-Scenario!$B$14)/Scenario!$B$15,""),""))
A12: =Scenario!$B$13+0.0200 | B12: =IF($A12<=B$6,"n/m",IFERROR(IF(Scenario!$B$15>0,((Scenario!$C$20/(1+$A12)^1+Scenario!$C$21/(1+$A12)^2+Scenario!$C$22/(1+$A12)^3+Scenario!$C$23/(1+$A12)^4+Scenario!$C$24/(1+$A12)^5+(Scenario!$C$24*(1+B$6)/($A12-B$6))/(1+$A12)^5)-Scenario!$B$14)/Scenario!$B$15,""),"")) | C12: =IF($A12<=C$6,"n/m",IFERROR(IF(Scenario!$B$15>0,((Scenario!$C$20/(1+$A12)^1+Scenario!$C$21/(1+$A12)^2+Scenario!$C$22/(1+$A12)^3+Scenario!$C$23/(1+$A12)^4+Scenario!$C$24/(1+$A12)^5+(Scenario!$C$24*(1+C$6)/($A12-C$6))/(1+$A12)^5)-Scenario!$B$14)/Scenario!$B$15,""),"")) | D12: =IF($A12<=D$6,"n/m",IFERROR(IF(Scenario!$B$15>0,((Scenario!$C$20/(1+$A12)^1+Scenario!$C$21/(1+$A12)^2+Scenario!$C$22/(1+$A12)^3+Scenario!$C$23/(1+$A12)^4+Scenario!$C$24/(1+$A12)^5+(Scenario!$C$24*(1+D$6)/($A12-D$6))/(1+$A12)^5)-Scenario!$B$14)/Scenario!$B$15,""),"")) | E12: =IF($A12<=E$6,"n/m",IFERROR(IF(Scenario!$B$15>0,((Scenario!$C$20/(1+$A12)^1+Scenario!$C$21/(1+$A12)^2+Scenario!$C$22/(1+$A12)^3+Scenario!$C$23/(1+$A12)^4+Scenario!$C$24/(1+$A12)^5+(Scenario!$C$24*(1+E$6)/($A12-E$6))/(1+$A12)^5)-Scenario!$B$14)/Scenario!$B$15,""),"")) | F12: =IF($A12<=F$6,"n/m",IFERROR(IF(Scenario!$B$15>0,((Scenario!$C$20/(1+$A12)^1+Scenario!$C$21/(1+$A12)^2+Scenario!$C$22/(1+$A12)^3+Scenario!$C$23/(1+$A12)^4+Scenario!$C$24/(1+$A12)^5+(Scenario!$C$24*(1+F$6)/($A12-F$6))/(1+$A12)^5)-Scenario!$B$14)/Scenario!$B$15,""),""))
A13: =Scenario!$B$13+0.0300 | B13: =IF($A13<=B$6,"n/m",IFERROR(IF(Scenario!$B$15>0,((Scenario!$C$20/(1+$A13)^1+Scenario!$C$21/(1+$A13)^2+Scenario!$C$22/(1+$A13)^3+Scenario!$C$23/(1+$A13)^4+Scenario!$C$24/(1+$A13)^5+(Scenario!$C$24*(1+B$6)/($A13-B$6))/(1+$A13)^5)-Scenario!$B$14)/Scenario!$B$15,""),"")) | C13: =IF($A13<=C$6,"n/m",IFERROR(IF(Scenario!$B$15>0,((Scenario!$C$20/(1+$A13)^1+Scenario!$C$21/(1+$A13)^2+Scenario!$C$22/(1+$A13)^3+Scenario!$C$23/(1+$A13)^4+Scenario!$C$24/(1+$A13)^5+(Scenario!$C$24*(1+C$6)/($A13-C$6))/(1+$A13)^5)-Scenario!$B$14)/Scenario!$B$15,""),"")) | D13: =IF($A13<=D$6,"n/m",IFERROR(IF(Scenario!$B$15>0,((Scenario!$C$20/(1+$A13)^1+Scenario!$C$21/(1+$A13)^2+Scenario!$C$22/(1+$A13)^3+Scenario!$C$23/(1+$A13)^4+Scenario!$C$24/(1+$A13)^5+(Scenario!$C$24*(1+D$6)/($A13-D$6))/(1+$A13)^5)-Scenario!$B$14)/Scenario!$B$15,""),"")) | E13: =IF($A13<=E$6,"n/m",IFERROR(IF(Scenario!$B$15>0,((Scenario!$C$20/(1+$A13)^1+Scenario!$C$21/(1+$A13)^2+Scenario!$C$22/(1+$A13)^3+Scenario!$C$23/(1+$A13)^4+Scenario!$C$24/(1+$A13)^5+(Scenario!$C$24*(1+E$6)/($A13-E$6))/(1+$A13)^5)-Scenario!$B$14)/Scenario!$B$15,""),"")) | F13: =IF($A13<=F$6,"n/m",IFERROR(IF(Scenario!$B$15>0,((Scenario!$C$20/(1+$A13)^1+Scenario!$C$21/(1+$A13)^2+Scenario!$C$22/(1+$A13)^3+Scenario!$C$23/(1+$A13)^4+Scenario!$C$24/(1+$A13)^5+(Scenario!$C$24*(1+F$6)/($A13-F$6))/(1+$A13)^5)-Scenario!$B$14)/Scenario!$B$15,""),""))
A16: VALUE PER SHARE — WACC (rows) x STAGE-1 GROWTH (columns, applied to all five years)
A17: WACC \ g1-5 | B17: =AVERAGE(Scenario!$B$7:Scenario!$B$11)-0.0400 | C17: =AVERAGE(Scenario!$B$7:Scenario!$B$11)-0.0200 | D17: =AVERAGE(Scenario!$B$7:Scenario!$B$11)+0 | E17: =AVERAGE(Scenario!$B$7:Scenario!$B$11)+0.0200 | F17: =AVERAGE(Scenario!$B$7:Scenario!$B$11)+0.0400
A18: =Scenario!$B$13-0.0300 | B18: =IF($A18<=Scenario!$B$12,"n/m",IFERROR(IF(Scenario!$B$15>0,((Scenario!$B$6*(1+B$17)^1/(1+$A18)^1+Scenario!$B$6*(1+B$17)^2/(1+$A18)^2+Scenario!$B$6*(1+B$17)^3/(1+$A18)^3+Scenario!$B$6*(1+B$17)^4/(1+$A18)^4+Scenario!$B$6*(1+B$17)^5/(1+$A18)^5+(Scenario!$B$6*(1+B$17)^5*(1+Scenario!$B$12)/($A18-Scenario!$B$12))/(1+$A18)^5)-Scenario!$B$14)/Scenario!$B$15,""),"")) | C18: =IF($A18<=Scenario!$B$12,"n/m",IFERROR(IF(Scenario!$B$15>0,((Scenario!$B$6*(1+C$17)^1/(1+$A18)^1+Scenario!$B$6*(1+C$17)^2/(1+$A18)^2+Scenario!$B$6*(1+C$17)^3/(1+$A18)^3+Scenario!$B$6*(1+C$17)^4/(1+$A18)^4+Scenario!$B$6*(1+C$17)^5/(1+$A18)^5+(Scenario!$B$6*(1+C$17)^5*(1+Scenario!$B$12)/($A18-Scenario!$B$12))/(1+$A18)^5)-Scenario!$B$14)/Scenario!$B$15,""),"")) | D18: =IF($A18<=Scenario!$B$12,"n/m",IFERROR(IF(Scenario!$B$15>0,((Scenario!$B$6*(1+D$17)^1/(1+$A18)^1+Scenario!$B$6*(1+D$17)^2/(1+$A18)^2+Scenario!$B$6*(1+D$17)^3/(1+$A18)^3+Scenario!$B$6*(1+D$17)^4/(1+$A18)^4+Scenario!$B$6*(1+D$17)^5/(1+$A18)^5+(Scenario!$B$6*(1+D$17)^5*(1+Scenario!$B$12)/($A18-Scenario!$B$12))/(1+$A18)^5)-Scenario!$B$14)/Scenario!$B$15,""),"")) | E18: =IF($A18<=Scenario!$B$12,"n/m",IFERROR(IF(Scenario!$B$15>0,((Scenario!$B$6*(1+E$17)^1/(1+$A18)^1+Scenario!$B$6*(1+E$17)^2/(1+$A18)^2+Scenario!$B$6*(1+E$17)^3/(1+$A18)^3+Scenario!$B$6*(1+E$17)^4/(1+$A18)^4+Scenario!$B$6*(1+E$17)^5/(1+$A18)^5+(Scenario!$B$6*(1+E$17)^5*(1+Scenario!$B$12)/($A18-Scenario!$B$12))/(1+$A18)^5)-Scenario!$B$14)/Scenario!$B$15,""),"")) | F18: =IF($A18<=Scenario!$B$12,"n/m",IFERROR(IF(Scenario!$B$15>0,((Scenario!$B$6*(1+F$17)^1/(1+$A18)^1+Scenario!$B$6*(1+F$17)^2/(1+$A18)^2+Scenario!$B$6*(1+F$17)^3/(1+$A18)^3+Scenario!$B$6*(1+F$17)^4/(1+$A18)^4+Scenario!$B$6*(1+F$17)^5/(1+$A18)^5+(Scenario!$B$6*(1+F$17)^5*(1+Scenario!$B$12)/($A18-Scenario!$B$12))/(1+$A18)^5)-Scenario!$B$14)/Scenario!$B$15,""),""))
A19: =Scenario!$B$13-0.0200 | B19: =IF($A19<=Scenario!$B$12,"n/m",IFERROR(IF(Scenario!$B$15>0,((Scenario!$B$6*(1+B$17)^1/(1+$A19)^1+Scenario!$B$6*(1+B$17)^2/(1+$A19)^2+Scenario!$B$6*(1+B$17)^3/(1+$A19)^3+Scenario!$B$6*(1+B$17)^4/(1+$A19)^4+Scenario!$B$6*(1+B$17)^5/(1+$A19)^5+(Scenario!$B$6*(1+B$17)^5*(1+Scenario!$B$12)/($A19-Scenario!$B$12))/(1+$A19)^5)-Scenario!$B$14)/Scenario!$B$15,""),"")) | C19: =IF($A19<=Scenario!$B$12,"n/m",IFERROR(IF(Scenario!$B$15>0,((Scenario!$B$6*(1+C$17)^1/(1+$A19)^1+Scenario!$B$6*(1+C$17)^2/(1+$A19)^2+Scenario!$B$6*(1+C$17)^3/(1+$A19)^3+Scenario!$B$6*(1+C$17)^4/(1+$A19)^4+Scenario!$B$6*(1+C$17)^5/(1+$A19)^5+(Scenario!$B$6*(1+C$17)^5*(1+Scenario!$B$12)/($A19-Scenario!$B$12))/(1+$A19)^5)-Scenario!$B$14)/Scenario!$B$15,""),"")) | D19: =IF($A19<=Scenario!$B$12,"n/m",IFERROR(IF(Scenario!$B$15>0,((Scenario!$B$6*(1+D$17)^1/(1+$A19)^1+Scenario!$B$6*(1+D$17)^2/(1+$A19)^2+Scenario!$B$6*(1+D$17)^3/(1+$A19)^3+Scenario!$B$6*(1+D$17)^4/(1+$A19)^4+Scenario!$B$6*(1+D$17)^5/(1+$A19)^5+(Scenario!$B$6*(1+D$17)^5*(1+Scenario!$B$12)/($A19-Scenario!$B$12))/(1+$A19)^5)-Scenario!$B$14)/Scenario!$B$15,""),"")) | E19: =IF($A19<=Scenario!$B$12,"n/m",IFERROR(IF(Scenario!$B$15>0,((Scenario!$B$6*(1+E$17)^1/(1+$A19)^1+Scenario!$B$6*(1+E$17)^2/(1+$A19)^2+Scenario!$B$6*(1+E$17)^3/(1+$A19)^3+Scenario!$B$6*(1+E$17)^4/(1+$A19)^4+Scenario!$B$6*(1+E$17)^5/(1+$A19)^5+(Scenario!$B$6*(1+E$17)^5*(1+Scenario!$B$12)/($A19-Scenario!$B$12))/(1+$A19)^5)-Scenario!$B$14)/Scenario!$B$15,""),"")) | F19: =IF($A19<=Scenario!$B$12,"n/m",IFERROR(IF(Scenario!$B$15>0,((Scenario!$B$6*(1+F$17)^1/(1+$A19)^1+Scenario!$B$6*(1+F$17)^2/(1+$A19)^2+Scenario!$B$6*(1+F$17)^3/(1+$A19)^3+Scenario!$B$6*(1+F$17)^4/(1+$A19)^4+Scenario!$B$6*(1+F$17)^5/(1+$A19)^5+(Scenario!$B$6*(1+F$17)^5*(1+Scenario!$B$12)/($A19-Scenario!$B$12))/(1+$A19)^5)-Scenario!$B$14)/Scenario!$B$15,""),""))
A20: =Scenario!$B$13-0.0100 | B20: =IF($A20<=Scenario!$B$12,"n/m",IFERROR(IF(Scenario!$B$15>0,((Scenario!$B$6*(1+B$17)^1/(1+$A20)^1+Scenario!$B$6*(1+B$17)^2/(1+$A20)^2+Scenario!$B$6*(1+B$17)^3/(1+$A20)^3+Scenario!$B$6*(1+B$17)^4/(1+$A20)^4+Scenario!$B$6*(1+B$17)^5/(1+$A20)^5+(Scenario!$B$6*(1+B$17)^5*(1+Scenario!$B$12)/($A20-Scenario!$B$12))/(1+$A20)^5)-Scenario!$B$14)/Scenario!$B$15,""),"")) | C20: =IF($A20<=Scenario!$B$12,"n/m",IFERROR(IF(Scenario!$B$15>0,((Scenario!$B$6*(1+C$17)^1/(1+$A20)^1+Scenario!$B$6*(1+C$17)^2/(1+$A20)^2+Scenario!$B$6*(1+C$17)^3/(1+$A20)^3+Scenario!$B$6*(1+C$17)^4/(1+$A20)^4+Scenario!$B$6*(1+C$17)^5/(1+$A20)^5+(Scenario!$B$6*(1+C$17)^5*(1+Scenario!$B$12)/($A20-Scenario!$B$12))/(1+$A20)^5)-Scenario!$B$14)/Scenario!$B$15,""),"")) | D20: =IF($A20<=Scenario!$B$12,"n/m",IFERROR(IF(Scenario!$B$15>0,((Scenario!$B$6*(1+D$17)^1/(1+$A20)^1+Scenario!$B$6*(1+D$17)^2/(1+$A20)^2+Scenario!$B$6*(1+D$17)^3/(1+$A20)^3+Scenario!$B$6*(1+D$17)^4/(1+$A20)^4+Scenario!$B$6*(1+D$17)^5/(1+$A20)^5+(Scenario!$B$6*(1+D$17)^5*(1+Scenario!$B$12)/($A20-Scenario!$B$12))/(1+$A20)^5)-Scenario!$B$14)/Scenario!$B$15,""),"")) | E20: =IF($A20<=Scenario!$B$12,"n/m",IFERROR(IF(Scenario!$B$15>0,((Scenario!$B$6*(1+E$17)^1/(1+$A20)^1+Scenario!$B$6*(1+E$17)^2/(1+$A20)^2+Scenario!$B$6*(1+E$17)^3/(1+$A20)^3+Scenario!$B$6*(1+E$17)^4/(1+$A20)^4+Scenario!$B$6*(1+E$17)^5/(1+$A20)^5+(Scenario!$B$6*(1+E$17)^5*(1+Scenario!$B$12)/($A20-Scenario!$B$12))/(1+$A20)^5)-Scenario!$B$14)/Scenario!$B$15,""),"")) | F20: =IF($A20<=Scenario!$B$12,"n/m",IFERROR(IF(Scenario!$B$15>0,((Scenario!$B$6*(1+F$17)^1/(1+$A20)^1+Scenario!$B$6*(1+F$17)^2/(1+$A20)^2+Scenario!$B$6*(1+F$17)^3/(1+$A20)^3+Scenario!$B$6*(1+F$17)^4/(1+$A20)^4+Scenario!$B$6*(1+F$17)^5/(1+$A20)^5+(Scenario!$B$6*(1+F$17)^5*(1+Scenario!$B$12)/($A20-Scenario!$B$12))/(1+$A20)^5)-Scenario!$B$14)/Scenario!$B$15,""),""))
A21: =Scenario!$B$13+0 | B21: =IF($A21<=Scenario!$B$12,"n/m",IFERROR(IF(Scenario!$B$15>0,((Scenario!$B$6*(1+B$17)^1/(1+$A21)^1+Scenario!$B$6*(1+B$17)^2/(1+$A21)^2+Scenario!$B$6*(1+B$17)^3/(1+$A21)^3+Scenario!$B$6*(1+B$17)^4/(1+$A21)^4+Scenario!$B$6*(1+B$17)^5/(1+$A21)^5+(Scenario!$B$6*(1+B$17)^5*(1+Scenario!$B$12)/($A21-Scenario!$B$12))/(1+$A21)^5)-Scenario!$B$14)/Scenario!$B$15,""),"")) | C21: =IF($A21<=Scenario!$B$12,"n/m",IFERROR(IF(Scenario!$B$15>0,((Scenario!$B$6*(1+C$17)^1/(1+$A21)^1+Scenario!$B$6*(1+C$17)^2/(1+$A21)^2+Scenario!$B$6*(1+C$17)^3/(1+$A21)^3+Scenario!$B$6*(1+C$17)^4/(1+$A21)^4+Scenario!$B$6*(1+C$17)^5/(1+$A21)^5+(Scenario!$B$6*(1+C$17)^5*(1+Scenario!$B$12)/($A21-Scenario!$B$12))/(1+$A21)^5)-Scenario!$B$14)/Scenario!$B$15,""),"")) | D21: =IF($A21<=Scenario!$B$12,"n/m",IFERROR(IF(Scenario!$B$15>0,((Scenario!$B$6*(1+D$17)^1/(1+$A21)^1+Scenario!$B$6*(1+D$17)^2/(1+$A21)^2+Scenario!$B$6*(1+D$17)^3/(1+$A21)^3+Scenario!$B$6*(1+D$17)^4/(1+$A21)^4+Scenario!$B$6*(1+D$17)^5/(1+$A21)^5+(Scenario!$B$6*(1+D$17)^5*(1+Scenario!$B$12)/($A21-Scenario!$B$12))/(1+$A21)^5)-Scenario!$B$14)/Scenario!$B$15,""),"")) | E21: =IF($A21<=Scenario!$B$12,"n/m",IFERROR(IF(Scenario!$B$15>0,((Scenario!$B$6*(1+E$17)^1/(1+$A21)^1+Scenario!$B$6*(1+E$17)^2/(1+$A21)^2+Scenario!$B$6*(1+E$17)^3/(1+$A21)^3+Scenario!$B$6*(1+E$17)^4/(1+$A21)^4+Scenario!$B$6*(1+E$17)^5/(1+$A21)^5+(Scenario!$B$6*(1+E$17)^5*(1+Scenario!$B$12)/($A21-Scenario!$B$12))/(1+$A21)^5)-Scenario!$B$14)/Scenario!$B$15,""),"")) | F21: =IF($A21<=Scenario!$B$12,"n/m",IFERROR(IF(Scenario!$B$15>0,((Scenario!$B$6*(1+F$17)^1/(1+$A21)^1+Scenario!$B$6*(1+F$17)^2/(1+$A21)^2+Scenario!$B$6*(1+F$17)^3/(1+$A21)^3+Scenario!$B$6*(1+F$17)^4/(1+$A21)^4+Scenario!$B$6*(1+F$17)^5/(1+$A21)^5+(Scenario!$B$6*(1+F$17)^5*(1+Scenario!$B$12)/($A21-Scenario!$B$12))/(1+$A21)^5)-Scenario!$B$14)/Scenario!$B$15,""),""))
A22: =Scenario!$B$13+0.0100 | B22: =IF($A22<=Scenario!$B$12,"n/m",IFERROR(IF(Scenario!$B$15>0,((Scenario!$B$6*(1+B$17)^1/(1+$A22)^1+Scenario!$B$6*(1+B$17)^2/(1+$A22)^2+Scenario!$B$6*(1+B$17)^3/(1+$A22)^3+Scenario!$B$6*(1+B$17)^4/(1+$A22)^4+Scenario!$B$6*(1+B$17)^5/(1+$A22)^5+(Scenario!$B$6*(1+B$17)^5*(1+Scenario!$B$12)/($A22-Scenario!$B$12))/(1+$A22)^5)-Scenario!$B$14)/Scenario!$B$15,""),"")) | C22: =IF($A22<=Scenario!$B$12,"n/m",IFERROR(IF(Scenario!$B$15>0,((Scenario!$B$6*(1+C$17)^1/(1+$A22)^1+Scenario!$B$6*(1+C$17)^2/(1+$A22)^2+Scenario!$B$6*(1+C$17)^3/(1+$A22)^3+Scenario!$B$6*(1+C$17)^4/(1+$A22)^4+Scenario!$B$6*(1+C$17)^5/(1+$A22)^5+(Scenario!$B$6*(1+C$17)^5*(1+Scenario!$B$12)/($A22-Scenario!$B$12))/(1+$A22)^5)-Scenario!$B$14)/Scenario!$B$15,""),"")) | D22: =IF($A22<=Scenario!$B$12,"n/m",IFERROR(IF(Scenario!$B$15>0,((Scenario!$B$6*(1+D$17)^1/(1+$A22)^1+Scenario!$B$6*(1+D$17)^2/(1+$A22)^2+Scenario!$B$6*(1+D$17)^3/(1+$A22)^3+Scenario!$B$6*(1+D$17)^4/(1+$A22)^4+Scenario!$B$6*(1+D$17)^5/(1+$A22)^5+(Scenario!$B$6*(1+D$17)^5*(1+Scenario!$B$12)/($A22-Scenario!$B$12))/(1+$A22)^5)-Scenario!$B$14)/Scenario!$B$15,""),"")) | E22: =IF($A22<=Scenario!$B$12,"n/m",IFERROR(IF(Scenario!$B$15>0,((Scenario!$B$6*(1+E$17)^1/(1+$A22)^1+Scenario!$B$6*(1+E$17)^2/(1+$A22)^2+Scenario!$B$6*(1+E$17)^3/(1+$A22)^3+Scenario!$B$6*(1+E$17)^4/(1+$A22)^4+Scenario!$B$6*(1+E$17)^5/(1+$A22)^5+(Scenario!$B$6*(1+E$17)^5*(1+Scenario!$B$12)/($A22-Scenario!$B$12))/(1+$A22)^5)-Scenario!$B$14)/Scenario!$B$15,""),"")) | F22: =IF($A22<=Scenario!$B$12,"n/m",IFERROR(IF(Scenario!$B$15>0,((Scenario!$B$6*(1+F$17)^1/(1+$A22)^1+Scenario!$B$6*(1+F$17)^2/(1+$A22)^2+Scenario!$B$6*(1+F$17)^3/(1+$A22)^3+Scenario!$B$6*(1+F$17)^4/(1+$A22)^4+Scenario!$B$6*(1+F$17)^5/(1+$A22)^5+(Scenario!$B$6*(1+F$17)^5*(1+Scenario!$B$12)/($A22-Scenario!$B$12))/(1+$A22)^5)-Scenario!$B$14)/Scenario!$B$15,""),""))
A23: =Scenario!$B$13+0.0200 | B23: =IF($A23<=Scenario!$B$12,"n/m",IFERROR(IF(Scenario!$B$15>0,((Scenario!$B$6*(1+B$17)^1/(1+$A23)^1+Scenario!$B$6*(1+B$17)^2/(1+$A23)^2+Scenario!$B$6*(1+B$17)^3/(1+$A23)^3+Scenario!$B$6*(1+B$17)^4/(1+$A23)^4+Scenario!$B$6*(1+B$17)^5/(1+$A23)^5+(Scenario!$B$6*(1+B$17)^5*(1+Scenario!$B$12)/($A23-Scenario!$B$12))/(1+$A23)^5)-Scenario!$B$14)/Scenario!$B$15,""),"")) | C23: =IF($A23<=Scenario!$B$12,"n/m",IFERROR(IF(Scenario!$B$15>0,((Scenario!$B$6*(1+C$17)^1/(1+$A23)^1+Scenario!$B$6*(1+C$17)^2/(1+$A23)^2+Scenario!$B$6*(1+C$17)^3/(1+$A23)^3+Scenario!$B$6*(1+C$17)^4/(1+$A23)^4+Scenario!$B$6*(1+C$17)^5/(1+$A23)^5+(Scenario!$B$6*(1+C$17)^5*(1+Scenario!$B$12)/($A23-Scenario!$B$12))/(1+$A23)^5)-Scenario!$B$14)/Scenario!$B$15,""),"")) | D23: =IF($A23<=Scenario!$B$12,"n/m",IFERROR(IF(Scenario!$B$15>0,((Scenario!$B$6*(1+D$17)^1/(1+$A23)^1+Scenario!$B$6*(1+D$17)^2/(1+$A23)^2+Scenario!$B$6*(1+D$17)^3/(1+$A23)^3+Scenario!$B$6*(1+D$17)^4/(1+$A23)^4+Scenario!$B$6*(1+D$17)^5/(1+$A23)^5+(Scenario!$B$6*(1+D$17)^5*(1+Scenario!$B$12)/($A23-Scenario!$B$12))/(1+$A23)^5)-Scenario!$B$14)/Scenario!$B$15,""),"")) | E23: =IF($A23<=Scenario!$B$12,"n/m",IFERROR(IF(Scenario!$B$15>0,((Scenario!$B$6*(1+E$17)^1/(1+$A23)^1+Scenario!$B$6*(1+E$17)^2/(1+$A23)^2+Scenario!$B$6*(1+E$17)^3/(1+$A23)^3+Scenario!$B$6*(1+E$17)^4/(1+$A23)^4+Scenario!$B$6*(1+E$17)^5/(1+$A23)^5+(Scenario!$B$6*(1+E$17)^5*(1+Scenario!$B$12)/($A23-Scenario!$B$12))/(1+$A23)^5)-Scenario!$B$14)/Scenario!$B$15,""),"")) | F23: =IF($A23<=Scenario!$B$12,"n/m",IFERROR(IF(Scenario!$B$15>0,((Scenario!$B$6*(1+F$17)^1/(1+$A23)^1+Scenario!$B$6*(1+F$17)^2/(1+$A23)^2+Scenario!$B$6*(1+F$17)^3/(1+$A23)^3+Scenario!$B$6*(1+F$17)^4/(1+$A23)^4+Scenario!$B$6*(1+F$17)^5/(1+$A23)^5+(Scenario!$B$6*(1+F$17)^5*(1+Scenario!$B$12)/($A23-Scenario!$B$12))/(1+$A23)^5)-Scenario!$B$14)/Scenario!$B$15,""),""))
A24: =Scenario!$B$13+0.0300 | B24: =IF($A24<=Scenario!$B$12,"n/m",IFERROR(IF(Scenario!$B$15>0,((Scenario!$B$6*(1+B$17)^1/(1+$A24)^1+Scenario!$B$6*(1+B$17)^2/(1+$A24)^2+Scenario!$B$6*(1+B$17)^3/(1+$A24)^3+Scenario!$B$6*(1+B$17)^4/(1+$A24)^4+Scenario!$B$6*(1+B$17)^5/(1+$A24)^5+(Scenario!$B$6*(1+B$17)^5*(1+Scenario!$B$12)/($A24-Scenario!$B$12))/(1+$A24)^5)-Scenario!$B$14)/Scenario!$B$15,""),"")) | C24: =IF($A24<=Scenario!$B$12,"n/m",IFERROR(IF(Scenario!$B$15>0,((Scenario!$B$6*(1+C$17)^1/(1+$A24)^1+Scenario!$B$6*(1+C$17)^2/(1+$A24)^2+Scenario!$B$6*(1+C$17)^3/(1+$A24)^3+Scenario!$B$6*(1+C$17)^4/(1+$A24)^4+Scenario!$B$6*(1+C$17)^5/(1+$A24)^5+(Scenario!$B$6*(1+C$17)^5*(1+Scenario!$B$12)/($A24-Scenario!$B$12))/(1+$A24)^5)-Scenario!$B$14)/Scenario!$B$15,""),"")) | D24: =IF($A24<=Scenario!$B$12,"n/m",IFERROR(IF(Scenario!$B$15>0,((Scenario!$B$6*(1+D$17)^1/(1+$A24)^1+Scenario!$B$6*(1+D$17)^2/(1+$A24)^2+Scenario!$B$6*(1+D$17)^3/(1+$A24)^3+Scenario!$B$6*(1+D$17)^4/(1+$A24)^4+Scenario!$B$6*(1+D$17)^5/(1+$A24)^5+(Scenario!$B$6*(1+D$17)^5*(1+Scenario!$B$12)/($A24-Scenario!$B$12))/(1+$A24)^5)-Scenario!$B$14)/Scenario!$B$15,""),"")) | E24: =IF($A24<=Scenario!$B$12,"n/m",IFERROR(IF(Scenario!$B$15>0,((Scenario!$B$6*(1+E$17)^1/(1+$A24)^1+Scenario!$B$6*(1+E$17)^2/(1+$A24)^2+Scenario!$B$6*(1+E$17)^3/(1+$A24)^3+Scenario!$B$6*(1+E$17)^4/(1+$A24)^4+Scenario!$B$6*(1+E$17)^5/(1+$A24)^5+(Scenario!$B$6*(1+E$17)^5*(1+Scenario!$B$12)/($A24-Scenario!$B$12))/(1+$A24)^5)-Scenario!$B$14)/Scenario!$B$15,""),"")) | F24: =IF($A24<=Scenario!$B$12,"n/m",IFERROR(IF(Scenario!$B$15>0,((Scenario!$B$6*(1+F$17)^1/(1+$A24)^1+Scenario!$B$6*(1+F$17)^2/(1+$A24)^2+Scenario!$B$6*(1+F$17)^3/(1+$A24)^3+Scenario!$B$6*(1+F$17)^4/(1+$A24)^4+Scenario!$B$6*(1+F$17)^5/(1+$A24)^5+(Scenario!$B$6*(1+F$17)^5*(1+Scenario!$B$12)/($A24-Scenario!$B$12))/(1+$A24)^5)-Scenario!$B$14)/Scenario!$B$15,""),""))
A26: Reference: current price | B26: =Scenario!$B$5
A27: Reference: Scenario value per share | B27: =Scenario!$B$33

Sheet Journal
A1: JOURNAL — INVESTMENT LOG
A2: One row per decision. Write the thesis before you buy, not after.
A3: LEGEND: every cell from row 6 down is yours to fill in (yellow fill, blue text). Row 5 is a worked example — overwrite or delete it. Percentages are stored as fractions, so type 30% or 0.30, not 30.
A4: Date Analysed | B4: Ticker | C4: Name | D4: Price at Analysis | E4: Blended IV | F4: MOS at Analysis | G4: Verdict | H4: Thesis | I4: Why It Is Cheap | J4: Catalyst | K4: Key Risks | L4: What Would Invalidate | M4: Target Price | N4: Expected Return | O4: Position Taken? | P4: Review Date | Q4: Outcome | R4: Notes
A5: EXAMPLE — 2026-09-04 | B5: DKFT | C5: Central Omega Resources Tbk. | D5: 685 | E5: 894.36 | F5: 0.2341 | G5: WATCH | H5: Cash-generative franchise trading below the blended intrinsic value of every lens; balance sheet carries net cash, so the downside is earnings normalisation rather than solvency. | I5: Cyclical earnings peak scares the market; index funds have been sellers since the sector reweighting. | J5: Full-year results confirming margin stabilisation, plus the declared dividend at the historical payout. | K5: Commodity price reversal, IDR depreciation on imported input costs, minority-shareholder governance. | L5: Two consecutive quarters of negative operating cash flow, or net debt/EBITDA above 2.0x. | M5: 804.92 | N5: 0.1751 | O5: No — watching for a 30% MOS | P5: 2026-11-15 | Q5: Open | R5: Sized at 4% if entered. Revisit after Q3 filing.

Sheet Setup
A1: SETUP — Model Assumptions
A2: Every value below is referenced by formulas elsewhere in this workbook. Change one and the model moves.
A3: Assumption | B3: Value | C3: Consumed by
A4: Tax Rate | B4: 0.22 | C4: Company!EPV cross-check (NOPAT = Normalised EBIT x (1 - Tax Rate))
A5: WACC (discount rate) | B5: 0.12 | C5: Scenario!B13 discount rate; Sensitivity (both grids, via Scenario); Company!EPV cross-check
A6: Terminal Growth | B6: 0.03 | C6: Scenario!B12 terminal growth + growth fade; Sensitivity grid axes
A7: Risk Free Rate | B7: 0.065 | C7: Company!Cost of equity (CAPM) = RF + Beta x ERP
A8: Equity Risk Premium | B8: 0.055 | C8: Company!Cost of equity (CAPM)
A9: MOS Buy threshold | B9: 0.3 | C9: Dashboard!count above buy MOS; Company!verdict test; Scenario!verdict test
A10: MOS Watch threshold | B10: 0.1 | C10: Dashboard!count above watch MOS; Company!verdict test; Scenario!verdict test
A12: Yellow cells with blue text are inputs — edit them directly.
A13: Black text = formula on the same sheet. Green text = link to another sheet in this workbook.
A14: Formula portability: this workbook uses only functions that behave identically in Microsoft Excel and Google Sheets (INDEX/MATCH rather than XLOOKUP/FILTER/QUERY).

Sheet RAW_idx_stocks
A1: Ticker | B1: Name | C1: IPO Date | D1: Outstanding Shares | E1: Note | F1: Price | G1: Volume | H1: Change | I1: Percentage Change | J1: Average | K1: Close Price | L1: High Price | M1: Open Price | N1: Low Price | O1: ARA Price | P1: ARB Price | Q1: Frequency | R1: Frequency Sell | S1: Frequency Buy | T1: 52W High | U1: 52W Low | V1: Pct From 52W High | W1: 1Y Price Change | X1: Currency | Y1: Fetched At
A2: AADI | B2: Adaro Andalan Indonesia Tbk. | C2: 05 Des 2024 | D2: 7.7868916e+09 | E2: UTAMA | F2: 9225 | G2: 1125400 | H2: 50 | I2: 0.5449591 | J2: 9175 | K2: 9225 | L2: 9250 | M2: 9200 | N2: 9175 | T2: 11800 | U2: 6700 | V2: -0.21822034 | W2: 0.28125 | X2: IDR | Y2: 2026-09-04T08:18:41
A3: AALI | B3: Astra Agro Lestari Tbk. | C3: 09 Des 1997 | D3: 1.9246884e+09 | E3: UTAMA | F3: 7350 | G3: 207200 | H3: 25 | I3: 0.34129694 | J3: 7325 | K3: 7350 | L3: 7375 | M3: 7350 | N3: 7300 | T3: 9000 | U3: 5825 | V3: -0.18333333 | W3: 0.024390244 | X3: IDR | Y3: 2026-09-04T08:18:41
A4: ABBA | B4: Mahaka Media Tbk. | C4: 2002-04-03 00:00:00 | D4: 3.9358928e+09 | E4: PEMANTAUAN KHUSUS | F4: 30 | G4: 153000 | H4: 0 | I4: 0 | J4: 30 | K4: 30 | L4: 30 | M4: 30 | N4: 30 | T4: 97 | U4: 29 | V4: -0.69072165 | W4: -0.16666667 | X4: IDR | Y4: 2026-09-04T08:18:41
A5: ABDA | B5: Asuransi Bina Dana Arta Tbk. | C5: 1989-07-06 00:00:00 | D5: 6.2080663e+08 | E5: PEMANTAUAN KHUSUS | F5: 3850 | G5: 1900 | H5: 20 | I5: 0.52219317 | J5: 3830 | K5: 3850 | L5: 3850 | M5: 3830 | N5: 3830 | T5: 4760 | U5: 2230 | V5: -0.19117647 | W5: 0.13235294 | X5: IDR | Y5: 2026-09-04T08:18:41
A6: ABMM | B6: ABM Investama Tbk. | C6: 06 Des 2011 | D6: 2.753165e+09 | E6: UTAMA | F6: 2720 | G6: 132500 | H6: 40 | I6: 1.4869889 | J6: 2680 | K6: 2720 | L6: 2730 | M6: 2710 | N6: 2700 | T6: 3190 | U6: 2120 | V6: -0.14733542 | W6: -0.090301003 | X6: IDR | Y6: 2026-09-04T08:18:41
A7: ACES | B7: Aspirasi Hidup Indonesia Tbk. | C7: 2007-11-06 00:00:00 | D7: 1.712039e+10 | E7: UTAMA | F7: 358 | G7: 3640100 | H7: 0 | I7: 0 | J7: 358 | K7: 358 | L7: 360 | M7: 358 | N7: 356 | T7: 494 | U7: 310 | V7: -0.27530364 | W7: -0.24789916 | X7: IDR | Y7: 2026-09-04T08:18:41
A8: ACRO | B8: Samcro Hyosung Adilestari Tbk. | C8: 2024-01-11 00:00:00 | D8: 3.4693456e+09 | E8: PENGEMBANGAN | F8: 62 | G8: 1128700 | H8: 0 | I8: 0 | J8: 62 | K8: 62 | L8: 62 | M8: 62 | N8: 61 | T8: 128 | U8: 51 | V8: -0.515625 | W8: -0.11428571 | X8: IDR | Y8: 2026-09-04T08:18:41
A9: ACST | B9: Acset Indonusa Tbk. | C9: 2013-06-24 00:00:00 | D9: 1.7675159e+10 | E9: PENGEMBANGAN | F9: 84 | G9: 70600 | H9: 0 | I9: 0 | J9: 84 | K9: 84 | L9: 84 | M9: 84 | N9: 84 | T9: 204 | U9: 69 | V9: -0.58823529 | W9: -0.045454545 | X9: IDR | Y9: 2026-09-04T08:18:41
A10: ADCP | B10: Adhi Commuter Properti Tbk. | C10: 21 Mei 2021 | D10: 2.2222222e+10 | E10: PENGEMBANGAN | F10: 50 | G10: 25400 | H10: 0 | I10: 0 | J10: 50 | K10: 50 | L10: 50 | M10: 50 | N10: 50 | T10: 75 | U10: 50 | V10: -0.33333333 | W10: 0 | X10: IDR | Y10: 2026-09-04T08:18:41
A11: ADES | B11: Akasha Wira International Tbk. | C11: 1994-06-13 00:00:00 | D11: 5.8989686e+08 | E11: PENGEMBANGAN | F11: 35000 | G11: 31900 | H11: 0 | I11: 0 | J11: 35000 | K11: 35000 | L11: 35000 | M11: 35000 | N11: 35000 | T11: 40000 | U11: 12900 | V11: -0.125 | W11: 1.3450586 | X11: IDR | Y11: 2026-09-04T08:18:41
A12: ADHI | B12: Adhi Karya (Persero) Tbk. | C12: 2004-03-18 00:00:00 | D12: 8.407609e+09 | E12: UTAMA | F12: 148 | G12: 4876700 | H12: -1 | I12: -0.6666667 | J12: 149 | K12: 148 | L12: 149 | M12: 147 | N12: 147 | T12: 318 | U12: 130 | V12: -0.53459119 | W12: -0.4751773 | X12: IDR | Y12: 2026-09-04T08:18:41
A13: ADMF | B13: Adira Dinamika Multi Finance Tbk. | C13: 2004-03-31 00:00:00 | D13: 1.2259869e+09 | E13: PENGEMBANGAN | F13: 8650 | G13: 11400 | H13: -75 | I13: -0.8595989 | J13: 8725 | K13: 8650 | L13: 8725 | M13: 8725 | N13: 8625 | T13: 9175 | U13: 7675 | V13: -0.057220708 | W13: -0.044198895 | X13: IDR | Y13: 2026-09-04T08:18:41
... A56: ARKO | B56: Arkora Hydro Tbk. | C56: 2022-07-08 00:00:00 | D56: 2.928495e+09 | E56: PENGEMBANGAN | F56: 4790 | G56: 1951900 | H56: 260 | I56: 5.7395145 | J56: 4530 | K56: 4790 | L56: 4840 | M56: 4570 | N56: 4540 | T56: 13000 | U56: 1065 | V56: -0.63153846 | W56: 3.2389381 | X56: IDR | Y56: 2026-09-04T08:18:41
A57: ARMY | B57: Armidian Karyatama Tbk. | C57: 2017-06-21 00:00:00 | E57: PEMANTAUAN KHUSUS | F57: 50 | G57: 38700 | H57: 0 | I57: 0 | J57: 50 | K57: 50 | L57: 50 | M57: 50 | N57: 50 | T57: 50 | U57: 50 | V57: 0 | W57: 0 | X57: IDR | Y57: 2026-09-04T08:18:41
A58: ARNA | B58: Arwana Citramulia Tbk. | C58: 2001-07-17 00:00:00 | D58: 7.029977e+09 | E58: UTAMA | F58: 500 | G58: 736800 | H58: 0 | I58: 0 | J58: 500 | K58: 500 | L58: 500 | M58: 500 | N58: 496 | T58: 585 | U58: 392 | V58: -0.14529915 | W58: -0.13043478 | X58: IDR | Y58: 2026-09-04T08:18:41
A59: ARTA | B59: Arthavest Tbk. | C59: 2002-11-05 00:00:00 | D59: 4.4667419e+08 | E59: PENGEMBANGAN | F59: 2370 | G59: 1000 | H59: 10 | I59: 0.4237288 | J59: 2360 | K59: 2370 | L59: 2370 | M59: 2360 | N59: 2360 | T59: 4370 | U59: 1910 | V59: -0.4576659 | W59: -0.35245902 | X59: IDR | Y59: 2026-09-04T08:18:41
A60: ARTI | B60: Ratu Prabu Energi Tbk. | C60: 2003-04-30 00:00:00 | D60: 7840000000 | E60: PEMANTAUAN KHUSUS | F60: 2 | G60: 0 | H60: 0 | I60: 0 | J60: 2 | K60: 2 | L60: 2 | M60: 0 | N60: 2 | T60: 2 | U60: 2 | V60: 0 | W60: 0 | X60: IDR | Y60: 2026-09-04T08:18:41
A61: ARTO | B61: Bank Jago Tbk. | C61: 2016-01-12 00:00:00 | D61: 1.3861331e+10 | E61: UTAMA | F61: 1310 | G61: 792400 | H61: 5 | I61: 0.38314175 | J61: 1305 | K61: 1310 | L61: 1320 | M61: 1305 | N61: 1305 | T61: 2440 | U61: 740 | V61: -0.46311475 | W61: -0.345 | X61: IDR | Y61: 2026-09-04T08:18:41
A62: ASBI | B62: Asuransi Bintang Tbk. | C62: 1989-11-29 00:00:00 | D62: 3.4838648e+08 | E62: PENGEMBANGAN | F62: 430 | G62: 12400 | H62: 0 | I62: 0 | J62: 430 | K62: 430 | L62: 430 | M62: 422 | N62: 416 | T62: 585 | U62: 370 | V62: -0.26495726 | W62: -0.013761468 | X62: IDR | Y62: 2026-09-04T08:18:41
A63: ASDM | B63: Asuransi Dayin Mitra Tbk. | C63: 15 Des 1989 | D63: 3.8399998e+08 | E63: PENGEMBANGAN | F63: 515 | G63: 11300 | H63: -5 | I63: -0.9615384 | J63: 520 | K63: 515 | L63: 520 | M63: 520 | N63: 510 | T63: 765 | U63: 488 | V63: -0.32679739 | W63: -0.037383178 | X63: IDR | Y63: 2026-09-04T08:18:41
A64: ASGR | B64: Astra Graphia Tbk. | C64: 1989-11-15 00:00:00 | D64: 1.3487805e+09 | E64: UTAMA | F64: 1790 | G64: 64600 | H64: 5 | I64: 0.28089888 | J64: 1785 | K64: 1790 | L64: 1795 | M64: 1785 | N64: 1785 | T64: 1970 | U64: 1025 | V64: -0.091370558 | W64: 0.65740741 | X64: IDR | Y64: 2026-09-04T08:18:41
A65: ASHA | B65: Cilacap Samudera Fishing Industry Tbk. | C65: 27 Mei 2022 | D65: 4.9999999e+09 | E65: PENGEMBANGAN | F65: 62 | G65: 14726800 | H65: 2 | I65: 3.333333 | J65: 60 | K65: 62 | L65: 62 | M65: 61 | N65: 60 | T65: 125 | U65: 19 | V65: -0.504 | W65: 2.2631579 | X65: IDR | Y65: 2026-09-04T08:18:41
A66: ASII | B66: Astra International Tbk. | C66: 1990-04-04 00:00:00 | D66: 3.9920063e+10 | E66: UTAMA | F66: 5050 | G66: 16062700 | H66: -50 | I66: -0.9803922 | J66: 5100 | K66: 5050 | L66: 5100 | M66: 5100 | N66: 4970 | T66: 7475 | U66: 4350 | V66: -0.32441472 | W66: 0.030612245 | X66: IDR | Y66: 2026-09-04T08:18:41
A67: ASJT | B67: Asuransi Jasa Tania Tbk. | C67: 23 Des 2003 | D67: 1.3999999e+09 | E67: PENGEMBANGAN | F67: 153 | G67: 212000 | H67: 0 | I67: 0 | J67: 153 | K67: 153 | L67: 153 | M67: 152 | N67: 150 | T67: 286 | U67: 101 | V67: -0.46503497 | W67: 0.39090909 | X67: IDR | Y67: 2026-09-04T08:18:41
A68: ASLC | B68: Autopedia Sukses Lestari Tbk. | C68: 2022-01-25 00:00:00 | D68: 12746354688 | E68: PENGEMBANGAN | F68: 64 | G68: 4026100 | H68: 1 | I68: 1.5873017 | J68: 63 | K68: 64 | L68: 64 | M68: 64 | N68: 63 | T68: 136 | U68: 50 | V68: -0.52941176 | W68: 0 | X68: IDR | Y68: 2026-09-04T08:18:41
A69: ASLI | B69: Asri Karya Lestari Tbk. | C69: 2024-01-05 00:00:00 | D69: 6.25e+09 | E69: PENGEMBANGAN | F69: 197 | G69: 3098900 | H69: -2 | I69: -1.0050251 | J69: 199 | K69: 197 | L69: 199 | M69: 199 | N69: 192 | T69: 750 | U69: 50 | V69: -0.73733333 | W69: 2.94 | X69: IDR | Y69: 2026-09-04T08:18:41
... A179: BTEK | B179: Bumi Teknokultura Unggul Tbk. | C179: 14 Mei 2004 | D179: 4.6277496e+10 | E179: PEMANTAUAN KHUSUS | F179: 11 | G179: 13478600 | H179: 0 | I179: 0 | J179: 11 | K179: 11 | L179: 11 | M179: 11 | N179: 11 | T179: 42 | U179: 5 | V179: -0.73809524 | W179: 1.2 | X179: IDR | Y179: 2026-09-04T08:18:42
A180: BTEL | B180: Bakrie Telecom Tbk. | C180: 2006-02-03 00:00:00 | E180: PEMANTAUAN KHUSUS | F180: 50 | H180: 0 | I180: 0 | J180: 50 | K180: 50 | T180: 50 | U180: 50 | V180: 0 | W180: 0 | X180: IDR | Y180: 2026-09-04T08:18:42
A181: BTON | B181: Betonjaya Manunggal Tbk. | C181: 2001-07-18 00:00:00 | D181: 720000000 | E181: PENGEMBANGAN | F181: 368 | G181: 3400 | H181: 0 | I181: 0 | J181: 368 | K181: 368 | L181: 368 | M181: 368 | N181: 368 | T181: 456 | U181: 308 | V181: -0.19298246 | W181: -0.051546392 | X181: IDR | Y181: 2026-09-04T08:18:42
A182: BTPN | B182: Bank SMBC Indonesia Tbk. | C182: 2008-03-12 00:00:00 | D182: 1.0645945e+10 | E182: UTAMA | F182: 2140 | G182: 12000 | H182: -20 | I182: -0.9259259 | J182: 2160 | K182: 2140 | L182: 2150 | M182: 2150 | N182: 2100 | T182: 2530 | U182: 1900 | V182: -0.1541502 | W182: 0.028846154 | X182: IDR | Y182: 2026-09-04T08:18:42
A183: BTPS | B183: Bank BTPN Syariah Tbk. | C183: 08 Mei 2018 | D183: 7.7036998e+09 | E183: UTAMA | F183: 995 | G183: 551100 | H183: 5 | I183: 0.50505046 | J183: 990 | K183: 995 | L183: 1000 | M183: 995 | N183: 985 | T183: 1575 | U183: 835 | V183: -0.36825397 | W183: -0.32312925 | X183: IDR | Y183: 2026-09-04T08:18:42
A184: BUAH | B184: Segar Kumala Indonesia Tbk. | C184: 09 Agt 2022 | D184: 2e+09 | E184: PENGEMBANGAN | F184: 515 | G184: 30600 | H184: 5 | I184: 0.9803922 | J184: 510 | K184: 515 | L184: 515 | M184: 510 | N184: 510 | T184: 825 | U184: 440 | V184: -0.37575758 | W184: -0.21969697 | X184: IDR | Y184: 2026-09-04T08:18:42
A185: BUDI | B185: Budi Starch & Sweetener Tbk. | C185: 08 Mei 1995 | D185: 4.4912768e+09 | E185: UTAMA | F185: 218 | G185: 85500 | H185: 2 | I185: 0.9259259 | J185: 216 | K185: 218 | L185: 222 | M185: 216 | N185: 216 | T185: 268 | U185: 199 | V185: -0.18656716 | W185: -0.052173913 | X185: IDR | Y185: 2026-09-04T08:18:42
A186: BUKA | B186: Bukalapak.com Tbk. | C186: 06 Agt 2021 | D186: 9.1833655e+10 | E186: EKONOMI BARU | F186: 118 | G186: 11711300 | H186: 0 | I186: 0 | J186: 118 | K186: 118 | L186: 119 | M186: 119 | N186: 117 | T186: 198 | U186: 93 | V186: -0.4040404 | W186: -0.32183908 | X186: IDR | Y186: 2026-09-04T08:18:42
A187: BUKK | B187: Bukaka Teknik Utama Tbk. | C187: 2015-06-29 00:00:00 | D187: 2.6404521e+09 | E187: UTAMA | F187: 1030 | G187: 18300 | H187: 20 | I187: 1.904762 | J187: 1010 | K187: 1030 | L187: 1080 | M187: 1010 | N187: 1010 | T187: 2750 | U187: 625 | V187: -0.62545455 | W187: 0.27160494 | X187: IDR | Y187: 2026-09-04T08:18:42
A188: BULL | B188: Buana Lintas Lautan Tbk. | C188: 23 Mei 2011 | D188: 1.5494437e+10 | E188: PENGEMBANGAN | F188: 464 | G188: 676130500 | H188: 12 | I188: 2.6548672 | J188: 452 | K188: 464 | L188: 478 | M188: 460 | N188: 456 | T188: 685 | U188: 147 | V188: -0.32262774 | W188: 2.0326797 | X188: IDR | Y188: 2026-09-04T08:18:42
A189: BUMI | B189: Bumi Resources Tbk. | C189: 1990-07-30 00:00:00 | D189: 3.7133541e+11 | E189: UTAMA | F189: 192 | G189: 2112600800 | H189: 5 | I189: 2.6595745 | J189: 187 | K189: 192 | L189: 194 | M189: 189 | N189: 186 | T189: 484 | U189: 103 | V189: -0.60330579 | W189: 0.77777778 | X189: IDR | Y189: 2026-09-04T08:18:42
A190: BUVA | B190: Bukit Uluwatu Villa Tbk. | C190: 2010-07-12 00:00:00 | D190: 2.4617055e+10 | E190: PENGEMBANGAN | F190: 790 | G190: 51707000 | H190: 5 | I190: 0.63291136 | J190: 785 | K190: 790 | L190: 795 | M190: 785 | N190: 770 | T190: 2320 | U190: 260 | V190: -0.65948276 | W190: 2.0384615 | X190: IDR | Y190: 2026-09-04T08:18:42
A191: BVIC | B191: Bank Victoria International Tbk. | C191: 1999-06-30 00:00:00 | D191: 1.8419418e+10 | E191: UTAMA | F191: 93 | G191: 278300 | H191: 0 | I191: 0 | J191: 93 | K191: 93 | L191: 94 | M191: 94 | N191: 93 | T191: 185 | U191: 69 | V191: -0.4972973 | W191: 0 | X191: IDR | Y191: 2026-09-04T08:18:42
A192: BWPT | B192: Eagle High Plantations Tbk. | C192: 27 Okt 2009 | D192: 3.112237e+10 | E192: UTAMA | F192: 93 | G192: 61782800 | H192: 1 | I192: 1.0869565 | J192: 92 | K192: 93 | L192: 94 | M192: 92 | N192: 91 | T192: 193 | U192: 60 | V192: -0.51813472 | W192: -0.225 | X192: IDR | Y192: 2026-09-04T08:18:42
... A231: COIN | B231: Indokripto Koin Semesta Tbk. | C231: 2025-07-09 00:00:00 | D231: 1.4705882e+10 | E231: PENGEMBANGAN | F231: 740 | G231: 5199100 | H231: 20 | I231: 2.7586207 | J231: 720 | K231: 740 | L231: 745 | M231: 735 | N231: 720 | T231: 4800 | U231: 570 | V231: -0.84583333 | W231: -0.54601227 | X231: IDR | Y231: 2026-09-04T08:18:42
A232: COWL | B232: Cowell Development Tbk. | C232: 19 Des 2007 | E232: PEMANTAUAN KHUSUS | F232: 50 | G232: 100 | H232: 0 | I232: 0 | J232: 50 | K232: 50 | L232: 50 | M232: 50 | N232: 50 | T232: 50 | U232: 50 | V232: 0 | W232: 0 | X232: IDR | Y232: 2026-09-04T08:18:42
A233: CPIN | B233: Charoen Pokphand Indonesia Tbk. | C233: 1991-03-18 00:00:00 | D233: 1.6398e+10 | E233: UTAMA | F233: 3140 | G233: 3898100 | H233: 0 | I233: 0 | J233: 3140 | K233: 3140 | L233: 3160 | M233: 3150 | N233: 3120 | T233: 5375 | U233: 3010 | V233: -0.41581395 | W233: -0.29596413 | X233: IDR | Y233: 2026-09-04T08:18:42
A234: CPRI | B234: Capri Nusa Satu Properti Tbk. | C234: 2019-04-11 00:00:00 | D234: 2.4333799e+09 | E234: PEMANTAUAN KHUSUS | F234: 50 | G234: 0 | H234: 0 | I234: 0 | J234: 50 | K234: 50 | L234: 50 | M234: 0 | N234: 50 | T234: 50 | U234: 50 | V234: 0 | W234: 0 | X234: IDR | Y234: 2026-09-04T08:18:42
A235: CPRO | B235: Central Proteina Prima Tbk. | C235: 2006-11-28 00:00:00 | D235: 5.9572381e+10 | E235: PENGEMBANGAN | F235: 50 | G235: 7017100 | H235: -1 | I235: -1.9607844 | J235: 51 | K235: 50 | L235: 51 | M235: 51 | N235: 50 | T235: 88 | U235: 50 | V235: -0.43181818 | W235: -0.019607843 | X235: IDR | Y235: 2026-09-04T08:18:42
A236: CRAB | B236: Toba Surimi Industries Tbk. | C236: 10 Agt 2022 | D236: 1.95e+09 | E236: PENGEMBANGAN | F236: 208 | G236: 853500 | H236: 0 | I236: 0 | J236: 208 | K236: 208 | L236: 212 | M236: 212 | N236: 208 | T236: 390 | U236: 199 | V236: -0.46666667 | W236: -0.12605042 | X236: IDR | Y236: 2026-09-04T08:18:42
A237: CRSN | B237: Carsurin Tbk. | C237: 2023-07-10 00:00:00 | D237: 2.8920001e+09 | E237: PENGEMBANGAN | F237: 124 | G237: 4349400 | H237: 9 | I237: 7.826087 | J237: 115 | K237: 124 | L237: 125 | M237: 116 | N237: 116 | T237: 198 | U237: 83 | V237: -0.37373737 | W237: 0.13761468 | X237: IDR | Y237: 2026-09-04T08:18:42
A238: CSAP | B238: Catur Sentosa Adiprana Tbk. | C238: 12 Des 2007 | D238: 5.6831751e+09 | E238: PENGEMBANGAN | F238: 292 | G238: 17800 | H238: 2 | I238: 0.68965517 | J238: 290 | K238: 292 | L238: 300 | M238: 300 | N238: 292 | T238: 384 | U238: 258 | V238: -0.23958333 | W238: 0.12307692 | X238: IDR | Y238: 2026-09-04T08:18:42
A239: CSIS | B239: Cahayasakti Investindo Sukses Tbk. | C239: 10 Mei 2017 | D239: 1.8298029e+09 | E239: PENGEMBANGAN | F239: 196 | G239: 851900 | H239: -4 | I239: -2 | J239: 200 | K239: 196 | L239: 202 | M239: 200 | N239: 195 | T239: 619.811 | U239: 95 | V239: -0.68377457 | W239: 0.86666667 | X239: IDR | Y239: 2026-09-04T08:18:42
A240: CSMI | B240: Cipta Selera Murni Tbk. | C240: 2020-04-09 00:00:00 | D240: 8.160615e+08 | E240: PENGEMBANGAN | F240: 81 | G240: 6654400 | H240: 2 | I240: 2.5316454 | J240: 79 | K240: 81 | L240: 82 | M240: 80 | N240: 79 | T240: 640 | U240: 57 | V240: -0.8734375 | W240: -0.80528846 | X240: IDR | Y240: 2026-09-04T08:18:42
A241: CSRA | B241: Cisadane Sawit Raya Tbk. | C241: 2020-01-09 00:00:00 | D241: 2.0499999e+09 | E241: UTAMA | F241: 755 | G241: 24000 | H241: 5 | I241: 0.6666667 | J241: 750 | K241: 755 | L241: 755 | M241: 750 | N241: 750 | T241: 1085 | U241: 640 | V241: -0.30414747 | W241: 0.013422819 | X241: IDR | Y241: 2026-09-04T08:18:42
A242: CTBN | B242: Citra Tubindo Tbk. | C242: 1989-11-28 00:00:00 | D242: 8.0037152e+08 | E242: PENGEMBANGAN | F242: 4050 | G242: 200 | H242: 50 | I242: 1.25 | J242: 4000 | K242: 4050 | L242: 4050 | M242: 4050 | N242: 4050 | T242: 9100 | U242: 3950 | V242: -0.55494505 | W242: -0.33057851 | X242: IDR | Y242: 2026-09-04T08:18:42
A243: CTRA | B243: Ciputra Development Tbk. | C243: 1994-03-28 00:00:00 | D243: 1.8535695e+10 | E243: UTAMA | F243: 630 | G243: 2365300 | H243: 5 | I243: 0.8 | J243: 625 | K243: 630 | L243: 635 | M243: 630 | N243: 625 | T243: 1110 | U243: 510 | V243: -0.43243243 | W243: -0.37 | X243: IDR | Y243: 2026-09-04T08:18:42
A244: CTTH | B244: Citatah Tbk. | C244: 1996-07-03 00:00:00 | D244: 1230839808 | E244: PENGEMBANGAN | F244: 136 | G244: 8385700 | H244: 2 | I244: 1.4925373 | J244: 134 | K244: 136 | L244: 142 | M244: 134 | N244: 134 | T244: 250 | U244: 25 | V244: -0.456 | W244: 4.44 | X244: IDR | Y244: 2026-09-04T08:18:42
... A347: GOLF | B347: Intra Golflink Resorts Tbk. | C347: 2024-07-08 00:00:00 | D347: 1.9486761e+10 | E347: UTAMA | F347: 167 | G347: 1455000 | H347: -3 | I347: -1.764706 | J347: 170 | K347: 167 | L347: 173 | M347: 172 | N347: 166 | T347: 454 | U347: 119 | V347: -0.63215859 | W347: -0.21962617 | X347: IDR | Y347: 2026-09-04T08:18:42
A348: GOLL | B348: Golden Plantation Tbk. | C348: 23 Des 2014 | E348: PEMANTAUAN KHUSUS | F348: 50 | H348: 0 | I348: 0 | J348: 50 | K348: 50 | T348: 50 | U348: 50 | V348: 0 | W348: 0 | X348: IDR | Y348: 2026-09-04T08:18:42
A349: GOOD | B349: Garudafood Putra Putri Jaya Tbk. | C349: 10 Okt 2018 | D349: 3.6877602e+10 | E349: UTAMA | F349: 302 | G349: 27300 | H349: 2 | I349: 0.6666667 | J349: 300 | K349: 302 | L349: 302 | M349: 300 | N349: 300 | T349: 456 | U349: 286 | V349: -0.3377193 | W349: -0.20526316 | X349: IDR | Y349: 2026-09-04T08:18:42
A350: GOTO | B350: GoTo Gojek Tokopedia Tbk. | C350: 2022-04-11 00:00:00 | D350: 1.0660924e+12 | E350: EKONOMI BARU | F350: 50 | G350: 18534100 | H350: 0 | I350: 0 | J350: 50 | K350: 50 | L350: 50 | M350: 50 | N350: 50 | T350: 73 | U350: 50 | V350: -0.31506849 | W350: -0.19354839 | X350: IDR | Y350: 2026-09-04T08:18:42
A351: GPRA | B351: Perdana Gapuraprima Tbk. | C351: 10 Okt 2007 | D351: 4.2766554e+09 | E351: PENGEMBANGAN | F351: 109 | G351: 127677100 | H351: 2 | I351: 1.8691588 | J351: 107 | K351: 109 | L351: 111 | M351: 107 | N351: 105 | T351: 160 | U351: 92 | V351: -0.31875 | W351: -0.30128205 | X351: IDR | Y351: 2026-09-04T08:18:42
A352: GPSO | B352: Geoprima Solusi Tbk. | C352: 2021-09-06 00:00:00 | D352: 7.334151e+08 | E352: PENGEMBANGAN | F352: 294 | G352: 19173300 | H352: 16 | I352: 5.755396 | J352: 278 | K352: 294 | L352: 296 | M352: 282 | N352: 282 | T352: 1395 | U352: 248 | V352: -0.78924731 | W352: -0.27227723 | X352: IDR | Y352: 2026-09-04T08:18:42
A353: GRIA | B353: Ingria Pratama Capitalindo Tbk. | C353: 08 Agt 2023 | D353: 7.3757202e+09 | E353: PENGEMBANGAN | F353: 143 | G353: 1820500 | H353: 1 | I353: 0.70422534 | J353: 142 | K353: 143 | L353: 145 | M353: 145 | N353: 141 | T353: 210 | U353: 80 | V353: -0.31904762 | W353: 0.53763441 | X353: IDR | Y353: 2026-09-04T08:18:42
A354: GRPH | B354: Griptha Putra Persada Tbk. | C354: 2024-01-17 00:00:00 | D354: 9.9999999e+08 | E354: PENGEMBANGAN | F354: 61 | G354: 2828200 | H354: 0 | I354: 0 | J354: 61 | K354: 61 | L354: 62 | M354: 61 | N354: 60 | T354: 98 | U354: 50 | V354: -0.37755102 | W354: 0.22 | X354: IDR | Y354: 2026-09-04T08:18:42
A355: GRPM | B355: Graha Prima Mentari Tbk. | C355: 2023-07-10 00:00:00 | D355: 1.5716665e+09 | E355: AKSELERASI | F355: 240 | G355: 491300 | H355: 4 | I355: 1.6949153 | J355: 236 | K355: 240 | L355: 256 | M355: 256 | N355: 228 | T355: 525 | U355: 46 | V355: -0.54285714 | W355: 4.106383 | X355: IDR | Y355: 2026-09-04T08:18:42
A356: GSMF | B356: Equity Development Investment Tbk. | C356: 23 Okt 1989 | D356: 1.42304e+10 | E356: PENGEMBANGAN | F356: 89 | G356: 957200 | H356: 2 | I356: 2.2727273 | J356: 87 | K356: 89 | L356: 90 | M356: 86 | N356: 86 | T356: 167 | U356: 54 | V356: -0.46706587 | W356: 0.61818182 | X356: IDR | Y356: 2026-09-04T08:18:42
A357: GTBO | B357: Garda Tujuh Buana Tbk. | C357: 2009-07-09 00:00:00 | D357: 2.5000001e+09 | E357: PENGEMBANGAN | F357: 170 | G357: 1700 | H357: 0 | I357: 0 | J357: 170 | K357: 170 | L357: 170 | M357: 160 | N357: 160 | T357: 328 | U357: 160 | V357: -0.48170732 | W357: -0.090909091 | X357: IDR | Y357: 2026-09-04T08:18:42
A358: GTRA | B358: Grahaprima Suksesmandiri Tbk. | C358: 2023-03-30 00:00:00 | D358: 1.894375e+09 | E358: PENGEMBANGAN | F358: 252 | G358: 78800 | H358: 0 | I358: 0 | J358: 252 | K358: 252 | L358: 258 | M358: 252 | N358: 246 | T358: 446 | U358: 128 | V358: -0.43497758 | W358: 0.76223776 | X358: IDR | Y358: 2026-09-04T08:18:42
A359: GTSI | B359: GTS Internasional Tbk. | C359: 2021-09-08 00:00:00 | D359: 1.5819143e+10 | E359: UTAMA | F359: 191 | G359: 19575800 | H359: -1 | I359: -0.5208333 | J359: 192 | K359: 191 | L359: 194 | M359: 192 | N359: 190 | T359: 520 | U359: 45 | V359: -0.63269231 | W359: 3.0638298 | X359: IDR | Y359: 2026-09-04T08:18:42
A360: GULA | B360: Aman Agrindo Tbk. | C360: 03 Agt 2022 | D360: 1.0703625e+09 | E360: PENGEMBANGAN | F360: 750 | G360: 7940900 | H360: 5 | I360: 0.671141 | J360: 745 | K360: 750 | L360: 755 | M360: 745 | N360: 740 | T360: 870 | U360: 232 | V360: -0.13793103 | W360: 1.9069767 | X360: IDR | Y360: 2026-09-04T08:18:42
... A381: HOKI | B381: Buyung Poetra Sembada Tbk. | C381: 2017-06-22 00:00:00 | D381: 9.6777524e+09 | E381: PENGEMBANGAN | F381: 55 | G381: 15359600 | H381: 1 | I381: 1.8518519 | J381: 54 | K381: 55 | L381: 57 | M381: 54 | N381: 54 | T381: 107 | U381: 50 | V381: -0.48598131 | W381: -0.35294118 | X381: IDR | Y381: 2026-09-04T08:18:43
A382: HOME | B382: Hotel Mandarine Regency Tbk. | C382: 2008-07-17 00:00:00 | E382: PEMANTAUAN KHUSUS | F382: 50 | G382: 703700 | H382: 0 | I382: 0 | J382: 50 | K382: 50 | L382: 50 | M382: 50 | N382: 50 | T382: 50 | U382: 50 | V382: 0 | W382: 0 | X382: IDR | Y382: 2026-09-04T08:18:43
A383: HOMI | B383: Grand House Mulia Tbk. | C383: 2020-09-10 00:00:00 | D383: 1.5750001e+09 | E383: PENGEMBANGAN | F383: 186 | G383: 651300 | H383: 2 | I383: 1.0869565 | J383: 184 | K383: 186 | L383: 190 | M383: 184 | N383: 182 | T383: 900 | U383: 159 | V383: -0.79333333 | W383: -0.055837563 | X383: IDR | Y383: 2026-09-04T08:18:43
A384: HOPE | B384: Harapan Duta Pertiwi Tbk. | C384: 24 Mei 2021 | D384: 2.1303602e+09 | E384: PENGEMBANGAN | F384: 226 | G384: 21449100 | H384: 2 | I384: 0.88495575 | J384: 224 | K384: 226 | L384: 238 | M384: 226 | N384: 224 | T384: 420 | U384: 90 | V384: -0.46190476 | W384: 0.83739837 | X384: IDR | Y384: 2026-09-04T08:18:43
A385: HOTL | B385: Saraswati Griya Lestari Tbk. | C385: 2013-01-10 00:00:00 | D385: 3.5500003e+09 | E385: PEMANTAUAN KHUSUS | F385: 50 | G385: 0 | H385: 0 | I385: 0 | J385: 50 | K385: 50 | L385: 50 | M385: 0 | N385: 50 | T385: 50 | U385: 50 | V385: 0 | W385: 0 | X385: IDR | Y385: 2026-09-04T08:18:43
A386: HRME | B386: Menteng Heritage Realty Tbk. | C386: 2019-04-12 00:00:00 | D386: 5.9587501e+09 | E386: PEMANTAUAN KHUSUS | F386: 41 | G386: 268800 | H386: -1 | I386: -2.3809524 | J386: 42 | K386: 41 | L386: 41 | M386: 41 | N386: 41 | T386: 72 | U386: 32 | V386: -0.43055556 | W386: 0.17142857 | X386: IDR | Y386: 2026-09-04T08:18:43
A387: HRTA | B387: Hartadinata Abadi Tbk. | C387: 2017-06-21 00:00:00 | D387: 4.6052622e+09 | E387: UTAMA | F387: 2220 | G387: 11676300 | H387: 70 | I387: 3.2407407 | J387: 2150 | K387: 2220 | L387: 2270 | M387: 2180 | N387: 2180 | T387: 3440 | U387: 635 | V387: -0.35465116 | W387: 2.1489362 | X387: IDR | Y387: 2026-09-04T08:18:43
A388: HRUM | B388: Harum Energy Tbk. | C388: 06 Okt 2010 | D388: 1.3148557e+10 | E388: UTAMA | F388: 855 | G388: 21044400 | H388: 40 | I388: 4.9079757 | J388: 815 | K388: 855 | L388: 860 | M388: 820 | N388: 820 | T388: 1375 | U388: 595 | V388: -0.37818182 | W388: -0.017241379 | X388: IDR | Y388: 2026-09-04T08:18:43
A389: HUMI | B389: Humpuss Maritim Internasional Tbk. | C389: 09 Agt 2023 | D389: 1.8063334e+10 | E389: PENGEMBANGAN | F389: 152 | G389: 26656600 | H389: -1 | I389: -0.65789474 | J389: 153 | K389: 152 | L389: 157 | M389: 157 | N389: 150 | T389: 390 | U389: 65 | V389: -0.61025641 | W389: 1.3030303 | X389: IDR | Y389: 2026-09-04T08:18:43
A390: HYGN | B390: Ecocare Indo Pasifik Tbk. | C390: 2024-02-13 00:00:00 | D390: 2.4981703e+09 | E390: PENGEMBANGAN | F390: 168 | G390: 346000 | H390: 2 | I390: 1.2048193 | J390: 166 | K390: 168 | L390: 169 | M390: 166 | N390: 166 | T390: 197 | U390: 122 | V390: -0.14720812 | W390: 0.090909091 | X390: IDR | Y390: 2026-09-04T08:18:43
A391: IATA | B391: MNC Energy Investments Tbk. | C391: 2006-09-13 00:00:00 | D391: 3.1275829e+10 | E391: PENGEMBANGAN | F391: 127 | G391: 1824750500 | H391: 12 | I391: 10.434783 | J391: 115 | K391: 127 | L391: 132 | M391: 118 | N391: 117 | T391: 198 | U391: 51 | V391: -0.35858586 | W391: 1.2678571 | X391: IDR | Y391: 2026-09-04T08:18:43
A392: IBFN | B392: Intan Baru Prana Tbk. | C392: 22 Des 2014 | D392: 1.5173324e+09 | E392: PEMANTAUAN KHUSUS | F392: 63 | G392: 799400 | H392: 0 | I392: 0 | J392: 63 | K392: 63 | L392: 74 | M392: 74 | N392: 62 | T392: 242 | U392: 16 | V392: -0.73966942 | W392: 2.7058824 | X392: IDR | Y392: 2026-09-04T08:18:43
A393: IBOS | B393: Indo Boga Sukses Tbk. | C393: 2022-04-25 00:00:00 | D393: 8.0657897e+09 | E393: AKSELERASI | F393: 71 | G393: 3989400 | H393: 2 | I393: 2.8985508 | J393: 69 | K393: 71 | L393: 72 | M393: 70 | N393: 69 | T393: 200 | U393: 31 | V393: -0.645 | W393: 1.0882353 | X393: IDR | Y393: 2026-09-04T08:18:43
A394: IBST | B394: Inti Bangun Sejahtera Tbk. | C394: 31 Agt 2012 | D394: 1.350905e+09 | E394: PEMANTAUAN KHUSUS | F394: 8475 | G394: 900 | H394: 0 | I394: 0 | J394: 8475 | K394: 8475 | L394: 8475 | M394: 8450 | N394: 8450 | T394: 8475 | U394: 4210 | V394: 0 | W394: 0.5990566 | X394: IDR | Y394: 2026-09-04T08:18:43
... A401: IGAR | B401: Champion Pacific Indonesia Tbk. | C401: 1990-11-05 00:00:00 | D401: 9.2778057e+08 | E401: PENGEMBANGAN | F401: 448 | G401: 4800 | H401: 4 | I401: 0.9009009 | J401: 444 | K401: 448 | L401: 448 | M401: 448 | N401: 444 | T401: 775 | U401: 398 | V401: -0.42193548 | W401: -0.2 | X401: IDR | Y401: 2026-09-04T08:18:43
A402: IIKP | B402: Inti Agri Resources Tbk. | C402: 14 Okt 2002 | E402: PEMANTAUAN KHUSUS | F402: 50 | G402: 200 | H402: 0 | I402: 0 | J402: 50 | K402: 50 | L402: 50 | M402: 50 | N402: 50 | T402: 50 | U402: 50 | V402: 0 | W402: 0 | X402: IDR | Y402: 2026-09-04T08:18:43
A403: IKAI | B403: Intikeramik Alamasri Industri Tbk. | C403: 1997-06-04 00:00:00 | D403: 1.3305799e+10 | E403: PEMANTAUAN KHUSUS | F403: 21 | G403: 2054700 | H403: 1 | I403: 5 | J403: 20 | K403: 21 | L403: 21 | M403: 21 | N403: 21 | T403: 42 | U403: 8 | V403: -0.5 | W403: 1.625 | X403: IDR | Y403: 2026-09-04T08:18:43
A404: IKAN | B404: Era Mandiri Cemerlang Tbk. | C404: 2020-02-12 00:00:00 | D404: 8.3333299e+08 | E404: PENGEMBANGAN | F404: 87 | G404: 2079900 | H404: 0 | I404: 0 | J404: 87 | K404: 87 | L404: 88 | M404: 88 | N404: 86 | T404: 187 | U404: 62 | V404: -0.53475936 | W404: -0.34090909 | X404: IDR | Y404: 2026-09-04T08:18:43
A405: IKBI | B405: Sumi Indo Kabel Tbk. | C405: 1991-01-21 00:00:00 | D405: 1.224e+09 | E405: PENGEMBANGAN | F405: 670 | G405: 1808000 | H405: 20 | I405: 3.076923 | J405: 650 | K405: 670 | L405: 685 | M405: 655 | N405: 655 | T405: 715 | U405: 438 | V405: -0.062937063 | W405: 0.41350211 | X405: IDR | Y405: 2026-09-04T08:18:43
A406: IKPM | B406: Ikapharmindo Putramas Tbk. | C406: 2023-11-08 00:00:00 | D406: 1.6846625e+09 | E406: PENGEMBANGAN | F406: 195 | G406: 36100 | H406: -3 | I406: -1.5151515 | J406: 198 | K406: 195 | L406: 199 | M406: 199 | N406: 194 | T406: 340 | U406: 167 | V406: -0.42647059 | W406: 0 | X406: IDR | Y406: 2026-09-04T08:18:43
A407: IMAS | B407: Indomobil Sukses Internasional Tbk. | C407: 1993-11-15 00:00:00 | D407: 3.9942909e+09 | E407: UTAMA | F407: 865 | G407: 161000 | H407: 5 | I407: 0.58139535 | J407: 860 | K407: 865 | L407: 880 | M407: 860 | N407: 850 | T407: 1465 | U407: 750 | V407: -0.40955631 | W407: -0.19534884 | X407: IDR | Y407: 2026-09-04T08:18:43
A408: IMJS | B408: Indomobil Multi Jasa Tbk. | C408: 10 Des 2013 | D408: 1.0849262e+10 | E408: PENGEMBANGAN | F408: 165 | G408: 635700 | H408: 3 | I408: 1.8518519 | J408: 162 | K408: 165 | L408: 166 | M408: 162 | N408: 162 | T408: 490.958 | U408: 118 | V408: -0.66392237 | W408: -0.38432836 | X408: IDR | Y408: 2026-09-04T08:18:43
A409: IMPC | B409: Impack Pratama Industri Tbk. | C409: 17 Des 2014 | D409: 5.4685278e+10 | E409: UTAMA | F409: 1595 | G409: 2589500 | H409: 0 | I409: 0 | J409: 1595 | K409: 1595 | L409: 1610 | M409: 1600 | N409: 1595 | T409: 4170 | U409: 660 | V409: -0.617506 | W409: 1.4166667 | X409: IDR | Y409: 2026-09-04T08:18:43
A410: INAF | B410: Indofarma Tbk. | C410: 2001-04-17 00:00:00 | D410: 3.0992677e+09 | E410: PEMANTAUAN KHUSUS | F410: 126 | G410: 0 | H410: 0 | I410: 0 | J410: 126 | K410: 126 | L410: 126 | M410: 0 | N410: 126 | T410: 126 | U410: 126 | V410: 0 | W410: 0 | X410: IDR | Y410: 2026-09-04T08:18:43
A411: INAI | B411: Indal Aluminium Industry Tbk. | C411: 05 Des 1994 | D411: 6.3359999e+08 | E411: PENGEMBANGAN | F411: 179 | G411: 722000 | H411: -1 | I411: -0.55555557 | J411: 180 | K411: 179 | L411: 184 | M411: 182 | N411: 174 | T411: 312 | U411: 118 | V411: -0.42628205 | W411: 0.12578616 | X411: IDR | Y411: 2026-09-04T08:18:43
A412: INCF | B412: Indo Komoditi Korpora Tbk. | C412: 2016-09-06 00:00:00 | D412: 1.4383704e+09 | E412: PEMANTAUAN KHUSUS | F412: 50 | G412: 66300 | H412: 0 | I412: 0 | J412: 50 | K412: 50 | L412: 50 | M412: 50 | N412: 50 | T412: 84 | U412: 24 | V412: -0.4047619 | W412: 0.78571429 | X412: IDR | Y412: 2026-09-04T08:18:43
A413: INCI | B413: Intanwijaya Internasional Tbk. | C413: 1990-07-24 00:00:00 | D413: 2.0765662e+08 | E413: PENGEMBANGAN | F413: 680 | G413: 33700 | H413: 5 | I413: 0.74074073 | J413: 675 | K413: 680 | L413: 680 | M413: 675 | N413: 660 | T413: 920 | U413: 550 | V413: -0.26086957 | W413: 0.14285714 | X413: IDR | Y413: 2026-09-04T08:18:43
A414: INCO | B414: Vale Indonesia Tbk. | C414: 16 Mei 1990 | D414: 1.0539784e+10 | E414: UTAMA | F414: 5425 | G414: 2843600 | H414: 25 | I414: 0.46296297 | J414: 5400 | K414: 5425 | L414: 5500 | M414: 5450 | N414: 5400 | T414: 7900 | U414: 3530 | V414: -0.31329114 | W414: 0.38392857 | X414: IDR | Y414: 2026-09-04T08:18:43
... A470: KBLV | B470: First Media Tbk. | C470: 2000-02-25 00:00:00 | D470: 1.742168e+09 | E470: PENGEMBANGAN | F470: 159 | G470: 200001600 | H470: 2 | I470: 1.2820513 | J470: 157 | K470: 159 | L470: 172 | M470: 162 | N470: 153 | T470: 334 | U470: 56 | V470: -0.5239521 | W470: 0.67368421 | X470: IDR | Y470: 2026-09-04T08:18:43
A471: KBRI | B471: Kertas Basuki Rachmat Indonesia Tbk. | C471: 2008-07-11 00:00:00 | D471: 8.688e+09 | E471: PEMANTAUAN KHUSUS | F471: 50 | H471: 0 | I471: 0 | J471: 50 | K471: 50 | T471: 50 | U471: 50 | V471: 0 | W471: 0 | X471: IDR | Y471: 2026-09-04T08:18:43
A472: KDSI | B472: Kedawung Setia Industrial Tbk. | C472: 1996-07-29 00:00:00 | D472: 1.62e+09 | E472: PENGEMBANGAN | F472: 456 | G472: 3000 | H472: -2 | I472: -0.43668123 | J472: 458 | K472: 456 | L472: 458 | M472: 458 | N472: 456 | T472: 550 | U472: 392 | V472: -0.17090909 | W472: -0.046025105 | X472: IDR | Y472: 2026-09-04T08:18:43
...

Sheet RAW_key_statistics
A1: Ticker | B1: Current PE Ratio (Annualised) | C1: Current PE Ratio (TTM) | D1: Forward PE Ratio | E1: IHSG PE Ratio TTM (Median) | F1: Earnings Yield (TTM) | G1: Current Price to Sales(TTM) | H1: Current Price to Book Value | I1: Current Price To Cashflow (TTM) | J1: Current Price To Free Cashflow (TTM) | K1: EV to EBIT (TTM) | L1: EV to EBITDA (TTM) | M1: PEG Ratio | N1: PEG Ratio (3yr) | O1: PEG (Forward) | P1: Current EPS (TTM) | Q1: Current EPS (Annualised) | R1: Revenue Per Share (TTM) | S1: Cash Per Share (Quarter) | T1: Current Book Value Per Share | U1: Free Cashflow Per Share (TTM) | V1: Current Ratio (Quarter) | W1: Quick Ratio (Quarter) | X1: Debt to Equity Ratio (Quarter) | Y1: LT Debt/Equity (Quarter) | Z1: Total Liabilities/Equity (Quarter) | AA1: Total Debt/Total Assets (Quarter) | AB1: Financial Leverage (Quarter) | AC1: Interest Coverage (TTM) | AD1: Free cash flow (Quarter) | AE1: Altman Z-Score (Modified) | AF1: Return on Assets (TTM) | AG1: Return on Equity (TTM) | AH1: Return on Capital Employed (TTM) | AI1: Return On Invested Capital (TTM) | AJ1: Days Sales Outstanding (Quarter) | AK1: Days Inventory (Quarter) | AL1: Days Payables Outstanding (Quarter) | AM1: Cash Conversion Cycle (Quarter) | AN1: Receivables Turnover (Quarter) | AO1: Asset Turnover (TTM) | AP1: Inventory Turnover (TTM) | AQ1: Gross Profit Margin (Quarter) | AR1: Operating Profit Margin (Quarter) | AS1: Net Profit Margin (Quarter) | AT1: Revenue (Quarter YoY Growth) | AU1: Gross Profit (Quarter YoY Growth) | AV1: Net Income (Quarter YoY Growth) | AW1: Dividend | AX1: Dividend (TTM) | AY1: Payout Ratio | AZ1: Dividend Yield | BA1: Latest Dividend Ex-Date | BB1: Piotroski F-Score | BC1: EPS Rating | BD1: Relative Strength Rating | BE1: Rank (Market Cap) | BF1: Rank (Current PE Ratio TTM) | BG1: Rank (Earnings Yield) | BH1: Rank (P/S) | BI1: Rank (P/B) | BJ1: Rank (Near 52 Weeks High) | BK1: Revenue (TTM) | BL1: Gross Profit (TTM) | BM1: EBITDA (TTM) | BN1: Net Income (TTM) | BO1: Cash (Quarter) | BP1: Total Assets (Quarter) | BQ1: Total Liabilities (Quarter) | BR1: Working Capital (Quarter) | BS1: Market Cap | BT1: Enterprise Value | BU1: Current Share Outstanding | BV1: Total Equity | BW1: Total Debt (Quarter) | BX1: Net Debt (Quarter) | BY1: Current Assets (Quarter) | BZ1: Current Liabilities (Quarter) | CA1: EBIT (TTM) | CB1: Operating Cash Flow (TTM) | CC1: Capital expenditure (TTM) | CD1: Free cash flow (TTM) | CE1: Inventory (Quarter) | CF1: Retained Earnings (Quarter) | CG1: Beta | CH1: Earnings Yield Greenblatt (EBIT/EV) | CI1: ROC Greenblatt | CJ1: Acquirers Multiple (EV/EBIT) | CK1: FCF Yield (TTM) | CL1: NCAV | CM1: NCAV per Share | CN1: Net-Net Pass | CO1: Normalised EBIT (5Y) | CP1: Normalised EBIT Margin | CQ1: Normalised/Trailing EBIT | CR1: EPV per Share | CS1: Working Capital Intensity | CT1: Implied Terminal Multiple | CU1: Revenue CAGR 3Y | CV1: Revenue CAGR 5Y | CW1: EPS CAGR 3Y | CX1: Net Income CAGR 3Y | CY1: Gross Margin 5Y Avg | CZ1: EBIT Margin 5Y Avg | DA1: ROE 5Y Avg | DB1: Revenue Volatility 5Y | DC1: Quarters of History | DD1: Years of Annual History | DE1: F: ROA Positive | DF1: F: CFO Positive | DG1: F: ROA Improving | DH1: F: Accruals | DI1: F: Leverage Falling | DJ1: F: Current Ratio Improving | DK1: F: No Dilution | DL1: F: Gross Margin Improving | DM1: F: Asset Turnover Improving | DN1: F-Score Basis | DO1: 52W High | DP1: 52W Low | DQ1: Pct From 52W High | DR1: 1Y Price Change | DS1: Price CAGR 3Y | DT1: Price CAGR 5Y | DU1: Price Percentile 10Y | DV1: Max Drawdown 10Y | DW1: Months of Price History | DX1: Latest Filing Date | DY1: Quarters Stale | DZ1: Statement Currency | EA1: FX Rate Applied | EB1: Share Count Source | EC1: Reported/Implied Shares | ED1: Minority Interest | EE1: Data Source | EF1: Fetched At
